Workbook

Sheet Dashboard
A1: VUSLAT RECRUITMENT COMPANY | EXECUTIVE DASHBOARD
A2: Every figure below is a live formula. Add or edit rows on the operational sheets and this page updates itself - press F9 if Excel is in manual calculation mode. The records currently loaded are sample data - see section 4 of the Settings sheet before going live.
B3: =" Reporting currency: TJS (Somoni) | Report generated: "&TEXT(TODAY(),"DD MMMM YYYY")&" | Customers in pipeline: "&COUNTA(Customers!$A$4:$A$1003)&" | Active campaigns: "&COUNTIF('Marketing & Advertising'!$R$4:$R$1003,"Active") -> Reporting currency: TJS (Somoni) | Report generated: 30 July 2026 | Customers in pipeline: 12 | Active campaigns: 3
B5: OPERATIONAL KEY PERFORMANCE INDICATORS
B7: TOTAL LEADS | E7: CUSTOMERS CONTACTED | H7: CONSULTATION APPOINTMENTS | K7: CONSULTATIONS COMPLETED | N7: CONTRACTS SIGNED | Q7: ACTIVE CUSTOMERS
B8: =COUNTA('Lead Management'!$A$4:$A$1003) -> 30 | E8: =COUNT('Lead Management'!$S$4:$S$1003) -> 26 | H8: =COUNTA(Consultation!$A$4:$A$1003) -> 18 | K8: =COUNTIF(Consultation!$J$4:$J$1003,"Completed") -> 14 | N8: =COUNTA(Contracts!$A$4:$A$1003) -> 12 | Q8: =COUNTIF(Customers!$R$4:$R$1003,"Active") -> 9
B11: VISA APPLICATIONS SUBMITTED | E11: APPROVED VISAS | H11: REJECTED VISAS | K11: WORKERS SENT TO EUROPE | N11: PENDING CASES | Q11: COMPLETED CASES
B12: =COUNTIF('Process Tracking'!$AL$5:$AL$1003,"Completed") -> 8 | E12: =COUNTIF('Process Tracking'!$AT$5:$AT$1003,"Completed") -> 5 | H12: =COUNTIF('Process Tracking'!$AX$5:$AX$1003,"Completed") -> 1 | K12: =COUNTIF('Process Tracking'!$BF$5:$BF$1003,"Completed") -> 3 | N12: =COUNTA(Customers!$A$4:$A$1003)-COUNTIF(Customers!$R$4:$R$1003,"Completed")-COUNTIF(Customers!$R$4:$R$1003,"Cancelled") -> 9 | Q12: =COUNTIF('Process Tracking'!$BJ$5:$BJ$1003,"Completed") -> 2
B15: FINANCIAL KEY PERFORMANCE INDICATORS (all amounts in TJS)
B17: TODAY'S REVENUE | E17: MONTHLY REVENUE | H17: TOTAL PAYMENTS COLLECTED | K17: CONSULTATION FEES | N17: TOTAL REVENUE | Q17: OUTSTANDING PAYMENTS
B18: =SUMIFS(Finance!$E$4:$E$1003,Finance!$F$4:$F$1003,TODAY(),Finance!$J$4:$J$1003,"Paid") -> 9300 | E18: =SUMIFS(Finance!$E$4:$E$1003,Finance!$F$4:$F$1003,">="&EOMONTH(TODAY(),-1)+1,Finance!$F$4:$F$1003,"<="&EOMONTH(TODAY(),0),Finance!$J$4:$J$1003,"Paid") -> 9300 | H18: =Finance!$AA$4 -> 225250 | K18: =Finance!$AA$5 -> 700 | N18: =Finance!$AA$6 -> 225950 | Q18: =Finance!$AA$9 -> 12250
B21: ACCOUNTS RECEIVABLE | E21: TOTAL CONTRACT VALUE | H21: COMPANY EXPENSES | K21: NET PROFIT | N21: PROFIT MARGIN | Q21: COLLECTION RATE
B22: =Finance!$AA$10 -> 63750 | E22: =Finance!$AA$11 -> 289000 | H22: =Finance!$AA$18 -> 192300 | K22: =Finance!$AA$20 -> 33650 | N22: =Finance!$AA$21 -> 0.14892675 | Q22: =Finance!$AA$22 -> 0.77941176
B25: PERFORMANCE CHARTS

Sheet Lead Management
A1: VUSLAT RECRUITMENT COMPANY | LEAD MANAGEMENT
A2: One row per potential customer. Grey columns (I, U, V, W) are calculated - do not type in them. Use the drop-downs in columns G, K, L, M, N, O, Q, R.
A3: Lead ID | B3: Full Name | C3: Phone Number | D3: WhatsApp | E3: Email | F3: Passport Number | G3: Nationality | H3: Date of Birth | I3: Age | J3: Profession | K3: Education | L3: Russian Language Level | M3: English Language Level | N3: Preferred European Country | O3: Lead Source | P3: Registration Date | Q3: Assigned Sales Manager | R3: Lead Status | S3: Last Contact Date | T3: Next Follow-up Date | U3: Days Since Registration | V3: Consultation Booked | W3: Converted to Customer | X3: Notes
A4: LD-001 | B4: Firdavs Rahmonov | C4: +992 91 203 1137 | D4: +992 91 203 1137 | E4: firdavs1@mail.tj | F4: A4101373 | G4: Tajik | H4: 33767 | I4: =IF($H4="","",DATEDIF($H4,TODAY(),"Y")) -> 34 | J4: Truck Driver (CE) | K4: Vocational | L4: Intermediate | M4: Basic | N4: Poland | O4: Instagram | P4: 46030 | Q4: Nilufar Karimova | R4: Consultation Completed | S4: 46032 | U4: =IF($P4="","",TODAY()-$P4) -> 203 | V4: =IF($A4="","",IF(COUNTIF(Consultation!$B$4:$B$1003,$A4)>0,"Yes","No")) -> Yes | W4: =IF($A4="","",IF(COUNTIF(Customers!$B$4:$B$1003,$A4)>0,"Yes","No")) -> Yes | X4: Certified welder, 6 years experience in Russia.
A5: LD-002 | B5: Nilufar Sharipova | C5: +992 92 206 1274 | D5: +992 92 206 1274 | E5: nilufar2@mail.tj | F5: A4102746 | G5: Tajik | H5: 36487 | I5: =IF($H5="","",DATEDIF($H5,TODAY(),"Y")) -> 26 | J5: Nurse | K5: Bachelor | L5: Advanced | M5: Intermediate | N5: Germany | O5: Instagram | P5: 46037 | Q5: Jamshed Sattorov | R5: Consultation Completed | S5: 46039 | U5: =IF($P5="","",TODAY()-$P5) -> 196 | V5: =IF($A5="","",IF(COUNTIF(Consultation!$B$4:$B$1003,$A5)>0,"Yes","No")) -> Yes | W5: =IF($A5="","",IF(COUNTIF(Customers!$B$4:$B$1003,$A5)>0,"Yes","No")) -> Yes
A6: LD-003 | B6: Jamshed Karimov | C6: +992 93 209 1411 | D6: +992 93 209 1411 | E6: jamshed3@mail.tj | F6: A4104119 | G6: Tajik | H6: 32240 | I6: =IF($H6="","",DATEDIF($H6,TODAY(),"Y")) -> 38 | J6: Seamstress | K6: Master | L6: Fluent | M6: Advanced | N6: Czech Republic | O6: Facebook | P6: 46058 | Q6: Dilnoza Aliyeva | R6: Consultation Completed | S6: 46060 | U6: =IF($P6="","",TODAY()-$P6) -> 175 | V6: =IF($A6="","",IF(COUNTIF(Consultation!$B$4:$B$1003,$A6)>0,"Yes","No")) -> Yes | W6: =IF($A6="","",IF(COUNTIF(Customers!$B$4:$B$1003,$A6)>0,"Yes","No")) -> Yes | X6: Has valid Schengen refusal history - checked, cleared.
A7: LD-004 | B7: Zarina Nazriyeva | C7: +992 94 212 1548 | D7: +992 94 212 1548 | E7: zarina4@mail.tj | F7: A4105492 | G7: Tajik | H7: 34960 | I7: =IF($H7="","",DATEDIF($H7,TODAY(),"Y")) -> 30 | J7: Forklift Operator | K7: Secondary | L7: Basic | M7: None | N7: Poland | O7: Instagram | P7: 46065 | Q7: Nilufar Karimova | R7: Consultation Completed | S7: 46067 | U7: =IF($P7="","",TODAY()-$P7) -> 168 | V7: =IF($A7="","",IF(COUNTIF(Consultation!$B$4:$B$1003,$A7)>0,"Yes","No")) -> Yes | W7: =IF($A7="","",IF(COUNTIF(Customers!$B$4:$B$1003,$A7)>0,"Yes","No")) -> Yes
A8: LD-005 | B8: Bakhtiyor Umarov | C8: +992 95 215 1685 | D8: +992 95 215 1685 | E8: bakhtiyor5@mail.tj | F8: A4106865 | G8: Tajik | H8: 37289 | I8: =IF($H8="","",DATEDIF($H8,TODAY(),"Y")) -> 24 | J8: Welder | K8: Vocational | L8: Intermediate | M8: Basic | N8: Slovakia | O8: Website | P8: 46044 | Q8: Jamshed Sattorov | R8: Consultation Completed | S8: 46046 | U8: =IF($P8="","",TODAY()-$P8) -> 189 | V8: =IF($A8="","",IF(COUNTIF(Consultation!$B$4:$B$1003,$A8)>0,"Yes","No")) -> Yes | W8: =IF($A8="","",IF(COUNTIF(Customers!$B$4:$B$1003,$A8)>0,"Yes","No")) -> Yes | X8: Driving licence category CE, ready to travel immediately.
A9: LD-006 | B9: Manizha Qodirova | C9: +992 96 218 1822 | D9: +992 96 218 1822 | E9: manizha6@mail.tj | F9: A4108238 | G9: Tajik | H9: 33432 | I9: =IF($H9="","",DATEDIF($H9,TODAY(),"Y")) -> 35 | J9: Truck Driver (CE) | K9: Bachelor | L9: Advanced | M9: Intermediate | N9: Germany | O9: Referral | P9: 46071 | Q9: Dilnoza Aliyeva | R9: Consultation Completed | S9: 46073 | U9: =IF($P9="","",TODAY()-$P9) -> 162 | V9: =IF($A9="","",IF(COUNTIF(Consultation!$B$4:$B$1003,$A9)>0,"Yes","No")) -> Yes | W9: =IF($A9="","",IF(COUNTIF(Customers!$B$4:$B$1003,$A9)>0,"Yes","No")) -> Yes
A10: LD-007 | B10: Rustam Sattorov | C10: +992 97 221 1959 | D10: +992 97 221 1959 | E10: rustam7@mail.tj | F10: A4109611 | G10: Tajik | H10: 36153 | I10: =IF($H10="","",DATEDIF($H10,TODAY(),"Y")) -> 27 | J10: Nurse | K10: Master | L10: Fluent | M10: Advanced | N10: Poland | O10: Instagram | P10: 46085 | Q10: Nilufar Karimova | R10: Consultation Completed | S10: 46087 | U10: =IF($P10="","",TODAY()-$P10) -> 148 | V10: =IF($A10="","",IF(COUNTIF(Consultation!$B$4:$B$1003,$A10)>0,"Yes","No")) -> Yes | W10: =IF($A10="","",IF(COUNTIF(Customers!$B$4:$B$1003,$A10)>0,"Yes","No")) -> Yes
A11: LD-008 | B11: Dilnoza Aliyeva | C11: +992 90 224 2096 | D11: +992 90 224 2096 | E11: dilnoza8@mail.tj | F11: A4110984 | G11: Tajik | H11: 31905 | I11: =IF($H11="","",DATEDIF($H11,TODAY(),"Y")) -> 39 | J11: Seamstress | K11: Secondary | L11: Basic | M11: None | N11: Lithuania | O11: Instagram | P11: 46092 | Q11: Jamshed Sattorov | R11: Consultation Completed | S11: 46094 | U11: =IF($P11="","",TODAY()-$P11) -> 141 | V11: =IF($A11="","",IF(COUNTIF(Consultation!$B$4:$B$1003,$A11)>0,"Yes","No")) -> Yes | W11: =IF($A11="","",IF(COUNTIF(Customers!$B$4:$B$1003,$A11)>0,"Yes","No")) -> Yes | X11: Wants family reunification later, informed about the procedure.
A12: LD-009 | B12: Sherali Yusupov | C12: +992 91 227 2233 | D12: +992 91 227 2233 | E12: sherali9@mail.tj | F12: A4112357 | G12: Uzbek | H12: 34626 | I12: =IF($H12="","",DATEDIF($H12,TODAY(),"Y")) -> 31 | J12: Forklift Operator | K12: Vocational | L12: Intermediate | M12: Basic | N12: Czech Republic | O12: Facebook | P12: 46099 | Q12: Dilnoza Aliyeva | R12: Consultation Completed | S12: 46101 | U12: =IF($P12="","",TODAY()-$P12) -> 134 | V12: =IF($A12="","",IF(COUNTIF(Consultation!$B$4:$B$1003,$A12)>0,"Yes","No")) -> Yes | W12: =IF($A12="","",IF(COUNTIF(Customers!$B$4:$B$1003,$A12)>0,"Yes","No")) -> Yes
A13: LD-010 | B13: Malika Ismoilova | C13: +992 92 230 2370 | D13: +992 92 230 2370 | E13: malika10@mail.tj | F13: A4113730 | G13: Tajik | H13: 36953 | I13: =IF($H13="","",DATEDIF($H13,TODAY(),"Y")) -> 25 | J13: Welder | K13: Bachelor | L13: Advanced | M13: Intermediate | N13: Poland | O13: Instagram | P13: 46114 | Q13: Nilufar Karimova | R13: Consultation Completed | S13: 46116 | U13: =IF($P13="","",TODAY()-$P13) -> 119 | V13: =IF($A13="","",IF(COUNTIF(Consultation!$B$4:$B$1003,$A13)>0,"Yes","No")) -> Yes | W13: =IF($A13="","",IF(COUNTIF(Customers!$B$4:$B$1003,$A13)>0,"Yes","No")) -> Yes
A14: LD-011 | B14: Farrukh Davlatov | C14: +992 93 233 2507 | D14: +992 93 233 2507 | E14: farrukh11@mail.tj | F14: A4115103 | G14: Tajik | H14: 33099 | I14: =IF($H14="","",DATEDIF($H14,TODAY(),"Y")) -> 35 | J14: Truck Driver (CE) | K14: Master | L14: Fluent | M14: Advanced | N14: Hungary | O14: Website | P14: 46106 | Q14: Jamshed Sattorov | R14: Consultation Completed | S14: 46108 | U14: =IF($P14="","",TODAY()-$P14) -> 127 | V14: =IF($A14="","",IF(COUNTIF(Consultation!$B$4:$B$1003,$A14)>0,"Yes","No")) -> Yes | W14: =IF($A14="","",IF(COUNTIF(Customers!$B$4:$B$1003,$A14)>0,"Yes","No")) -> Yes
A15: LD-012 | B15: Gulnora Safarova | C15: +992 94 236 2644 | D15: +992 94 236 2644 | E15: gulnora12@mail.tj | F15: A4116476 | G15: Tajik | H15: 35455 | I15: =IF($H15="","",DATEDIF($H15,TODAY(),"Y")) -> 29 | J15: Nurse | K15: Secondary | L15: Basic | M15: None | N15: Romania | O15: Referral | P15: 46121 | Q15: Dilnoza Aliyeva | R15: Consultation Completed | S15: 46123 | U15: =IF($P15="","",TODAY()-$P15) -> 112 | V15: =IF($A15="","",IF(COUNTIF(Consultation!$B$4:$B$1003,$A15)>0,"Yes","No")) -> Yes | W15: =IF($A15="","",IF(COUNTIF(Customers!$B$4:$B$1003,$A15)>0,"Yes","No")) -> Yes | X15: Referred by CUS-006. Speaks basic Polish.
A16: LD-013 | B16: Umed Nazriev | C16: +992 95 239 2781 | D16: +992 95 239 2781 | E16: umed13@mail.tj | F16: A4117849 | G16: Tajik | H16: 31572 | I16: =IF($H16="","",DATEDIF($H16,TODAY(),"Y")) -> 40 | J16: Seamstress | K16: Vocational | L16: Intermediate | M16: Basic | N16: Germany | O16: Instagram | P16: 46128 | Q16: Nilufar Karimova | R16: Consultation Completed | S16: 46130 | U16: =IF($P16="","",TODAY()-$P16) -> 105 | V16: =IF($A16="","",IF(COUNTIF(Consultation!$B$4:$B$1003,$A16)>0,"Yes","No")) -> Yes | W16: =IF($A16="","",IF(COUNTIF(Customers!$B$4:$B$1003,$A16)>0,"Yes","No")) -> No
A17: LD-014 | B17: Shahnoza Rajabova | C17: +992 96 242 2918 | D17: +992 96 242 2918 | E17: shahnoza14@mail.tj | F17: A4119222 | G17: Tajik | H17: 34293 | I17: =IF($H17="","",DATEDIF($H17,TODAY(),"Y")) -> 32 | J17: Forklift Operator | K17: Bachelor | L17: Advanced | M17: Intermediate | N17: Poland | O17: Facebook | P17: 46115 | Q17: Jamshed Sattorov | R17: Consultation Completed | S17: 46117 | U17: =IF($P17="","",TODAY()-$P17) -> 118 | V17: =IF($A17="","",IF(COUNTIF(Consultation!$B$4:$B$1003,$A17)>0,"Yes","No")) -> Yes | W17: =IF($A17="","",IF(COUNTIF(Customers!$B$4:$B$1003,$A17)>0,"Yes","No")) -> No
A18: LD-015 | B18: Iskandar Mirzoev | C18: +992 97 245 3055 | D18: +992 97 245 3055 | E18: iskandar15@mail.tj | F18: A4120595 | G18: Tajik | H18: 36620 | I18: =IF($H18="","",DATEDIF($H18,TODAY(),"Y")) -> 26 | J18: Welder | K18: Master | L18: Fluent | M18: Advanced | N18: Poland | O18: Instagram | P18: 46149 | Q18: Dilnoza Aliyeva | R18: Consultation Scheduled | S18: 46151 | U18: =IF($P18="","",TODAY()-$P18) -> 84 | V18: =IF($A18="","",IF(COUNTIF(Consultation!$B$4:$B$1003,$A18)>0,"Yes","No")) -> Yes | W18: =IF($A18="","",IF(COUNTIF(Customers!$B$4:$B$1003,$A18)>0,"Yes","No")) -> No
A19: LD-016 | B19: Sitora Hakimova | C19: +992 90 248 3192 | D19: +992 90 248 3192 | E19: sitora16@mail.tj | F19: A4121968 | G19: Tajik | H19: 32766 | I19: =IF($H19="","",DATEDIF($H19,TODAY(),"Y")) -> 36 | J19: Truck Driver (CE) | K19: Secondary | L19: Basic | M19: None | N19: Czech Republic | O19: Instagram | P19: 46156 | Q19: Nilufar Karimova | R19: Consultation Scheduled | S19: 46158 | U19: =IF($P19="","",TODAY()-$P19) -> 77 | V19: =IF($A19="","",IF(COUNTIF(Consultation!$B$4:$B$1003,$A19)>0,"Yes","No")) -> Yes | W19: =IF($A19="","",IF(COUNTIF(Customers!$B$4:$B$1003,$A19)>0,"Yes","No")) -> No
A20: LD-017 | B20: Daler Ashurov | C20: +992 91 251 3329 | D20: +992 91 251 3329 | E20: daler17@mail.tj | F20: A4123341 | G20: Tajik | H20: 35121 | I20: =IF($H20="","",DATEDIF($H20,TODAY(),"Y")) -> 30 | J20: Nurse | K20: Vocational | L20: Intermediate | M20: Basic | N20: Slovakia | O20: Walk-in | P20: 46162 | Q20: Jamshed Sattorov | R20: Follow-up Required | S20: 46164 | T20: 46243 | U20: =IF($P20="","",TODAY()-$P20) -> 71 | V20: =IF($A20="","",IF(COUNTIF(Consultation!$B$4:$B$1003,$A20)>0,"Yes","No")) -> Yes | W20: =IF($A20="","",IF(COUNTIF(Customers!$B$4:$B$1003,$A20)>0,"Yes","No")) -> No | X20: Did not attend the consultation appointment - reschedule.
A21: LD-018 | B21: Nasiba Kholova | C21: +992 92 254 3466 | D21: +992 92 254 3466 | E21: nasiba18@mail.tj | F21: A4124714 | G21: Uzbek | H21: 31238 | I21: =IF($H21="","",DATEDIF($H21,TODAY(),"Y")) -> 41 | J21: Seamstress | K21: Bachelor | L21: Advanced | M21: Intermediate | N21: Germany | O21: Website | P21: 46170 | Q21: Dilnoza Aliyeva | R21: Not Interested | S21: 46172 | U21: =IF($P21="","",TODAY()-$P21) -> 63 | V21: =IF($A21="","",IF(COUNTIF(Consultation!$B$4:$B$1003,$A21)>0,"Yes","No")) -> Yes | W21: =IF($A21="","",IF(COUNTIF(Customers!$B$4:$B$1003,$A21)>0,"Yes","No")) -> No | X21: Decided to travel to Russia instead. Archived.
A22: LD-019 | B22: Parviz Odinaev | C22: +992 93 257 3603 | D22: +992 93 257 3603 | E22: parviz19@mail.tj | F22: A4126087 | G22: Tajik | H22: 33959 | I22: =IF($H22="","",DATEDIF($H22,TODAY(),"Y")) -> 33 | J22: Forklift Operator | K22: Master | L22: Fluent | M22: Advanced | N22: Poland | O22: Instagram | P22: 46176 | Q22: Nilufar Karimova | R22: New Lead | U22: =IF($P22="","",TODAY()-$P22) -> 57 | V22: =IF($A22="","",IF(COUNTIF(Consultation!$B$4:$B$1003,$A22)>0,"Yes","No")) -> No | W22: =IF($A22="","",IF(COUNTIF(Customers!$B$4:$B$1003,$A22)>0,"Yes","No")) -> No
A23: LD-020 | B23: Mavluda Ergasheva | C23: +992 94 260 3740 | D23: +992 94 260 3740 | E23: mavluda20@mail.tj | F23: A4127460 | G23: Tajik | H23: 36285 | I23: =IF($H23="","",DATEDIF($H23,TODAY(),"Y")) -> 27 | J23: Welder | K23: Secondary | L23: Basic | M23: None | N23: Lithuania | O23: Instagram | P23: 46183 | Q23: Jamshed Sattorov | R23: Contacted | S23: 46185 | T23: 46236 | U23: =IF($P23="","",TODAY()-$P23) -> 50 | V23: =IF($A23="","",IF(COUNTIF(Consultation!$B$4:$B$1003,$A23)>0,"Yes","No")) -> No | W23: =IF($A23="","",IF(COUNTIF(Customers!$B$4:$B$1003,$A23)>0,"Yes","No")) -> No
A24: LD-021 | B24: Sorbon Latifov | C24: +992 95 263 3877 | D24: +992 95 263 3877 | E24: sorbon21@mail.tj | F24: A4128833 | G24: Tajik | H24: 32432 | I24: =IF($H24="","",DATEDIF($H24,TODAY(),"Y")) -> 37 | J24: Truck Driver (CE) | K24: Vocational | L24: Intermediate | M24: Basic | N24: Germany | O24: Facebook | P24: 46188 | Q24: Dilnoza Aliyeva | R24: Contacted | S24: 46190 | T24: 46237 | U24: =IF($P24="","",TODAY()-$P24) -> 45 | V24: =IF($A24="","",IF(COUNTIF(Consultation!$B$4:$B$1003,$A24)>0,"Yes","No")) -> No | W24: =IF($A24="","",IF(COUNTIF(Customers!$B$4:$B$1003,$A24)>0,"Yes","No")) -> No
A25: LD-022 | B25: Zulfiya Muminova | C25: +992 96 266 4014 | D25: +992 96 266 4014 | E25: zulfiya22@mail.tj | F25: A4130206 | G25: Tajik | H25: 34785 | I25: =IF($H25="","",DATEDIF($H25,TODAY(),"Y")) -> 31 | J25: Nurse | K25: Bachelor | L25: Advanced | M25: Intermediate | N25: Poland | O25: Referral | P25: 46193 | Q25: Nilufar Karimova | R25: No Answer | S25: 46195 | T25: 46238 | U25: =IF($P25="","",TODAY()-$P25) -> 40 | V25: =IF($A25="","",IF(COUNTIF(Consultation!$B$4:$B$1003,$A25)>0,"Yes","No")) -> No | W25: =IF($A25="","",IF(COUNTIF(Customers!$B$4:$B$1003,$A25)>0,"Yes","No")) -> No | X25: Requested a call back after Ramadan.
A26: LD-023 | B26: Amirbek Turaev | C26: +992 97 269 4151 | D26: +992 97 269 4151 | E26: amirbek23@mail.tj | F26: A4131579 | G26: Tajik | H26: 37479 | I26: =IF($H26="","",DATEDIF($H26,TODAY(),"Y")) -> 23 | J26: Seamstress | K26: Master | L26: Fluent | M26: Advanced | N26: Czech Republic | O26: Instagram | P26: 46198 | Q26: Jamshed Sattorov | R26: Follow-up Required | S26: 46200 | T26: 46239 | U26: =IF($P26="","",TODAY()-$P26) -> 35 | V26: =IF($A26="","",IF(COUNTIF(Consultation!$B$4:$B$1003,$A26)>0,"Yes","No")) -> No | W26: =IF($A26="","",IF(COUNTIF(Customers!$B$4:$B$1003,$A26)>0,"Yes","No")) -> No
A27: LD-024 | B27: Nigina Saidova | C27: +992 90 272 4288 | D27: +992 90 272 4288 | E27: nigina24@mail.tj | F27: A4132952 | G27: Tajik | H27: 33260 | I27: =IF($H27="","",DATEDIF($H27,TODAY(),"Y")) -> 35 | J27: Forklift Operator | K27: Secondary | L27: Basic | M27: None | N27: Netherlands | O27: Website | P27: 46204 | Q27: Dilnoza Aliyeva | R27: New Lead | U27: =IF($P27="","",TODAY()-$P27) -> 29 | V27: =IF($A27="","",IF(COUNTIF(Consultation!$B$4:$B$1003,$A27)>0,"Yes","No")) -> No | W27: =IF($A27="","",IF(COUNTIF(Customers!$B$4:$B$1003,$A27)>0,"Yes","No")) -> No
A28: LD-025 | B28: Behruz Rahimov | C28: +992 91 275 4425 | D28: +992 91 275 4425 | E28: behruz25@mail.tj | F28: A4134325 | G28: Tajik | H28: 35952 | I28: =IF($H28="","",DATEDIF($H28,TODAY(),"Y")) -> 28 | J28: Welder | K28: Vocational | L28: Intermediate | M28: Basic | N28: Poland | O28: Instagram | P28: 46209 | Q28: Nilufar Karimova | R28: Contacted | S28: 46211 | T28: 46241 | U28: =IF($P28="","",TODAY()-$P28) -> 24 | V28: =IF($A28="","",IF(COUNTIF(Consultation!$B$4:$B$1003,$A28)>0,"Yes","No")) -> No | W28: =IF($A28="","",IF(COUNTIF(Customers!$B$4:$B$1003,$A28)>0,"Yes","No")) -> No
A29: LD-026 | B29: Mehrangez Boboeva | C29: +992 92 278 4562 | D29: +992 92 278 4562 | E29: mehrangez26@mail.tj | F29: A4135698 | G29: Tajik | H29: 32098 | I29: =IF($H29="","",DATEDIF($H29,TODAY(),"Y")) -> 38 | J29: Truck Driver (CE) | K29: Bachelor | L29: Advanced | M29: Intermediate | N29: Portugal | O29: Walk-in | P29: 46213 | Q29: Jamshed Sattorov | R29: On Hold | S29: 46215 | T29: 46242 | U29: =IF($P29="","",TODAY()-$P29) -> 20 | V29: =IF($A29="","",IF(COUNTIF(Consultation!$B$4:$B$1003,$A29)>0,"Yes","No")) -> No | W29: =IF($A29="","",IF(COUNTIF(Customers!$B$4:$B$1003,$A29)>0,"Yes","No")) -> No | X29: Walk-in from the Dushanbe office, brochure handed out.
A30: LD-027 | B30: Sanjar Ochilov | C30: +992 93 281 4699 | D30: +992 93 281 4699 | E30: sanjar27@mail.tj | F30: A4137071 | G30: Uzbek | H30: 34425 | I30: =IF($H30="","",DATEDIF($H30,TODAY(),"Y")) -> 32 | J30: Nurse | K30: Master | L30: Fluent | M30: Advanced | N30: Germany | O30: Instagram | P30: 46218 | Q30: Dilnoza Aliyeva | R30: New Lead | U30: =IF($P30="","",TODAY()-$P30) -> 15 | V30: =IF($A30="","",IF(COUNTIF(Consultation!$B$4:$B$1003,$A30)>0,"Yes","No")) -> No | W30: =IF($A30="","",IF(COUNTIF(Customers!$B$4:$B$1003,$A30)>0,"Yes","No")) -> No
A31: LD-028 | B31: Firuza Yatimova | C31: +992 94 284 4836 | D31: +992 94 284 4836 | E31: firuza28@mail.tj | F31: A4138444 | G31: Tajik | H31: 37146 | I31: =IF($H31="","",DATEDIF($H31,TODAY(),"Y")) -> 24 | J31: Seamstress | K31: Secondary | L31: Basic | M31: None | N31: Poland | O31: Referral | P31: 46221 | Q31: Nilufar Karimova | R31: No Answer | S31: 46223 | T31: 46244 | U31: =IF($P31="","",TODAY()-$P31) -> 12 | V31: =IF($A31="","",IF(COUNTIF(Consultation!$B$4:$B$1003,$A31)>0,"Yes","No")) -> No | W31: =IF($A31="","",IF(COUNTIF(Customers!$B$4:$B$1003,$A31)>0,"Yes","No")) -> No
A32: LD-029 | B32: Komron Salimov | C32: +992 95 287 4973 | D32: +992 95 287 4973 | E32: komron29@mail.tj | F32: A4139817 | G32: Tajik | H32: 32927 | I32: =IF($H32="","",DATEDIF($H32,TODAY(),"Y")) -> 36 | J32: Forklift Operator | K32: Vocational | L32: Intermediate | M32: Basic | N32: Croatia | O32: Instagram | P32: 46225 | Q32: Jamshed Sattorov | R32: Follow-up Required | S32: 46227 | T32: 46245 | U32: =IF($P32="","",TODAY()-$P32) -> 8 | V32: =IF($A32="","",IF(COUNTIF(Consultation!$B$4:$B$1003,$A32)>0,"Yes","No")) -> No | W32: =IF($A32="","",IF(COUNTIF(Customers!$B$4:$B$1003,$A32)>0,"Yes","No")) -> No
A33: LD-030 | B33: Anisa Juraeva | C33: +992 96 290 5110 | D33: +992 96 290 5110 | E33: anisa30@mail.tj | F33: A4141190 | G33: Tajik | H33: 35618 | I33: =IF($H33="","",DATEDIF($H33,TODAY(),"Y")) -> 29 | J33: Welder | K33: Bachelor | L33: Advanced | M33: Intermediate | N33: Poland | O33: Website | P33: 46230 | Q33: Dilnoza Aliyeva | R33: New Lead | U33: =IF($P33="","",TODAY()-$P33) -> 3 | V33: =IF($A33="","",IF(COUNTIF(Consultation!$B$4:$B$1003,$A33)>0,"Yes","No")) -> No | W33: =IF($A33="","",IF(COUNTIF(Customers!$B$4:$B$1003,$A33)>0,"Yes","No")) -> No
I34: =IF($H34="","",DATEDIF($H34,TODAY(),"Y")) | U34: =IF($P34="","",TODAY()-$P34) | V34: =IF($A34="","",IF(COUNTIF(Consultation!$B$4:$B$1003,$A34)>0,"Yes","No")) | W34: =IF($A34="","",IF(COUNTIF(Customers!$B$4:$B$1003,$A34)>0,"Yes","No"))
I35: =IF($H35="","",DATEDIF($H35,TODAY(),"Y")) | U35: =IF($P35="","",TODAY()-$P35) | V35: =IF($A35="","",IF(COUNTIF(Consultation!$B$4:$B$1003,$A35)>0,"Yes","No")) | W35: =IF($A35="","",IF(COUNTIF(Customers!$B$4:$B$1003,$A35)>0,"Yes","No"))
I36: =IF($H36="","",DATEDIF($H36,TODAY(),"Y")) | U36: =IF($P36="","",TODAY()-$P36) | V36: =IF($A36="","",IF(COUNTIF(Consultation!$B$4:$B$1003,$A36)>0,"Yes","No")) | W36: =IF($A36="","",IF(COUNTIF(Customers!$B$4:$B$1003,$A36)>0,"Yes","No"))
I37: =IF($H37="","",DATEDIF($H37,TODAY(),"Y")) | U37: =IF($P37="","",TODAY()-$P37) | V37: =IF($A37="","",IF(COUNTIF(Consultation!$B$4:$B$1003,$A37)>0,"Yes","No")) | W37: =IF($A37="","",IF(COUNTIF(Customers!$B$4:$B$1003,$A37)>0,"Yes","No"))
I38: =IF($H38="","",DATEDIF($H38,TODAY(),"Y")) | U38: =IF($P38="","",TODAY()-$P38) | V38: =IF($A38="","",IF(COUNTIF(Consultation!$B$4:$B$1003,$A38)>0,"Yes","No")) | W38: =IF($A38="","",IF(COUNTIF(Customers!$B$4:$B$1003,$A38)>0,"Yes","No"))
I39: =IF($H39="","",DATEDIF($H39,TODAY(),"Y")) | U39: =IF($P39="","",TODAY()-$P39) | V39: =IF($A39="","",IF(COUNTIF(Consultation!$B$4:$B$1003,$A39)>0,"Yes","No")) | W39: =IF($A39="","",IF(COUNTIF(Customers!$B$4:$B$1003,$A39)>0,"Yes","No"))
I40: =IF($H40="","",DATEDIF($H40,TODAY(),"Y")) | U40: =IF($P40="","",TODAY()-$P40) | V40: =IF($A40="","",IF(COUNTIF(Consultation!$B$4:$B$1003,$A40)>0,"Yes","No")) | W40: =IF($A40="","",IF(COUNTIF(Customers!$B$4:$B$1003,$A40)>0,"Yes","No"))
I41: =IF($H41="","",DATEDIF($H41,TODAY(),"Y")) | U41: =IF($P41="","",TODAY()-$P41) | V41: =IF($A41="","",IF(COUNTIF(Consultation!$B$4:$B$1003,$A41)>0,"Yes","No")) | W41: =IF($A41="","",IF(COUNTIF(Customers!$B$4:$B$1003,$A41)>0,"Yes","No"))
I42: =IF($H42="","",DATEDIF($H42,TODAY(),"Y")) | U42: =IF($P42="","",TODAY()-$P42) | V42: =IF($A42="","",IF(COUNTIF(Consultation!$B$4:$B$1003,$A42)>0,"Yes","No")) | W42: =IF($A42="","",IF(COUNTIF(Customers!$B$4:$B$1003,$A42)>0,"Yes","No"))
I43: =IF($H43="","",DATEDIF($H43,TODAY(),"Y")) | U43: =IF($P43="","",TODAY()-$P43) | V43: =IF($A43="","",IF(COUNTIF(Consultation!$B$4:$B$1003,$A43)>0,"Yes","No")) | W43: =IF($A43="","",IF(COUNTIF(Customers!$B$4:$B$1003,$A43)>0,"Yes","No"))
I44: =IF($H44="","",DATEDIF($H44,TODAY(),"Y")) | U44: =IF($P44="","",TODAY()-$P44) | V44: =IF($A44="","",IF(COUNTIF(Consultation!$B$4:$B$1003,$A44)>0,"Yes","No")) | W44: =IF($A44="","",IF(COUNTIF(Customers!$B$4:$B$1003,$A44)>0,"Yes","No"))
I45: =IF($H45="","",DATEDIF($H45,TODAY(),"Y")) | U45: =IF($P45="","",TODAY()-$P45) | V45: =IF($A45="","",IF(COUNTIF(Consultation!$B$4:$B$1003,$A45)>0,"Yes","No")) | W45: =IF($A45="","",IF(COUNTIF(Customers!$B$4:$B$1003,$A45)>0,"Yes","No"))
... I203: =IF($H203="","",DATEDIF($H203,TODAY(),"Y")) | U203: =IF($P203="","",TODAY()-$P203) | V203: =IF($A203="","",IF(COUNTIF(Consultation!$B$4:$B$1003,$A203)>0,"Yes","No")) | W203: =IF($A203="","",IF(COUNTIF(Customers!$B$4:$B$1003,$A203)>0,"Yes","No"))

Sheet Consultation
A1: VUSLAT RECRUITMENT COMPANY | CONSULTATION
A2: Every candidate pays a 50 TJS in-office consultation fee. Type the Lead ID in column B - the name, phone and fee fill in automatically.
A3: Consultation ID | B3: Lead ID | C3: Full Name | D3: Phone | E3: Consultation Date | F3: Time | G3: Consultant | H3: Consultation Fee (TJS) | I3: Payment Status | J3: Consultation Status | K3: Customer Evaluation | L3: Recommended Country | M3: Recommended Job | N3: Next Action | O3: Consultant Notes | P3: Converted to Customer | Q3: Days Since Consultation
A4: CNS-001 | B4: LD-001 | C4: =IFERROR(INDEX('Lead Management'!$B$4:$B$1003,MATCH($B4,'Lead Management'!$A$4:$A$1003,0)),"") -> Firdavs Rahmonov | D4: =IFERROR(INDEX('Lead Management'!$C$4:$C$1003,MATCH($B4,'Lead Management'!$A$4:$A$1003,0)),"") -> +992 91 203 1137 | E4: 46035 | F4: 10:00 | G4: Zarina Nazarova | H4: =IF($A4="","",Settings!$B$8) -> 50 | I4: Paid | J4: Completed | K4: Strong Candidate | L4: Poland | M4: Welder | N4: Prepare Contract | P4: =IF($B4="","",IF(COUNTIF(Customers!$B$4:$B$1003,$B4)>0,"Yes","No")) -> Yes | Q4: =IF($E4="","",IF($E4>TODAY(),"Scheduled",TODAY()-$E4)) -> 198
A5: CNS-002 | B5: LD-002 | C5: =IFERROR(INDEX('Lead Management'!$B$4:$B$1003,MATCH($B5,'Lead Management'!$A$4:$A$1003,0)),"") -> Nilufar Sharipova | D5: =IFERROR(INDEX('Lead Management'!$C$4:$C$1003,MATCH($B5,'Lead Management'!$A$4:$A$1003,0)),"") -> +992 92 206 1274 | E5: 46042 | F5: 11:30 | G5: Dilnoza Aliyeva | H5: =IF($A5="","",Settings!$B$8) -> 50 | I5: Paid | J5: Completed | K5: Strong Candidate | L5: Germany | M5: Warehouse Operator | N5: Prepare Contract | P5: =IF($B5="","",IF(COUNTIF(Customers!$B$4:$B$1003,$B5)>0,"Yes","No")) -> Yes | Q5: =IF($E5="","",IF($E5>TODAY(),"Scheduled",TODAY()-$E5)) -> 191
A6: CNS-003 | B6: LD-003 | C6: =IFERROR(INDEX('Lead Management'!$B$4:$B$1003,MATCH($B6,'Lead Management'!$A$4:$A$1003,0)),"") -> Jamshed Karimov | D6: =IFERROR(INDEX('Lead Management'!$C$4:$C$1003,MATCH($B6,'Lead Management'!$A$4:$A$1003,0)),"") -> +992 93 209 1411 | E6: 46063 | F6: 12:00 | G6: Zarina Nazarova | H6: =IF($A6="","",Settings!$B$8) -> 50 | I6: Paid | J6: Completed | K6: Good Candidate | L6: Czech Republic | M6: Construction Worker | N6: Prepare Contract | P6: =IF($B6="","",IF(COUNTIF(Customers!$B$4:$B$1003,$B6)>0,"Yes","No")) -> Yes | Q6: =IF($E6="","",IF($E6>TODAY(),"Scheduled",TODAY()-$E6)) -> 170
A7: CNS-004 | B7: LD-004 | C7: =IFERROR(INDEX('Lead Management'!$B$4:$B$1003,MATCH($B7,'Lead Management'!$A$4:$A$1003,0)),"") -> Zarina Nazriyeva | D7: =IFERROR(INDEX('Lead Management'!$C$4:$C$1003,MATCH($B7,'Lead Management'!$A$4:$A$1003,0)),"") -> +992 94 212 1548 | E7: 46070 | F7: 13:30 | G7: Dilnoza Aliyeva | H7: =IF($A7="","",Settings!$B$8) -> 50 | I7: Paid | J7: Completed | K7: Strong Candidate | L7: Poland | M7: Electrician | N7: Prepare Contract | P7: =IF($B7="","",IF(COUNTIF(Customers!$B$4:$B$1003,$B7)>0,"Yes","No")) -> Yes | Q7: =IF($E7="","",IF($E7>TODAY(),"Scheduled",TODAY()-$E7)) -> 163
A8: CNS-005 | B8: LD-005 | C8: =IFERROR(INDEX('Lead Management'!$B$4:$B$1003,MATCH($B8,'Lead Management'!$A$4:$A$1003,0)),"") -> Bakhtiyor Umarov | D8: =IFERROR(INDEX('Lead Management'!$C$4:$C$1003,MATCH($B8,'Lead Management'!$A$4:$A$1003,0)),"") -> +992 95 215 1685 | E8: 46049 | F8: 14:00 | G8: Zarina Nazarova | H8: =IF($A8="","",Settings!$B$8) -> 50 | I8: Paid | J8: Completed | K8: Good Candidate | L8: Slovakia | M8: Truck Driver (CE) | N8: Prepare Contract | P8: =IF($B8="","",IF(COUNTIF(Customers!$B$4:$B$1003,$B8)>0,"Yes","No")) -> Yes | Q8: =IF($E8="","",IF($E8>TODAY(),"Scheduled",TODAY()-$E8)) -> 184
A9: CNS-006 | B9: LD-006 | C9: =IFERROR(INDEX('Lead Management'!$B$4:$B$1003,MATCH($B9,'Lead Management'!$A$4:$A$1003,0)),"") -> Manizha Qodirova | D9: =IFERROR(INDEX('Lead Management'!$C$4:$C$1003,MATCH($B9,'Lead Management'!$A$4:$A$1003,0)),"") -> +992 96 218 1822 | E9: 46076 | F9: 15:30 | G9: Dilnoza Aliyeva | H9: =IF($A9="","",Settings!$B$8) -> 50 | I9: Paid | J9: Completed | K9: Strong Candidate | L9: Germany | M9: Chef | N9: Prepare Contract | P9: =IF($B9="","",IF(COUNTIF(Customers!$B$4:$B$1003,$B9)>0,"Yes","No")) -> Yes | Q9: =IF($E9="","",IF($E9>TODAY(),"Scheduled",TODAY()-$E9)) -> 157
A10: CNS-007 | B10: LD-007 | C10: =IFERROR(INDEX('Lead Management'!$B$4:$B$1003,MATCH($B10,'Lead Management'!$A$4:$A$1003,0)),"") -> Rustam Sattorov | D10: =IFERROR(INDEX('Lead Management'!$C$4:$C$1003,MATCH($B10,'Lead Management'!$A$4:$A$1003,0)),"") -> +992 97 221 1959 | E10: 46090 | F10: 16:00 | G10: Zarina Nazarova | H10: =IF($A10="","",Settings!$B$8) -> 50 | I10: Paid | J10: Completed | K10: Good Candidate | L10: Poland | M10: Construction Worker | N10: Prepare Contract | P10: =IF($B10="","",IF(COUNTIF(Customers!$B$4:$B$1003,$B10)>0,"Yes","No")) -> Yes | Q10: =IF($E10="","",IF($E10>TODAY(),"Scheduled",TODAY()-$E10)) -> 143
A11: CNS-008 | B11: LD-008 | C11: =IFERROR(INDEX('Lead Management'!$B$4:$B$1003,MATCH($B11,'Lead Management'!$A$4:$A$1003,0)),"") -> Dilnoza Aliyeva | D11: =IFERROR(INDEX('Lead Management'!$C$4:$C$1003,MATCH($B11,'Lead Management'!$A$4:$A$1003,0)),"") -> +992 90 224 2096 | E11: 46097 | F11: 09:30 | G11: Dilnoza Aliyeva | H11: =IF($A11="","",Settings!$B$8) -> 50 | I11: Paid | J11: Completed | K11: Good Candidate | L11: Lithuania | M11: Warehouse Operator | N11: Prepare Contract | P11: =IF($B11="","",IF(COUNTIF(Customers!$B$4:$B$1003,$B11)>0,"Yes","No")) -> Yes | Q11: =IF($E11="","",IF($E11>TODAY(),"Scheduled",TODAY()-$E11)) -> 136
A12: CNS-009 | B12: LD-009 | C12: =IFERROR(INDEX('Lead Management'!$B$4:$B$1003,MATCH($B12,'Lead Management'!$A$4:$A$1003,0)),"") -> Sherali Yusupov | D12: =IFERROR(INDEX('Lead Management'!$C$4:$C$1003,MATCH($B12,'Lead Management'!$A$4:$A$1003,0)),"") -> +992 91 227 2233 | E12: 46104 | F12: 10:00 | G12: Zarina Nazarova | H12: =IF($A12="","",Settings!$B$8) -> 50 | I12: Paid | J12: Completed | K12: Average Candidate | L12: Czech Republic | M12: Plumber | N12: Prepare Contract | P12: =IF($B12="","",IF(COUNTIF(Customers!$B$4:$B$1003,$B12)>0,"Yes","No")) -> Yes | Q12: =IF($E12="","",IF($E12>TODAY(),"Scheduled",TODAY()-$E12)) -> 129
A13: CNS-010 | B13: LD-010 | C13: =IFERROR(INDEX('Lead Management'!$B$4:$B$1003,MATCH($B13,'Lead Management'!$A$4:$A$1003,0)),"") -> Malika Ismoilova | D13: =IFERROR(INDEX('Lead Management'!$C$4:$C$1003,MATCH($B13,'Lead Management'!$A$4:$A$1003,0)),"") -> +992 92 230 2370 | E13: 46119 | F13: 11:30 | G13: Dilnoza Aliyeva | H13: =IF($A13="","",Settings!$B$8) -> 50 | I13: Paid | J13: Completed | K13: Good Candidate | L13: Poland | M13: Painter | N13: Prepare Contract | P13: =IF($B13="","",IF(COUNTIF(Customers!$B$4:$B$1003,$B13)>0,"Yes","No")) -> Yes | Q13: =IF($E13="","",IF($E13>TODAY(),"Scheduled",TODAY()-$E13)) -> 114
A14: CNS-011 | B14: LD-011 | C14: =IFERROR(INDEX('Lead Management'!$B$4:$B$1003,MATCH($B14,'Lead Management'!$A$4:$A$1003,0)),"") -> Farrukh Davlatov | D14: =IFERROR(INDEX('Lead Management'!$C$4:$C$1003,MATCH($B14,'Lead Management'!$A$4:$A$1003,0)),"") -> +992 93 233 2507 | E14: 46111 | F14: 12:00 | G14: Zarina Nazarova | H14: =IF($A14="","",Settings!$B$8) -> 50 | I14: Paid | J14: Completed | K14: Average Candidate | L14: Hungary | M14: Agricultural Worker | N14: Prepare Contract | P14: =IF($B14="","",IF(COUNTIF(Customers!$B$4:$B$1003,$B14)>0,"Yes","No")) -> Yes | Q14: =IF($E14="","",IF($E14>TODAY(),"Scheduled",TODAY()-$E14)) -> 122
A15: CNS-012 | B15: LD-012 | C15: =IFERROR(INDEX('Lead Management'!$B$4:$B$1003,MATCH($B15,'Lead Management'!$A$4:$A$1003,0)),"") -> Gulnora Safarova | D15: =IFERROR(INDEX('Lead Management'!$C$4:$C$1003,MATCH($B15,'Lead Management'!$A$4:$A$1003,0)),"") -> +992 94 236 2644 | E15: 46126 | F15: 13:30 | G15: Dilnoza Aliyeva | H15: =IF($A15="","",Settings!$B$8) -> 50 | I15: Paid | J15: Completed | K15: Average Candidate | L15: Romania | M15: Cleaner | N15: Prepare Contract | P15: =IF($B15="","",IF(COUNTIF(Customers!$B$4:$B$1003,$B15)>0,"Yes","No")) -> Yes | Q15: =IF($E15="","",IF($E15>TODAY(),"Scheduled",TODAY()-$E15)) -> 107
A16: CNS-013 | B16: LD-013 | C16: =IFERROR(INDEX('Lead Management'!$B$4:$B$1003,MATCH($B16,'Lead Management'!$A$4:$A$1003,0)),"") -> Umed Nazriev | D16: =IFERROR(INDEX('Lead Management'!$C$4:$C$1003,MATCH($B16,'Lead Management'!$A$4:$A$1003,0)),"") -> +992 95 239 2781 | E16: 46133 | F16: 14:00 | G16: Zarina Nazarova | H16: =IF($A16="","",Settings!$B$8) -> 50 | I16: Paid | J16: Completed | K16: Weak Candidate | L16: Germany | M16: Auto Mechanic | N16: Close - Not Suitable | O16: Weak documents, diploma not apostilled. Advised to prepare first. | P16: =IF($B16="","",IF(COUNTIF(Customers!$B$4:$B$1003,$B16)>0,"Yes","No")) -> No | Q16: =IF($E16="","",IF($E16>TODAY(),"Scheduled",TODAY()-$E16)) -> 100
A17: CNS-014 | B17: LD-014 | C17: =IFERROR(INDEX('Lead Management'!$B$4:$B$1003,MATCH($B17,'Lead Management'!$A$4:$A$1003,0)),"") -> Shahnoza Rajabova | D17: =IFERROR(INDEX('Lead Management'!$C$4:$C$1003,MATCH($B17,'Lead Management'!$A$4:$A$1003,0)),"") -> +992 96 242 2918 | E17: 46120 | F17: 15:30 | G17: Dilnoza Aliyeva | H17: =IF($A17="","",Settings!$B$8) -> 50 | I17: Paid | J17: Completed | K17: Average Candidate | L17: Poland | M17: Forklift Operator | N17: Await Client Decision | O17: Good profile but wants to postpone the departure to next year. | P17: =IF($B17="","",IF(COUNTIF(Customers!$B$4:$B$1003,$B17)>0,"Yes","No")) -> No | Q17: =IF($E17="","",IF($E17>TODAY(),"Scheduled",TODAY()-$E17)) -> 113
A18: CNS-015 | B18: LD-015 | C18: =IFERROR(INDEX('Lead Management'!$B$4:$B$1003,MATCH($B18,'Lead Management'!$A$4:$A$1003,0)),"") -> Iskandar Mirzoev | D18: =IFERROR(INDEX('Lead Management'!$C$4:$C$1003,MATCH($B18,'Lead Management'!$A$4:$A$1003,0)),"") -> +992 97 245 3055 | E18: 46237 | F18: 16:00 | G18: Zarina Nazarova | H18: =IF($A18="","",Settings!$B$8) -> 50 | I18: Pending | J18: Scheduled | L18: Poland | M18: Welder | N18: Collect Documents | P18: =IF($B18="","",IF(COUNTIF(Customers!$B$4:$B$1003,$B18)>0,"Yes","No")) -> No | Q18: =IF($E18="","",IF($E18>TODAY(),"Scheduled",TODAY()-$E18)) -> Scheduled
A19: CNS-016 | B19: LD-016 | C19: =IFERROR(INDEX('Lead Management'!$B$4:$B$1003,MATCH($B19,'Lead Management'!$A$4:$A$1003,0)),"") -> Sitora Hakimova | D19: =IFERROR(INDEX('Lead Management'!$C$4:$C$1003,MATCH($B19,'Lead Management'!$A$4:$A$1003,0)),"") -> +992 90 248 3192 | E19: 46238 | F19: 09:30 | G19: Dilnoza Aliyeva | H19: =IF($A19="","",Settings!$B$8) -> 50 | I19: Pending | J19: Scheduled | L19: Czech Republic | M19: Warehouse Operator | N19: Collect Documents | P19: =IF($B19="","",IF(COUNTIF(Customers!$B$4:$B$1003,$B19)>0,"Yes","No")) -> No | Q19: =IF($E19="","",IF($E19>TODAY(),"Scheduled",TODAY()-$E19)) -> Scheduled
A20: CNS-017 | B20: LD-017 | C20: =IFERROR(INDEX('Lead Management'!$B$4:$B$1003,MATCH($B20,'Lead Management'!$A$4:$A$1003,0)),"") -> Daler Ashurov | D20: =IFERROR(INDEX('Lead Management'!$C$4:$C$1003,MATCH($B20,'Lead Management'!$A$4:$A$1003,0)),"") -> +992 91 251 3329 | E20: 46168 | F20: 10:00 | G20: Zarina Nazarova | H20: =IF($A20="","",Settings!$B$8) -> 50 | I20: Cancelled | J20: No-show | L20: Slovakia | M20: Construction Worker | N20: Schedule Follow-up | O20: Client did not come to the office. Fee not collected. | P20: =IF($B20="","",IF(COUNTIF(Customers!$B$4:$B$1003,$B20)>0,"Yes","No")) -> No | Q20: =IF($E20="","",IF($E20>TODAY(),"Scheduled",TODAY()-$E20)) -> 65
A21: CNS-018 | B21: LD-018 | C21: =IFERROR(INDEX('Lead Management'!$B$4:$B$1003,MATCH($B21,'Lead Management'!$A$4:$A$1003,0)),"") -> Nasiba Kholova | D21: =IFERROR(INDEX('Lead Management'!$C$4:$C$1003,MATCH($B21,'Lead Management'!$A$4:$A$1003,0)),"") -> +992 92 254 3466 | E21: 46176 | F21: 11:30 | G21: Dilnoza Aliyeva | H21: =IF($A21="","",Settings!$B$8) -> 50 | I21: Cancelled | J21: Cancelled | L21: Germany | M21: Seamstress | N21: Close - Not Suitable | O21: Client cancelled one day before the appointment. | P21: =IF($B21="","",IF(COUNTIF(Customers!$B$4:$B$1003,$B21)>0,"Yes","No")) -> No | Q21: =IF($E21="","",IF($E21>TODAY(),"Scheduled",TODAY()-$E21)) -> 57
C22: =IFERROR(INDEX('Lead Management'!$B$4:$B$1003,MATCH($B22,'Lead Management'!$A$4:$A$1003,0)),"") | D22: =IFERROR(INDEX('Lead Management'!$C$4:$C$1003,MATCH($B22,'Lead Management'!$A$4:$A$1003,0)),"") | H22: =IF($A22="","",Settings!$B$8) | P22: =IF($B22="","",IF(COUNTIF(Customers!$B$4:$B$1003,$B22)>0,"Yes","No")) | Q22: =IF($E22="","",IF($E22>TODAY(),"Scheduled",TODAY()-$E22))
C23: =IFERROR(INDEX('Lead Management'!$B$4:$B$1003,MATCH($B23,'Lead Management'!$A$4:$A$1003,0)),"") | D23: =IFERROR(INDEX('Lead Management'!$C$4:$C$1003,MATCH($B23,'Lead Management'!$A$4:$A$1003,0)),"") | H23: =IF($A23="","",Settings!$B$8) | P23: =IF($B23="","",IF(COUNTIF(Customers!$B$4:$B$1003,$B23)>0,"Yes","No")) | Q23: =IF($E23="","",IF($E23>TODAY(),"Scheduled",TODAY()-$E23))
C24: =IFERROR(INDEX('Lead Management'!$B$4:$B$1003,MATCH($B24,'Lead Management'!$A$4:$A$1003,0)),"") | D24: =IFERROR(INDEX('Lead Management'!$C$4:$C$1003,MATCH($B24,'Lead Management'!$A$4:$A$1003,0)),"") | H24: =IF($A24="","",Settings!$B$8) | P24: =IF($B24="","",IF(COUNTIF(Customers!$B$4:$B$1003,$B24)>0,"Yes","No")) | Q24: =IF($E24="","",IF($E24>TODAY(),"Scheduled",TODAY()-$E24))
C25: =IFERROR(INDEX('Lead Management'!$B$4:$B$1003,MATCH($B25,'Lead Management'!$A$4:$A$1003,0)),"") | D25: =IFERROR(INDEX('Lead Management'!$C$4:$C$1003,MATCH($B25,'Lead Management'!$A$4:$A$1003,0)),"") | H25: =IF($A25="","",Settings!$B$8) | P25: =IF($B25="","",IF(COUNTIF(Customers!$B$4:$B$1003,$B25)>0,"Yes","No")) | Q25: =IF($E25="","",IF($E25>TODAY(),"Scheduled",TODAY()-$E25))
C26: =IFERROR(INDEX('Lead Management'!$B$4:$B$1003,MATCH($B26,'Lead Management'!$A$4:$A$1003,0)),"") | D26: =IFERROR(INDEX('Lead Management'!$C$4:$C$1003,MATCH($B26,'Lead Management'!$A$4:$A$1003,0)),"") | H26: =IF($A26="","",Settings!$B$8) | P26: =IF($B26="","",IF(COUNTIF(Customers!$B$4:$B$1003,$B26)>0,"Yes","No")) | Q26: =IF($E26="","",IF($E26>TODAY(),"Scheduled",TODAY()-$E26))
C27: =IFERROR(INDEX('Lead Management'!$B$4:$B$1003,MATCH($B27,'Lead Management'!$A$4:$A$1003,0)),"") | D27: =IFERROR(INDEX('Lead Management'!$C$4:$C$1003,MATCH($B27,'Lead Management'!$A$4:$A$1003,0)),"") | H27: =IF($A27="","",Settings!$B$8) | P27: =IF($B27="","",IF(COUNTIF(Customers!$B$4:$B$1003,$B27)>0,"Yes","No")) | Q27: =IF($E27="","",IF($E27>TODAY(),"Scheduled",TODAY()-$E27))
C28: =IFERROR(INDEX('Lead Management'!$B$4:$B$1003,MATCH($B28,'Lead Management'!$A$4:$A$1003,0)),"") | D28: =IFERROR(INDEX('Lead Management'!$C$4:$C$1003,MATCH($B28,'Lead Management'!$A$4:$A$1003,0)),"") | H28: =IF($A28="","",Settings!$B$8) | P28: =IF($B28="","",IF(COUNTIF(Customers!$B$4:$B$1003,$B28)>0,"Yes","No")) | Q28: =IF($E28="","",IF($E28>TODAY(),"Scheduled",TODAY()-$E28))
C29: =IFERROR(INDEX('Lead Management'!$B$4:$B$1003,MATCH($B29,'Lead Management'!$A$4:$A$1003,0)),"") | D29: =IFERROR(INDEX('Lead Management'!$C$4:$C$1003,MATCH($B29,'Lead Management'!$A$4:$A$1003,0)),"") | H29: =IF($A29="","",Settings!$B$8) | P29: =IF($B29="","",IF(COUNTIF(Customers!$B$4:$B$1003,$B29)>0,"Yes","No")) | Q29: =IF($E29="","",IF($E29>TODAY(),"Scheduled",TODAY()-$E29))
C30: =IFERROR(INDEX('Lead Management'!$B$4:$B$1003,MATCH($B30,'Lead Management'!$A$4:$A$1003,0)),"") | D30: =IFERROR(INDEX('Lead Management'!$C$4:$C$1003,MATCH($B30,'Lead Management'!$A$4:$A$1003,0)),"") | H30: =IF($A30="","",Settings!$B$8) | P30: =IF($B30="","",IF(COUNTIF(Customers!$B$4:$B$1003,$B30)>0,"Yes","No")) | Q30: =IF($E30="","",IF($E30>TODAY(),"Scheduled",TODAY()-$E30))
C31: =IFERROR(INDEX('Lead Management'!$B$4:$B$1003,MATCH($B31,'Lead Management'!$A$4:$A$1003,0)),"") | D31: =IFERROR(INDEX('Lead Management'!$C$4:$C$1003,MATCH($B31,'Lead Management'!$A$4:$A$1003,0)),"") | H31: =IF($A31="","",Settings!$B$8) | P31: =IF($B31="","",IF(COUNTIF(Customers!$B$4:$B$1003,$B31)>0,"Yes","No")) | Q31: =IF($E31="","",IF($E31>TODAY(),"Scheduled",TODAY()-$E31))
C32: =IFERROR(INDEX('Lead Management'!$B$4:$B$1003,MATCH($B32,'Lead Management'!$A$4:$A$1003,0)),"") | D32: =IFERROR(INDEX('Lead Management'!$C$4:$C$1003,MATCH($B32,'Lead Management'!$A$4:$A$1003,0)),"") | H32: =IF($A32="","",Settings!$B$8) | P32: =IF($B32="","",IF(COUNTIF(Customers!$B$4:$B$1003,$B32)>0,"Yes","No")) | Q32: =IF($E32="","",IF($E32>TODAY(),"Scheduled",TODAY()-$E32))
C33: =IFERROR(INDEX('Lead Management'!$B$4:$B$1003,MATCH($B33,'Lead Management'!$A$4:$A$1003,0)),"") | D33: =IFERROR(INDEX('Lead Management'!$C$4:$C$1003,MATCH($B33,'Lead Management'!$A$4:$A$1003,0)),"") | H33: =IF($A33="","",Settings!$B$8) | P33: =IF($B33="","",IF(COUNTIF(Customers!$B$4:$B$1003,$B33)>0,"Yes","No")) | Q33: =IF($E33="","",IF($E33>TODAY(),"Scheduled",TODAY()-$E33))
... C203: =IFERROR(INDEX('Lead Management'!$B$4:$B$1003,MATCH($B203,'Lead Management'!$A$4:$A$1003,0)),"") | D203: =IFERROR(INDEX('Lead Management'!$C$4:$C$1003,MATCH($B203,'Lead Management'!$A$4:$A$1003,0)),"") | H203: =IF($A203="","",Settings!$B$8) | P203: =IF($B203="","",IF(COUNTIF(Customers!$B$4:$B$1003,$B203)>0,"Yes","No")) | Q203: =IF($E203="","",IF($E203>TODAY(),"Scheduled",TODAY()-$E203))

Sheet Customers
A1: VUSLAT RECRUITMENT COMPANY | CUSTOMERS
A2: Type the Customer ID, Lead ID, destination country and manager. Everything else - name, price, paid, balance, current stage and document progress - is calculated from the other sheets.
A3: Customer ID | B3: Lead ID | C3: Full Name | D3: Phone | E3: Passport Number | F3: Destination Country | G3: Job Position | H3: Employer | I3: Contract No | J3: Contract Date | K3: Assigned Manager | L3: Package Price (TJS) | M3: Total Paid (TJS) | N3: Balance (TJS) | O3: Payment Progress | P3: Current Stage | Q3: Documents % | R3: Customer Status | S3: Lead Source | T3: Registration Date | U3: Notes
A4: CUS-001 | B4: LD-001 | C4: =IFERROR(INDEX('Lead Management'!$B$4:$B$1003,MATCH($B4,'Lead Management'!$A$4:$A$1003,0)),"") -> Firdavs Rahmonov | D4: =IFERROR(INDEX('Lead Management'!$C$4:$C$1003,MATCH($B4,'Lead Management'!$A$4:$A$1003,0)),"") -> +992 91 203 1137 | E4: =IFERROR(INDEX('Lead Management'!$F$4:$F$1003,MATCH($B4,'Lead Management'!$A$4:$A$1003,0)),"") -> A4101373 | F4: Poland | G4: Welder | H4: Stal-Bud Sp. z o.o. | I4: CTR-2026-001 | J4: 46039 | K4: Nilufar Karimova | L4: =IF($F4="","",IFERROR(INDEX(Settings!$B$18:$B$27,MATCH($F4,Settings!$A$18:$A$27,0)),"")) -> 22000 | M4: =IF($A4="","",SUMIFS(Finance!$E$4:$E$1003,Finance!$B$4:$B$1003,$A4,Finance!$J$4:$J$1003,"Paid")) -> 22000 | N4: =IF($A4="","",IFERROR($L4-$M4,"")) -> 0 | O4: =IF($A4="","",IFERROR($M4/$L4,"")) -> 1 | P4: =IFERROR(INDEX('Process Tracking'!$E$5:$E$1003,MATCH($A4,'Process Tracking'!$A$5:$A$1003,0)),"") -> Case Completed | Q4: =IFERROR(INDEX(Documents!$Q$4:$Q$1003,MATCH($A4,Documents!$A$4:$A$1003,0)),"") -> 1 | R4: Completed | S4: =IFERROR(INDEX('Lead Management'!$O$4:$O$1003,MATCH($B4,'Lead Management'!$A$4:$A$1003,0)),"") -> Instagram | T4: =IFERROR(INDEX('Lead Management'!$P$4:$P$1003,MATCH($B4,'Lead Management'!$A$4:$A$1003,0)),"") -> 46030
A5: CUS-002 | B5: LD-002 | C5: =IFERROR(INDEX('Lead Management'!$B$4:$B$1003,MATCH($B5,'Lead Management'!$A$4:$A$1003,0)),"") -> Nilufar Sharipova | D5: =IFERROR(INDEX('Lead Management'!$C$4:$C$1003,MATCH($B5,'Lead Management'!$A$4:$A$1003,0)),"") -> +992 92 206 1274 | E5: =IFERROR(INDEX('Lead Management'!$F$4:$F$1003,MATCH($B5,'Lead Management'!$A$4:$A$1003,0)),"") -> A4102746 | F5: Germany | G5: Warehouse Operator | H5: Nordbau GmbH | I5: CTR-2026-002 | J5: 46046 | K5: Jamshed Sattorov | L5: =IF($F5="","",IFERROR(INDEX(Settings!$B$18:$B$27,MATCH($F5,Settings!$A$18:$A$27,0)),"")) -> 32000 | M5: =IF($A5="","",SUMIFS(Finance!$E$4:$E$1003,Finance!$B$4:$B$1003,$A5,Finance!$J$4:$J$1003,"Paid")) -> 32000 | N5: =IF($A5="","",IFERROR($L5-$M5,"")) -> 0 | O5: =IF($A5="","",IFERROR($M5/$L5,"")) -> 1 | P5: =IFERROR(INDEX('Process Tracking'!$E$5:$E$1003,MATCH($A5,'Process Tracking'!$A$5:$A$1003,0)),"") -> Case Completed | Q5: =IFERROR(INDEX(Documents!$Q$4:$Q$1003,MATCH($A5,Documents!$A$4:$A$1003,0)),"") -> 1 | R5: Completed | S5: =IFERROR(INDEX('Lead Management'!$O$4:$O$1003,MATCH($B5,'Lead Management'!$A$4:$A$1003,0)),"") -> Instagram | T5: =IFERROR(INDEX('Lead Management'!$P$4:$P$1003,MATCH($B5,'Lead Management'!$A$4:$A$1003,0)),"") -> 46037
A6: CUS-003 | B6: LD-003 | C6: =IFERROR(INDEX('Lead Management'!$B$4:$B$1003,MATCH($B6,'Lead Management'!$A$4:$A$1003,0)),"") -> Jamshed Karimov | D6: =IFERROR(INDEX('Lead Management'!$C$4:$C$1003,MATCH($B6,'Lead Management'!$A$4:$A$1003,0)),"") -> +992 93 209 1411 | E6: =IFERROR(INDEX('Lead Management'!$F$4:$F$1003,MATCH($B6,'Lead Management'!$A$4:$A$1003,0)),"") -> A4104119 | F6: Czech Republic | G6: Construction Worker | H6: Moravia Logistic a.s. | I6: CTR-2026-003 | J6: 46067 | K6: Dilnoza Aliyeva | L6: =IF($F6="","",IFERROR(INDEX(Settings!$B$18:$B$27,MATCH($F6,Settings!$A$18:$A$27,0)),"")) -> 25000 | M6: =IF($A6="","",SUMIFS(Finance!$E$4:$E$1003,Finance!$B$4:$B$1003,$A6,Finance!$J$4:$J$1003,"Paid")) -> 25000 | N6: =IF($A6="","",IFERROR($L6-$M6,"")) -> 0 | O6: =IF($A6="","",IFERROR($M6/$L6,"")) -> 1 | P6: =IFERROR(INDEX('Process Tracking'!$E$5:$E$1003,MATCH($A6,'Process Tracking'!$A$5:$A$1003,0)),"") -> Customer Departed to Europe | Q6: =IFERROR(INDEX(Documents!$Q$4:$Q$1003,MATCH($A6,Documents!$A$4:$A$1003,0)),"") -> 1 | R6: Active | S6: =IFERROR(INDEX('Lead Management'!$O$4:$O$1003,MATCH($B6,'Lead Management'!$A$4:$A$1003,0)),"") -> Facebook | T6: =IFERROR(INDEX('Lead Management'!$P$4:$P$1003,MATCH($B6,'Lead Management'!$A$4:$A$1003,0)),"") -> 46058
A7: CUS-004 | B7: LD-004 | C7: =IFERROR(INDEX('Lead Management'!$B$4:$B$1003,MATCH($B7,'Lead Management'!$A$4:$A$1003,0)),"") -> Zarina Nazriyeva | D7: =IFERROR(INDEX('Lead Management'!$C$4:$C$1003,MATCH($B7,'Lead Management'!$A$4:$A$1003,0)),"") -> +992 94 212 1548 | E7: =IFERROR(INDEX('Lead Management'!$F$4:$F$1003,MATCH($B7,'Lead Management'!$A$4:$A$1003,0)),"") -> A4105492 | F7: Poland | G7: Electrician | H7: Stal-Bud Sp. z o.o. | I7: CTR-2026-004 | J7: 46074 | K7: Nilufar Karimova | L7: =IF($F7="","",IFERROR(INDEX(Settings!$B$18:$B$27,MATCH($F7,Settings!$A$18:$A$27,0)),"")) -> 22000 | M7: =IF($A7="","",SUMIFS(Finance!$E$4:$E$1003,Finance!$B$4:$B$1003,$A7,Finance!$J$4:$J$1003,"Paid")) -> 22000 | N7: =IF($A7="","",IFERROR($L7-$M7,"")) -> 0 | O7: =IF($A7="","",IFERROR($M7/$L7,"")) -> 1 | P7: =IFERROR(INDEX('Process Tracking'!$E$5:$E$1003,MATCH($A7,'Process Tracking'!$A$5:$A$1003,0)),"") -> Flight Ticket Prepared | Q7: =IFERROR(INDEX(Documents!$Q$4:$Q$1003,MATCH($A7,Documents!$A$4:$A$1003,0)),"") -> 1 | R7: Active | S7: =IFERROR(INDEX('Lead Management'!$O$4:$O$1003,MATCH($B7,'Lead Management'!$A$4:$A$1003,0)),"") -> Instagram | T7: =IFERROR(INDEX('Lead Management'!$P$4:$P$1003,MATCH($B7,'Lead Management'!$A$4:$A$1003,0)),"") -> 46065
A8: CUS-005 | B8: LD-005 | C8: =IFERROR(INDEX('Lead Management'!$B$4:$B$1003,MATCH($B8,'Lead Management'!$A$4:$A$1003,0)),"") -> Bakhtiyor Umarov | D8: =IFERROR(INDEX('Lead Management'!$C$4:$C$1003,MATCH($B8,'Lead Management'!$A$4:$A$1003,0)),"") -> +992 95 215 1685 | E8: =IFERROR(INDEX('Lead Management'!$F$4:$F$1003,MATCH($B8,'Lead Management'!$A$4:$A$1003,0)),"") -> A4106865 | F8: Slovakia | G8: Truck Driver (CE) | H8: Tatra Works s.r.o. | I8: CTR-2026-005 | J8: 46053 | K8: Jamshed Sattorov | L8: =IF($F8="","",IFERROR(INDEX(Settings!$B$18:$B$27,MATCH($F8,Settings!$A$18:$A$27,0)),"")) -> 24000 | M8: =IF($A8="","",SUMIFS(Finance!$E$4:$E$1003,Finance!$B$4:$B$1003,$A8,Finance!$J$4:$J$1003,"Paid")) -> 18000 | N8: =IF($A8="","",IFERROR($L8-$M8,"")) -> 6000 | O8: =IF($A8="","",IFERROR($M8/$L8,"")) -> 0.75 | P8: =IFERROR(INDEX('Process Tracking'!$E$5:$E$1003,MATCH($A8,'Process Tracking'!$A$5:$A$1003,0)),"") -> Visa Approved | Q8: =IFERROR(INDEX(Documents!$Q$4:$Q$1003,MATCH($A8,Documents!$A$4:$A$1003,0)),"") -> 0.90909091 | R8: Active | S8: =IFERROR(INDEX('Lead Management'!$O$4:$O$1003,MATCH($B8,'Lead Management'!$A$4:$A$1003,0)),"") -> Website | T8: =IFERROR(INDEX('Lead Management'!$P$4:$P$1003,MATCH($B8,'Lead Management'!$A$4:$A$1003,0)),"") -> 46044
A9: CUS-006 | B9: LD-006 | C9: =IFERROR(INDEX('Lead Management'!$B$4:$B$1003,MATCH($B9,'Lead Management'!$A$4:$A$1003,0)),"") -> Manizha Qodirova | D9: =IFERROR(INDEX('Lead Management'!$C$4:$C$1003,MATCH($B9,'Lead Management'!$A$4:$A$1003,0)),"") -> +992 96 218 1822 | E9: =IFERROR(INDEX('Lead Management'!$F$4:$F$1003,MATCH($B9,'Lead Management'!$A$4:$A$1003,0)),"") -> A4108238 | F9: Germany | G9: Chef | H9: Nordbau GmbH | I9: CTR-2026-006 | J9: 46080 | K9: Dilnoza Aliyeva | L9: =IF($F9="","",IFERROR(INDEX(Settings!$B$18:$B$27,MATCH($F9,Settings!$A$18:$A$27,0)),"")) -> 32000 | M9: =IF($A9="","",SUMIFS(Finance!$E$4:$E$1003,Finance!$B$4:$B$1003,$A9,Finance!$J$4:$J$1003,"Paid")) -> 24000 | N9: =IF($A9="","",IFERROR($L9-$M9,"")) -> 8000 | O9: =IF($A9="","",IFERROR($M9/$L9,"")) -> 0.75 | P9: =IFERROR(INDEX('Process Tracking'!$E$5:$E$1003,MATCH($A9,'Process Tracking'!$A$5:$A$1003,0)),"") -> Visa Rejected | Q9: =IFERROR(INDEX(Documents!$Q$4:$Q$1003,MATCH($A9,Documents!$A$4:$A$1003,0)),"") -> 0.81818182 | R9: Cancelled | S9: =IFERROR(INDEX('Lead Management'!$O$4:$O$1003,MATCH($B9,'Lead Management'!$A$4:$A$1003,0)),"") -> Referral | T9: =IFERROR(INDEX('Lead Management'!$P$4:$P$1003,MATCH($B9,'Lead Management'!$A$4:$A$1003,0)),"") -> 46071 | U9: Visa refused by the German embassy - appeal not requested, case closed.
A10: CUS-007 | B10: LD-007 | C10: =IFERROR(INDEX('Lead Management'!$B$4:$B$1003,MATCH($B10,'Lead Management'!$A$4:$A$1003,0)),"") -> Rustam Sattorov | D10: =IFERROR(INDEX('Lead Management'!$C$4:$C$1003,MATCH($B10,'Lead Management'!$A$4:$A$1003,0)),"") -> +992 97 221 1959 | E10: =IFERROR(INDEX('Lead Management'!$F$4:$F$1003,MATCH($B10,'Lead Management'!$A$4:$A$1003,0)),"") -> A4109611 | F10: Poland | G10: Construction Worker | H10: Stal-Bud Sp. z o.o. | I10: CTR-2026-007 | J10: 46094 | K10: Nilufar Karimova | L10: =IF($F10="","",IFERROR(INDEX(Settings!$B$18:$B$27,MATCH($F10,Settings!$A$18:$A$27,0)),"")) -> 22000 | M10: =IF($A10="","",SUMIFS(Finance!$E$4:$E$1003,Finance!$B$4:$B$1003,$A10,Finance!$J$4:$J$1003,"Paid")) -> 16500 | N10: =IF($A10="","",IFERROR($L10-$M10,"")) -> 5500 | O10: =IF($A10="","",IFERROR($M10/$L10,"")) -> 0.75 | P10: =IFERROR(INDEX('Process Tracking'!$E$5:$E$1003,MATCH($A10,'Process Tracking'!$A$5:$A$1003,0)),"") -> Visa Decision Pending | Q10: =IFERROR(INDEX(Documents!$Q$4:$Q$1003,MATCH($A10,Documents!$A$4:$A$1003,0)),"") -> 0.81818182 | R10: Active | S10: =IFERROR(INDEX('Lead Management'!$O$4:$O$1003,MATCH($B10,'Lead Management'!$A$4:$A$1003,0)),"") -> Instagram | T10: =IFERROR(INDEX('Lead Management'!$P$4:$P$1003,MATCH($B10,'Lead Management'!$A$4:$A$1003,0)),"") -> 46085
A11: CUS-008 | B11: LD-008 | C11: =IFERROR(INDEX('Lead Management'!$B$4:$B$1003,MATCH($B11,'Lead Management'!$A$4:$A$1003,0)),"") -> Dilnoza Aliyeva | D11: =IFERROR(INDEX('Lead Management'!$C$4:$C$1003,MATCH($B11,'Lead Management'!$A$4:$A$1003,0)),"") -> +992 90 224 2096 | E11: =IFERROR(INDEX('Lead Management'!$F$4:$F$1003,MATCH($B11,'Lead Management'!$A$4:$A$1003,0)),"") -> A4110984 | F11: Lithuania | G11: Warehouse Operator | H11: Baltic Logistics UAB | I11: CTR-2026-008 | J11: 46101 | K11: Jamshed Sattorov | L11: =IF($F11="","",IFERROR(INDEX(Settings!$B$18:$B$27,MATCH($F11,Settings!$A$18:$A$27,0)),"")) -> 21000 | M11: =IF($A11="","",SUMIFS(Finance!$E$4:$E$1003,Finance!$B$4:$B$1003,$A11,Finance!$J$4:$J$1003,"Paid")) -> 15750 | N11: =IF($A11="","",IFERROR($L11-$M11,"")) -> 5250 | O11: =IF($A11="","",IFERROR($M11/$L11,"")) -> 0.75 | P11: =IFERROR(INDEX('Process Tracking'!$E$5:$E$1003,MATCH($A11,'Process Tracking'!$A$5:$A$1003,0)),"") -> Visa Application Submitted | Q11: =IFERROR(INDEX(Documents!$Q$4:$Q$1003,MATCH($A11,Documents!$A$4:$A$1003,0)),"") -> 0.81818182 | R11: Active | S11: =IFERROR(INDEX('Lead Management'!$O$4:$O$1003,MATCH($B11,'Lead Management'!$A$4:$A$1003,0)),"") -> Instagram | T11: =IFERROR(INDEX('Lead Management'!$P$4:$P$1003,MATCH($B11,'Lead Management'!$A$4:$A$1003,0)),"") -> 46092
A12: CUS-009 | B12: LD-009 | C12: =IFERROR(INDEX('Lead Management'!$B$4:$B$1003,MATCH($B12,'Lead Management'!$A$4:$A$1003,0)),"") -> Sherali Yusupov | D12: =IFERROR(INDEX('Lead Management'!$C$4:$C$1003,MATCH($B12,'Lead Management'!$A$4:$A$1003,0)),"") -> +992 91 227 2233 | E12: =IFERROR(INDEX('Lead Management'!$F$4:$F$1003,MATCH($B12,'Lead Management'!$A$4:$A$1003,0)),"") -> A4112357 | F12: Czech Republic | G12: Plumber | H12: Moravia Logistic a.s. | I12: CTR-2026-009 | J12: 46108 | K12: Dilnoza Aliyeva | L12: =IF($F12="","",IFERROR(INDEX(Settings!$B$18:$B$27,MATCH($F12,Settings!$A$18:$A$27,0)),"")) -> 25000 | M12: =IF($A12="","",SUMIFS(Finance!$E$4:$E$1003,Finance!$B$4:$B$1003,$A12,Finance!$J$4:$J$1003,"Paid")) -> 12500 | N12: =IF($A12="","",IFERROR($L12-$M12,"")) -> 12500 | O12: =IF($A12="","",IFERROR($M12/$L12,"")) -> 0.5 | P12: =IFERROR(INDEX('Process Tracking'!$E$5:$E$1003,MATCH($A12,'Process Tracking'!$A$5:$A$1003,0)),"") -> Embassy Appointment Booked | Q12: =IFERROR(INDEX(Documents!$Q$4:$Q$1003,MATCH($A12,Documents!$A$4:$A$1003,0)),"") -> 0.81818182 | R12: Active | S12: =IFERROR(INDEX('Lead Management'!$O$4:$O$1003,MATCH($B12,'Lead Management'!$A$4:$A$1003,0)),"") -> Facebook | T12: =IFERROR(INDEX('Lead Management'!$P$4:$P$1003,MATCH($B12,'Lead Management'!$A$4:$A$1003,0)),"") -> 46099 | U12: Payment 3 is overdue, accountant notified.
A13: CUS-010 | B13: LD-010 | C13: =IFERROR(INDEX('Lead Management'!$B$4:$B$1003,MATCH($B13,'Lead Management'!$A$4:$A$1003,0)),"") -> Malika Ismoilova | D13: =IFERROR(INDEX('Lead Management'!$C$4:$C$1003,MATCH($B13,'Lead Management'!$A$4:$A$1003,0)),"") -> +992 92 230 2370 | E13: =IFERROR(INDEX('Lead Management'!$F$4:$F$1003,MATCH($B13,'Lead Management'!$A$4:$A$1003,0)),"") -> A4113730 | F13: Poland | G13: Painter | H13: Stal-Bud Sp. z o.o. | I13: CTR-2026-010 | J13: 46123 | K13: Nilufar Karimova | L13: =IF($F13="","",IFERROR(INDEX(Settings!$B$18:$B$27,MATCH($F13,Settings!$A$18:$A$27,0)),"")) -> 22000 | M13: =IF($A13="","",SUMIFS(Finance!$E$4:$E$1003,Finance!$B$4:$B$1003,$A13,Finance!$J$4:$J$1003,"Paid")) -> 16500 | N13: =IF($A13="","",IFERROR($L13-$M13,"")) -> 5500 | O13: =IF($A13="","",IFERROR($M13/$L13,"")) -> 0.75 | P13: =IFERROR(INDEX('Process Tracking'!$E$5:$E$1003,MATCH($A13,'Process Tracking'!$A$5:$A$1003,0)),"") -> Employment Contract Issued | Q13: =IFERROR(INDEX(Documents!$Q$4:$Q$1003,MATCH($A13,Documents!$A$4:$A$1003,0)),"") -> 0.81818182 | R13: Active | S13: =IFERROR(INDEX('Lead Management'!$O$4:$O$1003,MATCH($B13,'Lead Management'!$A$4:$A$1003,0)),"") -> Instagram | T13: =IFERROR(INDEX('Lead Management'!$P$4:$P$1003,MATCH($B13,'Lead Management'!$A$4:$A$1003,0)),"") -> 46114
A14: CUS-011 | B14: LD-011 | C14: =IFERROR(INDEX('Lead Management'!$B$4:$B$1003,MATCH($B14,'Lead Management'!$A$4:$A$1003,0)),"") -> Farrukh Davlatov | D14: =IFERROR(INDEX('Lead Management'!$C$4:$C$1003,MATCH($B14,'Lead Management'!$A$4:$A$1003,0)),"") -> +992 93 233 2507 | E14: =IFERROR(INDEX('Lead Management'!$F$4:$F$1003,MATCH($B14,'Lead Management'!$A$4:$A$1003,0)),"") -> A4115103 | F14: Hungary | G14: Agricultural Worker | H14: Duna Ipari Kft. | I14: CTR-2026-011 | J14: 46115 | K14: Jamshed Sattorov | L14: =IF($F14="","",IFERROR(INDEX(Settings!$B$18:$B$27,MATCH($F14,Settings!$A$18:$A$27,0)),"")) -> 23000 | M14: =IF($A14="","",SUMIFS(Finance!$E$4:$E$1003,Finance!$B$4:$B$1003,$A14,Finance!$J$4:$J$1003,"Paid")) -> 11500 | N14: =IF($A14="","",IFERROR($L14-$M14,"")) -> 11500 | O14: =IF($A14="","",IFERROR($M14/$L14,"")) -> 0.5 | P14: =IFERROR(INDEX('Process Tracking'!$E$5:$E$1003,MATCH($A14,'Process Tracking'!$A$5:$A$1003,0)),"") -> Documents Sent to Employer | Q14: =IFERROR(INDEX(Documents!$Q$4:$Q$1003,MATCH($A14,Documents!$A$4:$A$1003,0)),"") -> 0.63636364 | R14: Active | S14: =IFERROR(INDEX('Lead Management'!$O$4:$O$1003,MATCH($B14,'Lead Management'!$A$4:$A$1003,0)),"") -> Website | T14: =IFERROR(INDEX('Lead Management'!$P$4:$P$1003,MATCH($B14,'Lead Management'!$A$4:$A$1003,0)),"") -> 46106 | U14: Waiting for the apostilled diploma from the client.
A15: CUS-012 | B15: LD-012 | C15: =IFERROR(INDEX('Lead Management'!$B$4:$B$1003,MATCH($B15,'Lead Management'!$A$4:$A$1003,0)),"") -> Gulnora Safarova | D15: =IFERROR(INDEX('Lead Management'!$C$4:$C$1003,MATCH($B15,'Lead Management'!$A$4:$A$1003,0)),"") -> +992 94 236 2644 | E15: =IFERROR(INDEX('Lead Management'!$F$4:$F$1003,MATCH($B15,'Lead Management'!$A$4:$A$1003,0)),"") -> A4116476 | F15: Romania | G15: Cleaner | H15: Carpat Agro SRL | I15: CTR-2026-012 | J15: 46130 | K15: Dilnoza Aliyeva | L15: =IF($F15="","",IFERROR(INDEX(Settings!$B$18:$B$27,MATCH($F15,Settings!$A$18:$A$27,0)),"")) -> 19000 | M15: =IF($A15="","",SUMIFS(Finance!$E$4:$E$1003,Finance!$B$4:$B$1003,$A15,Finance!$J$4:$J$1003,"Paid")) -> 9500 | N15: =IF($A15="","",IFERROR($L15-$M15,"")) -> 9500 | O15: =IF($A15="","",IFERROR($M15/$L15,"")) -> 0.5 | P15: =IFERROR(INDEX('Process Tracking'!$E$5:$E$1003,MATCH($A15,'Process Tracking'!$A$5:$A$1003,0)),"") -> Documents Being Prepared | Q15: =IFERROR(INDEX(Documents!$Q$4:$Q$1003,MATCH($A15,Documents!$A$4:$A$1003,0)),"") -> 0.36363636 | R15: Active | S15: =IFERROR(INDEX('Lead Management'!$O$4:$O$1003,MATCH($B15,'Lead Management'!$A$4:$A$1003,0)),"") -> Referral | T15: =IFERROR(INDEX('Lead Management'!$P$4:$P$1003,MATCH($B15,'Lead Management'!$A$4:$A$1003,0)),"") -> 46121
C16: =IFERROR(INDEX('Lead Management'!$B$4:$B$1003,MATCH($B16,'Lead Management'!$A$4:$A$1003,0)),"") | D16: =IFERROR(INDEX('Lead Management'!$C$4:$C$1003,MATCH($B16,'Lead Management'!$A$4:$A$1003,0)),"") | E16: =IFERROR(INDEX('Lead Management'!$F$4:$F$1003,MATCH($B16,'Lead Management'!$A$4:$A$1003,0)),"") | L16: =IF($F16="","",IFERROR(INDEX(Settings!$B$18:$B$27,MATCH($F16,Settings!$A$18:$A$27,0)),"")) | M16: =IF($A16="","",SUMIFS(Finance!$E$4:$E$1003,Finance!$B$4:$B$1003,$A16,Finance!$J$4:$J$1003,"Paid")) | N16: =IF($A16="","",IFERROR($L16-$M16,"")) | O16: =IF($A16="","",IFERROR($M16/$L16,"")) | P16: =IFERROR(INDEX('Process Tracking'!$E$5:$E$1003,MATCH($A16,'Process Tracking'!$A$5:$A$1003,0)),"") | Q16: =IFERROR(INDEX(Documents!$Q$4:$Q$1003,MATCH($A16,Documents!$A$4:$A$1003,0)),"") | S16: =IFERROR(INDEX('Lead Management'!$O$4:$O$1003,MATCH($B16,'Lead Management'!$A$4:$A$1003,0)),"") | T16: =IFERROR(INDEX('Lead Management'!$P$4:$P$1003,MATCH($B16,'Lead Management'!$A$4:$A$1003,0)),"")
C17: =IFERROR(INDEX('Lead Management'!$B$4:$B$1003,MATCH($B17,'Lead Management'!$A$4:$A$1003,0)),"") | D17: =IFERROR(INDEX('Lead Management'!$C$4:$C$1003,MATCH($B17,'Lead Management'!$A$4:$A$1003,0)),"") | E17: =IFERROR(INDEX('Lead Management'!$F$4:$F$1003,MATCH($B17,'Lead Management'!$A$4:$A$1003,0)),"") | L17: =IF($F17="","",IFERROR(INDEX(Settings!$B$18:$B$27,MATCH($F17,Settings!$A$18:$A$27,0)),"")) | M17: =IF($A17="","",SUMIFS(Finance!$E$4:$E$1003,Finance!$B$4:$B$1003,$A17,Finance!$J$4:$J$1003,"Paid")) | N17: =IF($A17="","",IFERROR($L17-$M17,"")) | O17: =IF($A17="","",IFERROR($M17/$L17,"")) | P17: =IFERROR(INDEX('Process Tracking'!$E$5:$E$1003,MATCH($A17,'Process Tracking'!$A$5:$A$1003,0)),"") | Q17: =IFERROR(INDEX(Documents!$Q$4:$Q$1003,MATCH($A17,Documents!$A$4:$A$1003,0)),"") | S17: =IFERROR(INDEX('Lead Management'!$O$4:$O$1003,MATCH($B17,'Lead Management'!$A$4:$A$1003,0)),"") | T17: =IFERROR(INDEX('Lead Management'!$P$4:$P$1003,MATCH($B17,'Lead Management'!$A$4:$A$1003,0)),"")
C18: =IFERROR(INDEX('Lead Management'!$B$4:$B$1003,MATCH($B18,'Lead Management'!$A$4:$A$1003,0)),"") | D18: =IFERROR(INDEX('Lead Management'!$C$4:$C$1003,MATCH($B18,'Lead Management'!$A$4:$A$1003,0)),"") | E18: =IFERROR(INDEX('Lead Management'!$F$4:$F$1003,MATCH($B18,'Lead Management'!$A$4:$A$1003,0)),"") | L18: =IF($F18="","",IFERROR(INDEX(Settings!$B$18:$B$27,MATCH($F18,Settings!$A$18:$A$27,0)),"")) | M18: =IF($A18="","",SUMIFS(Finance!$E$4:$E$1003,Finance!$B$4:$B$1003,$A18,Finance!$J$4:$J$1003,"Paid")) | N18: =IF($A18="","",IFERROR($L18-$M18,"")) | O18: =IF($A18="","",IFERROR($M18/$L18,"")) | P18: =IFERROR(INDEX('Process Tracking'!$E$5:$E$1003,MATCH($A18,'Process Tracking'!$A$5:$A$1003,0)),"") | Q18: =IFERROR(INDEX(Documents!$Q$4:$Q$1003,MATCH($A18,Documents!$A$4:$A$1003,0)),"") | S18: =IFERROR(INDEX('Lead Management'!$O$4:$O$1003,MATCH($B18,'Lead Management'!$A$4:$A$1003,0)),"") | T18: =IFERROR(INDEX('Lead Management'!$P$4:$P$1003,MATCH($B18,'Lead Management'!$A$4:$A$1003,0)),"")
C19: =IFERROR(INDEX('Lead Management'!$B$4:$B$1003,MATCH($B19,'Lead Management'!$A$4:$A$1003,0)),"") | D19: =IFERROR(INDEX('Lead Management'!$C$4:$C$1003,MATCH($B19,'Lead Management'!$A$4:$A$1003,0)),"") | E19: =IFERROR(INDEX('Lead Management'!$F$4:$F$1003,MATCH($B19,'Lead Management'!$A$4:$A$1003,0)),"") | L19: =IF($F19="","",IFERROR(INDEX(Settings!$B$18:$B$27,MATCH($F19,Settings!$A$18:$A$27,0)),"")) | M19: =IF($A19="","",SUMIFS(Finance!$E$4:$E$1003,Finance!$B$4:$B$1003,$A19,Finance!$J$4:$J$1003,"Paid")) | N19: =IF($A19="","",IFERROR($L19-$M19,"")) | O19: =IF($A19="","",IFERROR($M19/$L19,"")) | P19: =IFERROR(INDEX('Process Tracking'!$E$5:$E$1003,MATCH($A19,'Process Tracking'!$A$5:$A$1003,0)),"") | Q19: =IFERROR(INDEX(Documents!$Q$4:$Q$1003,MATCH($A19,Documents!$A$4:$A$1003,0)),"") | S19: =IFERROR(INDEX('Lead Management'!$O$4:$O$1003,MATCH($B19,'Lead Management'!$A$4:$A$1003,0)),"") | T19: =IFERROR(INDEX('Lead Management'!$P$4:$P$1003,MATCH($B19,'Lead Management'!$A$4:$A$1003,0)),"")
C20: =IFERROR(INDEX('Lead Management'!$B$4:$B$1003,MATCH($B20,'Lead Management'!$A$4:$A$1003,0)),"") | D20: =IFERROR(INDEX('Lead Management'!$C$4:$C$1003,MATCH($B20,'Lead Management'!$A$4:$A$1003,0)),"") | E20: =IFERROR(INDEX('Lead Management'!$F$4:$F$1003,MATCH($B20,'Lead Management'!$A$4:$A$1003,0)),"") | L20: =IF($F20="","",IFERROR(INDEX(Settings!$B$18:$B$27,MATCH($F20,Settings!$A$18:$A$27,0)),"")) | M20: =IF($A20="","",SUMIFS(Finance!$E$4:$E$1003,Finance!$B$4:$B$1003,$A20,Finance!$J$4:$J$1003,"Paid")) | N20: =IF($A20="","",IFERROR($L20-$M20,"")) | O20: =IF($A20="","",IFERROR($M20/$L20,"")) | P20: =IFERROR(INDEX('Process Tracking'!$E$5:$E$1003,MATCH($A20,'Process Tracking'!$A$5:$A$1003,0)),"") | Q20: =IFERROR(INDEX(Documents!$Q$4:$Q$1003,MATCH($A20,Documents!$A$4:$A$1003,0)),"") | S20: =IFERROR(INDEX('Lead Management'!$O$4:$O$1003,MATCH($B20,'Lead Management'!$A$4:$A$1003,0)),"") | T20: =IFERROR(INDEX('Lead Management'!$P$4:$P$1003,MATCH($B20,'Lead Management'!$A$4:$A$1003,0)),"")
C21: =IFERROR(INDEX('Lead Management'!$B$4:$B$1003,MATCH($B21,'Lead Management'!$A$4:$A$1003,0)),"") | D21: =IFERROR(INDEX('Lead Management'!$C$4:$C$1003,MATCH($B21,'Lead Management'!$A$4:$A$1003,0)),"") | E21: =IFERROR(INDEX('Lead Management'!$F$4:$F$1003,MATCH($B21,'Lead Management'!$A$4:$A$1003,0)),"") | L21: =IF($F21="","",IFERROR(INDEX(Settings!$B$18:$B$27,MATCH($F21,Settings!$A$18:$A$27,0)),"")) | M21: =IF($A21="","",SUMIFS(Finance!$E$4:$E$1003,Finance!$B$4:$B$1003,$A21,Finance!$J$4:$J$1003,"Paid")) | N21: =IF($A21="","",IFERROR($L21-$M21,"")) | O21: =IF($A21="","",IFERROR($M21/$L21,"")) | P21: =IFERROR(INDEX('Process Tracking'!$E$5:$E$1003,MATCH($A21,'Process Tracking'!$A$5:$A$1003,0)),"") | Q21: =IFERROR(INDEX(Documents!$Q$4:$Q$1003,MATCH($A21,Documents!$A$4:$A$1003,0)),"") | S21: =IFERROR(INDEX('Lead Management'!$O$4:$O$1003,MATCH($B21,'Lead Management'!$A$4:$A$1003,0)),"") | T21: =IFERROR(INDEX('Lead Management'!$P$4:$P$1003,MATCH($B21,'Lead Management'!$A$4:$A$1003,0)),"")
C22: =IFERROR(INDEX('Lead Management'!$B$4:$B$1003,MATCH($B22,'Lead Management'!$A$4:$A$1003,0)),"") | D22: =IFERROR(INDEX('Lead Management'!$C$4:$C$1003,MATCH($B22,'Lead Management'!$A$4:$A$1003,0)),"") | E22: =IFERROR(INDEX('Lead Management'!$F$4:$F$1003,MATCH($B22,'Lead Management'!$A$4:$A$1003,0)),"") | L22: =IF($F22="","",IFERROR(INDEX(Settings!$B$18:$B$27,MATCH($F22,Settings!$A$18:$A$27,0)),"")) | M22: =IF($A22="","",SUMIFS(Finance!$E$4:$E$1003,Finance!$B$4:$B$1003,$A22,Finance!$J$4:$J$1003,"Paid")) | N22: =IF($A22="","",IFERROR($L22-$M22,"")) | O22: =IF($A22="","",IFERROR($M22/$L22,"")) | P22: =IFERROR(INDEX('Process Tracking'!$E$5:$E$1003,MATCH($A22,'Process Tracking'!$A$5:$A$1003,0)),"") | Q22: =IFERROR(INDEX(Documents!$Q$4:$Q$1003,MATCH($A22,Documents!$A$4:$A$1003,0)),"") | S22: =IFERROR(INDEX('Lead Management'!$O$4:$O$1003,MATCH($B22,'Lead Management'!$A$4:$A$1003,0)),"") | T22: =IFERROR(INDEX('Lead Management'!$P$4:$P$1003,MATCH($B22,'Lead Management'!$A$4:$A$1003,0)),"")
C23: =IFERROR(INDEX('Lead Management'!$B$4:$B$1003,MATCH($B23,'Lead Management'!$A$4:$A$1003,0)),"") | D23: =IFERROR(INDEX('Lead Management'!$C$4:$C$1003,MATCH($B23,'Lead Management'!$A$4:$A$1003,0)),"") | E23: =IFERROR(INDEX('Lead Management'!$F$4:$F$1003,MATCH($B23,'Lead Management'!$A$4:$A$1003,0)),"") | L23: =IF($F23="","",IFERROR(INDEX(Settings!$B$18:$B$27,MATCH($F23,Settings!$A$18:$A$27,0)),"")) | M23: =IF($A23="","",SUMIFS(Finance!$E$4:$E$1003,Finance!$B$4:$B$1003,$A23,Finance!$J$4:$J$1003,"Paid")) | N23: =IF($A23="","",IFERROR($L23-$M23,"")) | O23: =IF($A23="","",IFERROR($M23/$L23,"")) | P23: =IFERROR(INDEX('Process Tracking'!$E$5:$E$1003,MATCH($A23,'Process Tracking'!$A$5:$A$1003,0)),"") | Q23: =IFERROR(INDEX(Documents!$Q$4:$Q$1003,MATCH($A23,Documents!$A$4:$A$1003,0)),"") | S23: =IFERROR(INDEX('Lead Management'!$O$4:$O$1003,MATCH($B23,'Lead Management'!$A$4:$A$1003,0)),"") | T23: =IFERROR(INDEX('Lead Management'!$P$4:$P$1003,MATCH($B23,'Lead Management'!$A$4:$A$1003,0)),"")
C24: =IFERROR(INDEX('Lead Management'!$B$4:$B$1003,MATCH($B24,'Lead Management'!$A$4:$A$1003,0)),"") | D24: =IFERROR(INDEX('Lead Management'!$C$4:$C$1003,MATCH($B24,'Lead Management'!$A$4:$A$1003,0)),"") | E24: =IFERROR(INDEX('Lead Management'!$F$4:$F$1003,MATCH($B24,'Lead Management'!$A$4:$A$1003,0)),"") | L24: =IF($F24="","",IFERROR(INDEX(Settings!$B$18:$B$27,MATCH($F24,Settings!$A$18:$A$27,0)),"")) | M24: =IF($A24="","",SUMIFS(Finance!$E$4:$E$1003,Finance!$B$4:$B$1003,$A24,Finance!$J$4:$J$1003,"Paid")) | N24: =IF($A24="","",IFERROR($L24-$M24,"")) | O24: =IF($A24="","",IFERROR($M24/$L24,"")) | P24: =IFERROR(INDEX('Process Tracking'!$E$5:$E$1003,MATCH($A24,'Process Tracking'!$A$5:$A$1003,0)),"") | Q24: =IFERROR(INDEX(Documents!$Q$4:$Q$1003,MATCH($A24,Documents!$A$4:$A$1003,0)),"") | S24: =IFERROR(INDEX('Lead Management'!$O$4:$O$1003,MATCH($B24,'Lead Management'!$A$4:$A$1003,0)),"") | T24: =IFERROR(INDEX('Lead Management'!$P$4:$P$1003,MATCH($B24,'Lead Management'!$A$4:$A$1003,0)),"")
C25: =IFERROR(INDEX('Lead Management'!$B$4:$B$1003,MATCH($B25,'Lead Management'!$A$4:$A$1003,0)),"") | D25: =IFERROR(INDEX('Lead Management'!$C$4:$C$1003,MATCH($B25,'Lead Management'!$A$4:$A$1003,0)),"") | E25: =IFERROR(INDEX('Lead Management'!$F$4:$F$1003,MATCH($B25,'Lead Management'!$A$4:$A$1003,0)),"") | L25: =IF($F25="","",IFERROR(INDEX(Settings!$B$18:$B$27,MATCH($F25,Settings!$A$18:$A$27,0)),"")) | M25: =IF($A25="","",SUMIFS(Finance!$E$4:$E$1003,Finance!$B$4:$B$1003,$A25,Finance!$J$4:$J$1003,"Paid")) | N25: =IF($A25="","",IFERROR($L25-$M25,"")) | O25: =IF($A25="","",IFERROR($M25/$L25,"")) | P25: =IFERROR(INDEX('Process Tracking'!$E$5:$E$1003,MATCH($A25,'Process Tracking'!$A$5:$A$1003,0)),"") | Q25: =IFERROR(INDEX(Documents!$Q$4:$Q$1003,MATCH($A25,Documents!$A$4:$A$1003,0)),"") | S25: =IFERROR(INDEX('Lead Management'!$O$4:$O$1003,MATCH($B25,'Lead Management'!$A$4:$A$1003,0)),"") | T25: =IFERROR(INDEX('Lead Management'!$P$4:$P$1003,MATCH($B25,'Lead Management'!$A$4:$A$1003,0)),"")
C26: =IFERROR(INDEX('Lead Management'!$B$4:$B$1003,MATCH($B26,'Lead Management'!$A$4:$A$1003,0)),"") | D26: =IFERROR(INDEX('Lead Management'!$C$4:$C$1003,MATCH($B26,'Lead Management'!$A$4:$A$1003,0)),"") | E26: =IFERROR(INDEX('Lead Management'!$F$4:$F$1003,MATCH($B26,'Lead Management'!$A$4:$A$1003,0)),"") | L26: =IF($F26="","",IFERROR(INDEX(Settings!$B$18:$B$27,MATCH($F26,Settings!$A$18:$A$27,0)),"")) | M26: =IF($A26="","",SUMIFS(Finance!$E$4:$E$1003,Finance!$B$4:$B$1003,$A26,Finance!$J$4:$J$1003,"Paid")) | N26: =IF($A26="","",IFERROR($L26-$M26,"")) | O26: =IF($A26="","",IFERROR($M26/$L26,"")) | P26: =IFERROR(INDEX('Process Tracking'!$E$5:$E$1003,MATCH($A26,'Process Tracking'!$A$5:$A$1003,0)),"") | Q26: =IFERROR(INDEX(Documents!$Q$4:$Q$1003,MATCH($A26,Documents!$A$4:$A$1003,0)),"") | S26: =IFERROR(INDEX('Lead Management'!$O$4:$O$1003,MATCH($B26,'Lead Management'!$A$4:$A$1003,0)),"") | T26: =IFERROR(INDEX('Lead Management'!$P$4:$P$1003,MATCH($B26,'Lead Management'!$A$4:$A$1003,0)),"")
C27: =IFERROR(INDEX('Lead Management'!$B$4:$B$1003,MATCH($B27,'Lead Management'!$A$4:$A$1003,0)),"") | D27: =IFERROR(INDEX('Lead Management'!$C$4:$C$1003,MATCH($B27,'Lead Management'!$A$4:$A$1003,0)),"") | E27: =IFERROR(INDEX('Lead Management'!$F$4:$F$1003,MATCH($B27,'Lead Management'!$A$4:$A$1003,0)),"") | L27: =IF($F27="","",IFERROR(INDEX(Settings!$B$18:$B$27,MATCH($F27,Settings!$A$18:$A$27,0)),"")) | M27: =IF($A27="","",SUMIFS(Finance!$E$4:$E$1003,Finance!$B$4:$B$1003,$A27,Finance!$J$4:$J$1003,"Paid")) | N27: =IF($A27="","",IFERROR($L27-$M27,"")) | O27: =IF($A27="","",IFERROR($M27/$L27,"")) | P27: =IFERROR(INDEX('Process Tracking'!$E$5:$E$1003,MATCH($A27,'Process Tracking'!$A$5:$A$1003,0)),"") | Q27: =IFERROR(INDEX(Documents!$Q$4:$Q$1003,MATCH($A27,Documents!$A$4:$A$1003,0)),"") | S27: =IFERROR(INDEX('Lead Management'!$O$4:$O$1003,MATCH($B27,'Lead Management'!$A$4:$A$1003,0)),"") | T27: =IFERROR(INDEX('Lead Management'!$P$4:$P$1003,MATCH($B27,'Lead Management'!$A$4:$A$1003,0)),"")
... C203: =IFERROR(INDEX('Lead Management'!$B$4:$B$1003,MATCH($B203,'Lead Management'!$A$4:$A$1003,0)),"") | D203: =IFERROR(INDEX('Lead Management'!$C$4:$C$1003,MATCH($B203,'Lead Management'!$A$4:$A$1003,0)),"") | E203: =IFERROR(INDEX('Lead Management'!$F$4:$F$1003,MATCH($B203,'Lead Management'!$A$4:$A$1003,0)),"") | L203: =IF($F203="","",IFERROR(INDEX(Settings!$B$18:$B$27,MATCH($F203,Settings!$A$18:$A$27,0)),"")) | M203: =IF($A203="","",SUMIFS(Finance!$E$4:$E$1003,Finance!$B$4:$B$1003,$A203,Finance!$J$4:$J$1003,"Paid")) | N203: =IF($A203="","",IFERROR($L203-$M203,"")) | O203: =IF($A203="","",IFERROR($M203/$L203,"")) | P203: =IFERROR(INDEX('Process Tracking'!$E$5:$E$1003,MATCH($A203,'Process Tracking'!$A$5:$A$1003,0)),"") | Q203: =IFERROR(INDEX(Documents!$Q$4:$Q$1003,MATCH($A203,Documents!$A$4:$A$1003,0)),"") | S203: =IFERROR(INDEX('Lead Management'!$O$4:$O$1003,MATCH($B203,'Lead Management'!$A$4:$A$1003,0)),"") | T203: =IFERROR(INDEX('Lead Management'!$P$4:$P$1003,MATCH($B203,'Lead Management'!$A$4:$A$1003,0)),"")

Sheet Contracts
A1: VUSLAT RECRUITMENT COMPANY | CONTRACTS
A2: The four instalments are calculated from the package price and the percentages on the Settings sheet. Column M must read OK on every row.
A3: Contract No | B3: Customer ID | C3: Full Name | D3: Contract Date | E3: Destination Country | F3: Contract Type | G3: Package Price (TJS) | H3: Payment 1 - Contract | I3: Payment 2 - Documents | J3: Payment 3 - Work Permit | K3: Payment 4 - Visa Approved | L3: Total Scheduled (TJS) | M3: Check | N3: Signed By (Company) | O3: Contract Status | P3: Valid Until | Q3: Notes
A4: CTR-2026-001 | B4: CUS-001 | C4: =IFERROR(INDEX(Customers!$C$4:$C$1003,MATCH($B4,Customers!$A$4:$A$1003,0)),"") -> Firdavs Rahmonov | D4: 46039 | E4: =IFERROR(INDEX(Customers!$F$4:$F$1003,MATCH($B4,Customers!$A$4:$A$1003,0)),"") -> Poland | F4: Standard Employment Package | G4: =IFERROR(INDEX(Customers!$L$4:$L$1003,MATCH($B4,Customers!$A$4:$A$1003,0)),"") -> 22000 | H4: =IF($G4="","",$G4*Settings!$B$9) -> 6600 | I4: =IF($G4="","",$G4*Settings!$B$10) -> 4400 | J4: =IF($G4="","",$G4*Settings!$B$11) -> 5500 | K4: =IF($G4="","",$G4*Settings!$B$12) -> 5500 | L4: =IF($G4="","",SUM($H4:$K4)) -> 22000 | M4: =IF($G4="","",IF(ROUND($L4,2)=ROUND($G4,2),"OK","MISMATCH")) -> OK | N4: Farrukh Rahmonov | O4: Completed | P4: =IF($D4="","",EDATE($D4,12)) -> 46404
A5: CTR-2026-002 | B5: CUS-002 | C5: =IFERROR(INDEX(Customers!$C$4:$C$1003,MATCH($B5,Customers!$A$4:$A$1003,0)),"") -> Nilufar Sharipova | D5: 46046 | E5: =IFERROR(INDEX(Customers!$F$4:$F$1003,MATCH($B5,Customers!$A$4:$A$1003,0)),"") -> Germany | F5: Premium Employment Package | G5: =IFERROR(INDEX(Customers!$L$4:$L$1003,MATCH($B5,Customers!$A$4:$A$1003,0)),"") -> 32000 | H5: =IF($G5="","",$G5*Settings!$B$9) -> 9600 | I5: =IF($G5="","",$G5*Settings!$B$10) -> 6400 | J5: =IF($G5="","",$G5*Settings!$B$11) -> 8000 | K5: =IF($G5="","",$G5*Settings!$B$12) -> 8000 | L5: =IF($G5="","",SUM($H5:$K5)) -> 32000 | M5: =IF($G5="","",IF(ROUND($L5,2)=ROUND($G5,2),"OK","MISMATCH")) -> OK | N5: Farrukh Rahmonov | O5: Completed | P5: =IF($D5="","",EDATE($D5,12)) -> 46411
A6: CTR-2026-003 | B6: CUS-003 | C6: =IFERROR(INDEX(Customers!$C$4:$C$1003,MATCH($B6,Customers!$A$4:$A$1003,0)),"") -> Jamshed Karimov | D6: 46067 | E6: =IFERROR(INDEX(Customers!$F$4:$F$1003,MATCH($B6,Customers!$A$4:$A$1003,0)),"") -> Czech Republic | F6: Standard Employment Package | G6: =IFERROR(INDEX(Customers!$L$4:$L$1003,MATCH($B6,Customers!$A$4:$A$1003,0)),"") -> 25000 | H6: =IF($G6="","",$G6*Settings!$B$9) -> 7500 | I6: =IF($G6="","",$G6*Settings!$B$10) -> 5000 | J6: =IF($G6="","",$G6*Settings!$B$11) -> 6250 | K6: =IF($G6="","",$G6*Settings!$B$12) -> 6250 | L6: =IF($G6="","",SUM($H6:$K6)) -> 25000 | M6: =IF($G6="","",IF(ROUND($L6,2)=ROUND($G6,2),"OK","MISMATCH")) -> OK | N6: Farrukh Rahmonov | O6: Active | P6: =IF($D6="","",EDATE($D6,12)) -> 46432
A7: CTR-2026-004 | B7: CUS-004 | C7: =IFERROR(INDEX(Customers!$C$4:$C$1003,MATCH($B7,Customers!$A$4:$A$1003,0)),"") -> Zarina Nazriyeva | D7: 46074 | E7: =IFERROR(INDEX(Customers!$F$4:$F$1003,MATCH($B7,Customers!$A$4:$A$1003,0)),"") -> Poland | F7: Standard Employment Package | G7: =IFERROR(INDEX(Customers!$L$4:$L$1003,MATCH($B7,Customers!$A$4:$A$1003,0)),"") -> 22000 | H7: =IF($G7="","",$G7*Settings!$B$9) -> 6600 | I7: =IF($G7="","",$G7*Settings!$B$10) -> 4400 | J7: =IF($G7="","",$G7*Settings!$B$11) -> 5500 | K7: =IF($G7="","",$G7*Settings!$B$12) -> 5500 | L7: =IF($G7="","",SUM($H7:$K7)) -> 22000 | M7: =IF($G7="","",IF(ROUND($L7,2)=ROUND($G7,2),"OK","MISMATCH")) -> OK | N7: Farrukh Rahmonov | O7: Active | P7: =IF($D7="","",EDATE($D7,12)) -> 46439
A8: CTR-2026-005 | B8: CUS-005 | C8: =IFERROR(INDEX(Customers!$C$4:$C$1003,MATCH($B8,Customers!$A$4:$A$1003,0)),"") -> Bakhtiyor Umarov | D8: 46053 | E8: =IFERROR(INDEX(Customers!$F$4:$F$1003,MATCH($B8,Customers!$A$4:$A$1003,0)),"") -> Slovakia | F8: Standard Employment Package | G8: =IFERROR(INDEX(Customers!$L$4:$L$1003,MATCH($B8,Customers!$A$4:$A$1003,0)),"") -> 24000 | H8: =IF($G8="","",$G8*Settings!$B$9) -> 7200 | I8: =IF($G8="","",$G8*Settings!$B$10) -> 4800 | J8: =IF($G8="","",$G8*Settings!$B$11) -> 6000 | K8: =IF($G8="","",$G8*Settings!$B$12) -> 6000 | L8: =IF($G8="","",SUM($H8:$K8)) -> 24000 | M8: =IF($G8="","",IF(ROUND($L8,2)=ROUND($G8,2),"OK","MISMATCH")) -> OK | N8: Farrukh Rahmonov | O8: Active | P8: =IF($D8="","",EDATE($D8,12)) -> 46418
A9: CTR-2026-006 | B9: CUS-006 | C9: =IFERROR(INDEX(Customers!$C$4:$C$1003,MATCH($B9,Customers!$A$4:$A$1003,0)),"") -> Manizha Qodirova | D9: 46080 | E9: =IFERROR(INDEX(Customers!$F$4:$F$1003,MATCH($B9,Customers!$A$4:$A$1003,0)),"") -> Germany | F9: Premium Employment Package | G9: =IFERROR(INDEX(Customers!$L$4:$L$1003,MATCH($B9,Customers!$A$4:$A$1003,0)),"") -> 32000 | H9: =IF($G9="","",$G9*Settings!$B$9) -> 9600 | I9: =IF($G9="","",$G9*Settings!$B$10) -> 6400 | J9: =IF($G9="","",$G9*Settings!$B$11) -> 8000 | K9: =IF($G9="","",$G9*Settings!$B$12) -> 8000 | L9: =IF($G9="","",SUM($H9:$K9)) -> 32000 | M9: =IF($G9="","",IF(ROUND($L9,2)=ROUND($G9,2),"OK","MISMATCH")) -> OK | N9: Farrukh Rahmonov | O9: Terminated | P9: =IF($D9="","",EDATE($D9,12)) -> 46445 | Q9: Terminated after the visa refusal.
A10: CTR-2026-007 | B10: CUS-007 | C10: =IFERROR(INDEX(Customers!$C$4:$C$1003,MATCH($B10,Customers!$A$4:$A$1003,0)),"") -> Rustam Sattorov | D10: 46094 | E10: =IFERROR(INDEX(Customers!$F$4:$F$1003,MATCH($B10,Customers!$A$4:$A$1003,0)),"") -> Poland | F10: Standard Employment Package | G10: =IFERROR(INDEX(Customers!$L$4:$L$1003,MATCH($B10,Customers!$A$4:$A$1003,0)),"") -> 22000 | H10: =IF($G10="","",$G10*Settings!$B$9) -> 6600 | I10: =IF($G10="","",$G10*Settings!$B$10) -> 4400 | J10: =IF($G10="","",$G10*Settings!$B$11) -> 5500 | K10: =IF($G10="","",$G10*Settings!$B$12) -> 5500 | L10: =IF($G10="","",SUM($H10:$K10)) -> 22000 | M10: =IF($G10="","",IF(ROUND($L10,2)=ROUND($G10,2),"OK","MISMATCH")) -> OK | N10: Farrukh Rahmonov | O10: Active | P10: =IF($D10="","",EDATE($D10,12)) -> 46459
A11: CTR-2026-008 | B11: CUS-008 | C11: =IFERROR(INDEX(Customers!$C$4:$C$1003,MATCH($B11,Customers!$A$4:$A$1003,0)),"") -> Dilnoza Aliyeva | D11: 46101 | E11: =IFERROR(INDEX(Customers!$F$4:$F$1003,MATCH($B11,Customers!$A$4:$A$1003,0)),"") -> Lithuania | F11: Standard Employment Package | G11: =IFERROR(INDEX(Customers!$L$4:$L$1003,MATCH($B11,Customers!$A$4:$A$1003,0)),"") -> 21000 | H11: =IF($G11="","",$G11*Settings!$B$9) -> 6300 | I11: =IF($G11="","",$G11*Settings!$B$10) -> 4200 | J11: =IF($G11="","",$G11*Settings!$B$11) -> 5250 | K11: =IF($G11="","",$G11*Settings!$B$12) -> 5250 | L11: =IF($G11="","",SUM($H11:$K11)) -> 21000 | M11: =IF($G11="","",IF(ROUND($L11,2)=ROUND($G11,2),"OK","MISMATCH")) -> OK | N11: Farrukh Rahmonov | O11: Active | P11: =IF($D11="","",EDATE($D11,12)) -> 46466
A12: CTR-2026-009 | B12: CUS-009 | C12: =IFERROR(INDEX(Customers!$C$4:$C$1003,MATCH($B12,Customers!$A$4:$A$1003,0)),"") -> Sherali Yusupov | D12: 46108 | E12: =IFERROR(INDEX(Customers!$F$4:$F$1003,MATCH($B12,Customers!$A$4:$A$1003,0)),"") -> Czech Republic | F12: Standard Employment Package | G12: =IFERROR(INDEX(Customers!$L$4:$L$1003,MATCH($B12,Customers!$A$4:$A$1003,0)),"") -> 25000 | H12: =IF($G12="","",$G12*Settings!$B$9) -> 7500 | I12: =IF($G12="","",$G12*Settings!$B$10) -> 5000 | J12: =IF($G12="","",$G12*Settings!$B$11) -> 6250 | K12: =IF($G12="","",$G12*Settings!$B$12) -> 6250 | L12: =IF($G12="","",SUM($H12:$K12)) -> 25000 | M12: =IF($G12="","",IF(ROUND($L12,2)=ROUND($G12,2),"OK","MISMATCH")) -> OK | N12: Farrukh Rahmonov | O12: Active | P12: =IF($D12="","",EDATE($D12,12)) -> 46473
A13: CTR-2026-010 | B13: CUS-010 | C13: =IFERROR(INDEX(Customers!$C$4:$C$1003,MATCH($B13,Customers!$A$4:$A$1003,0)),"") -> Malika Ismoilova | D13: 46123 | E13: =IFERROR(INDEX(Customers!$F$4:$F$1003,MATCH($B13,Customers!$A$4:$A$1003,0)),"") -> Poland | F13: Standard Employment Package | G13: =IFERROR(INDEX(Customers!$L$4:$L$1003,MATCH($B13,Customers!$A$4:$A$1003,0)),"") -> 22000 | H13: =IF($G13="","",$G13*Settings!$B$9) -> 6600 | I13: =IF($G13="","",$G13*Settings!$B$10) -> 4400 | J13: =IF($G13="","",$G13*Settings!$B$11) -> 5500 | K13: =IF($G13="","",$G13*Settings!$B$12) -> 5500 | L13: =IF($G13="","",SUM($H13:$K13)) -> 22000 | M13: =IF($G13="","",IF(ROUND($L13,2)=ROUND($G13,2),"OK","MISMATCH")) -> OK | N13: Farrukh Rahmonov | O13: Active | P13: =IF($D13="","",EDATE($D13,12)) -> 46488
A14: CTR-2026-011 | B14: CUS-011 | C14: =IFERROR(INDEX(Customers!$C$4:$C$1003,MATCH($B14,Customers!$A$4:$A$1003,0)),"") -> Farrukh Davlatov | D14: 46115 | E14: =IFERROR(INDEX(Customers!$F$4:$F$1003,MATCH($B14,Customers!$A$4:$A$1003,0)),"") -> Hungary | F14: Standard Employment Package | G14: =IFERROR(INDEX(Customers!$L$4:$L$1003,MATCH($B14,Customers!$A$4:$A$1003,0)),"") -> 23000 | H14: =IF($G14="","",$G14*Settings!$B$9) -> 6900 | I14: =IF($G14="","",$G14*Settings!$B$10) -> 4600 | J14: =IF($G14="","",$G14*Settings!$B$11) -> 5750 | K14: =IF($G14="","",$G14*Settings!$B$12) -> 5750 | L14: =IF($G14="","",SUM($H14:$K14)) -> 23000 | M14: =IF($G14="","",IF(ROUND($L14,2)=ROUND($G14,2),"OK","MISMATCH")) -> OK | N14: Farrukh Rahmonov | O14: Active | P14: =IF($D14="","",EDATE($D14,12)) -> 46480
A15: CTR-2026-012 | B15: CUS-012 | C15: =IFERROR(INDEX(Customers!$C$4:$C$1003,MATCH($B15,Customers!$A$4:$A$1003,0)),"") -> Gulnora Safarova | D15: 46130 | E15: =IFERROR(INDEX(Customers!$F$4:$F$1003,MATCH($B15,Customers!$A$4:$A$1003,0)),"") -> Romania | F15: Standard Employment Package | G15: =IFERROR(INDEX(Customers!$L$4:$L$1003,MATCH($B15,Customers!$A$4:$A$1003,0)),"") -> 19000 | H15: =IF($G15="","",$G15*Settings!$B$9) -> 5700 | I15: =IF($G15="","",$G15*Settings!$B$10) -> 3800 | J15: =IF($G15="","",$G15*Settings!$B$11) -> 4750 | K15: =IF($G15="","",$G15*Settings!$B$12) -> 4750 | L15: =IF($G15="","",SUM($H15:$K15)) -> 19000 | M15: =IF($G15="","",IF(ROUND($L15,2)=ROUND($G15,2),"OK","MISMATCH")) -> OK | N15: Farrukh Rahmonov | O15: Active | P15: =IF($D15="","",EDATE($D15,12)) -> 46495
C16: =IFERROR(INDEX(Customers!$C$4:$C$1003,MATCH($B16,Customers!$A$4:$A$1003,0)),"") | E16: =IFERROR(INDEX(Customers!$F$4:$F$1003,MATCH($B16,Customers!$A$4:$A$1003,0)),"") | G16: =IFERROR(INDEX(Customers!$L$4:$L$1003,MATCH($B16,Customers!$A$4:$A$1003,0)),"") | H16: =IF($G16="","",$G16*Settings!$B$9) | I16: =IF($G16="","",$G16*Settings!$B$10) | J16: =IF($G16="","",$G16*Settings!$B$11) | K16: =IF($G16="","",$G16*Settings!$B$12) | L16: =IF($G16="","",SUM($H16:$K16)) | M16: =IF($G16="","",IF(ROUND($L16,2)=ROUND($G16,2),"OK","MISMATCH")) | P16: =IF($D16="","",EDATE($D16,12))
C17: =IFERROR(INDEX(Customers!$C$4:$C$1003,MATCH($B17,Customers!$A$4:$A$1003,0)),"") | E17: =IFERROR(INDEX(Customers!$F$4:$F$1003,MATCH($B17,Customers!$A$4:$A$1003,0)),"") | G17: =IFERROR(INDEX(Customers!$L$4:$L$1003,MATCH($B17,Customers!$A$4:$A$1003,0)),"") | H17: =IF($G17="","",$G17*Settings!$B$9) | I17: =IF($G17="","",$G17*Settings!$B$10) | J17: =IF($G17="","",$G17*Settings!$B$11) | K17: =IF($G17="","",$G17*Settings!$B$12) | L17: =IF($G17="","",SUM($H17:$K17)) | M17: =IF($G17="","",IF(ROUND($L17,2)=ROUND($G17,2),"OK","MISMATCH")) | P17: =IF($D17="","",EDATE($D17,12))
C18: =IFERROR(INDEX(Customers!$C$4:$C$1003,MATCH($B18,Customers!$A$4:$A$1003,0)),"") | E18: =IFERROR(INDEX(Customers!$F$4:$F$1003,MATCH($B18,Customers!$A$4:$A$1003,0)),"") | G18: =IFERROR(INDEX(Customers!$L$4:$L$1003,MATCH($B18,Customers!$A$4:$A$1003,0)),"") | H18: =IF($G18="","",$G18*Settings!$B$9) | I18: =IF($G18="","",$G18*Settings!$B$10) | J18: =IF($G18="","",$G18*Settings!$B$11) | K18: =IF($G18="","",$G18*Settings!$B$12) | L18: =IF($G18="","",SUM($H18:$K18)) | M18: =IF($G18="","",IF(ROUND($L18,2)=ROUND($G18,2),"OK","MISMATCH")) | P18: =IF($D18="","",EDATE($D18,12))
C19: =IFERROR(INDEX(Customers!$C$4:$C$1003,MATCH($B19,Customers!$A$4:$A$1003,0)),"") | E19: =IFERROR(INDEX(Customers!$F$4:$F$1003,MATCH($B19,Customers!$A$4:$A$1003,0)),"") | G19: =IFERROR(INDEX(Customers!$L$4:$L$1003,MATCH($B19,Customers!$A$4:$A$1003,0)),"") | H19: =IF($G19="","",$G19*Settings!$B$9) | I19: =IF($G19="","",$G19*Settings!$B$10) | J19: =IF($G19="","",$G19*Settings!$B$11) | K19: =IF($G19="","",$G19*Settings!$B$12) | L19: =IF($G19="","",SUM($H19:$K19)) | M19: =IF($G19="","",IF(ROUND($L19,2)=ROUND($G19,2),"OK","MISMATCH")) | P19: =IF($D19="","",EDATE($D19,12))
C20: =IFERROR(INDEX(Customers!$C$4:$C$1003,MATCH($B20,Customers!$A$4:$A$1003,0)),"") | E20: =IFERROR(INDEX(Customers!$F$4:$F$1003,MATCH($B20,Customers!$A$4:$A$1003,0)),"") | G20: =IFERROR(INDEX(Customers!$L$4:$L$1003,MATCH($B20,Customers!$A$4:$A$1003,0)),"") | H20: =IF($G20="","",$G20*Settings!$B$9) | I20: =IF($G20="","",$G20*Settings!$B$10) | J20: =IF($G20="","",$G20*Settings!$B$11) | K20: =IF($G20="","",$G20*Settings!$B$12) | L20: =IF($G20="","",SUM($H20:$K20)) | M20: =IF($G20="","",IF(ROUND($L20,2)=ROUND($G20,2),"OK","MISMATCH")) | P20: =IF($D20="","",EDATE($D20,12))
C21: =IFERROR(INDEX(Customers!$C$4:$C$1003,MATCH($B21,Customers!$A$4:$A$1003,0)),"") | E21: =IFERROR(INDEX(Customers!$F$4:$F$1003,MATCH($B21,Customers!$A$4:$A$1003,0)),"") | G21: =IFERROR(INDEX(Customers!$L$4:$L$1003,MATCH($B21,Customers!$A$4:$A$1003,0)),"") | H21: =IF($G21="","",$G21*Settings!$B$9) | I21: =IF($G21="","",$G21*Settings!$B$10) | J21: =IF($G21="","",$G21*Settings!$B$11) | K21: =IF($G21="","",$G21*Settings!$B$12) | L21: =IF($G21="","",SUM($H21:$K21)) | M21: =IF($G21="","",IF(ROUND($L21,2)=ROUND($G21,2),"OK","MISMATCH")) | P21: =IF($D21="","",EDATE($D21,12))
C22: =IFERROR(INDEX(Customers!$C$4:$C$1003,MATCH($B22,Customers!$A$4:$A$1003,0)),"") | E22: =IFERROR(INDEX(Customers!$F$4:$F$1003,MATCH($B22,Customers!$A$4:$A$1003,0)),"") | G22: =IFERROR(INDEX(Customers!$L$4:$L$1003,MATCH($B22,Customers!$A$4:$A$1003,0)),"") | H22: =IF($G22="","",$G22*Settings!$B$9) | I22: =IF($G22="","",$G22*Settings!$B$10) | J22: =IF($G22="","",$G22*Settings!$B$11) | K22: =IF($G22="","",$G22*Settings!$B$12) | L22: =IF($G22="","",SUM($H22:$K22)) | M22: =IF($G22="","",IF(ROUND($L22,2)=ROUND($G22,2),"OK","MISMATCH")) | P22: =IF($D22="","",EDATE($D22,12))
C23: =IFERROR(INDEX(Customers!$C$4:$C$1003,MATCH($B23,Customers!$A$4:$A$1003,0)),"") | E23: =IFERROR(INDEX(Customers!$F$4:$F$1003,MATCH($B23,Customers!$A$4:$A$1003,0)),"") | G23: =IFERROR(INDEX(Customers!$L$4:$L$1003,MATCH($B23,Customers!$A$4:$A$1003,0)),"") | H23: =IF($G23="","",$G23*Settings!$B$9) | I23: =IF($G23="","",$G23*Settings!$B$10) | J23: =IF($G23="","",$G23*Settings!$B$11) | K23: =IF($G23="","",$G23*Settings!$B$12) | L23: =IF($G23="","",SUM($H23:$K23)) | M23: =IF($G23="","",IF(ROUND($L23,2)=ROUND($G23,2),"OK","MISMATCH")) | P23: =IF($D23="","",EDATE($D23,12))
C24: =IFERROR(INDEX(Customers!$C$4:$C$1003,MATCH($B24,Customers!$A$4:$A$1003,0)),"") | E24: =IFERROR(INDEX(Customers!$F$4:$F$1003,MATCH($B24,Customers!$A$4:$A$1003,0)),"") | G24: =IFERROR(INDEX(Customers!$L$4:$L$1003,MATCH($B24,Customers!$A$4:$A$1003,0)),"") | H24: =IF($G24="","",$G24*Settings!$B$9) | I24: =IF($G24="","",$G24*Settings!$B$10) | J24: =IF($G24="","",$G24*Settings!$B$11) | K24: =IF($G24="","",$G24*Settings!$B$12) | L24: =IF($G24="","",SUM($H24:$K24)) | M24: =IF($G24="","",IF(ROUND($L24,2)=ROUND($G24,2),"OK","MISMATCH")) | P24: =IF($D24="","",EDATE($D24,12))
C25: =IFERROR(INDEX(Customers!$C$4:$C$1003,MATCH($B25,Customers!$A$4:$A$1003,0)),"") | E25: =IFERROR(INDEX(Customers!$F$4:$F$1003,MATCH($B25,Customers!$A$4:$A$1003,0)),"") | G25: =IFERROR(INDEX(Customers!$L$4:$L$1003,MATCH($B25,Customers!$A$4:$A$1003,0)),"") | H25: =IF($G25="","",$G25*Settings!$B$9) | I25: =IF($G25="","",$G25*Settings!$B$10) | J25: =IF($G25="","",$G25*Settings!$B$11) | K25: =IF($G25="","",$G25*Settings!$B$12) | L25: =IF($G25="","",SUM($H25:$K25)) | M25: =IF($G25="","",IF(ROUND($L25,2)=ROUND($G25,2),"OK","MISMATCH")) | P25: =IF($D25="","",EDATE($D25,12))
C26: =IFERROR(INDEX(Customers!$C$4:$C$1003,MATCH($B26,Customers!$A$4:$A$1003,0)),"") | E26: =IFERROR(INDEX(Customers!$F$4:$F$1003,MATCH($B26,Customers!$A$4:$A$1003,0)),"") | G26: =IFERROR(INDEX(Customers!$L$4:$L$1003,MATCH($B26,Customers!$A$4:$A$1003,0)),"") | H26: =IF($G26="","",$G26*Settings!$B$9) | I26: =IF($G26="","",$G26*Settings!$B$10) | J26: =IF($G26="","",$G26*Settings!$B$11) | K26: =IF($G26="","",$G26*Settings!$B$12) | L26: =IF($G26="","",SUM($H26:$K26)) | M26: =IF($G26="","",IF(ROUND($L26,2)=ROUND($G26,2),"OK","MISMATCH")) | P26: =IF($D26="","",EDATE($D26,12))
C27: =IFERROR(INDEX(Customers!$C$4:$C$1003,MATCH($B27,Customers!$A$4:$A$1003,0)),"") | E27: =IFERROR(INDEX(Customers!$F$4:$F$1003,MATCH($B27,Customers!$A$4:$A$1003,0)),"") | G27: =IFERROR(INDEX(Customers!$L$4:$L$1003,MATCH($B27,Customers!$A$4:$A$1003,0)),"") | H27: =IF($G27="","",$G27*Settings!$B$9) | I27: =IF($G27="","",$G27*Settings!$B$10) | J27: =IF($G27="","",$G27*Settings!$B$11) | K27: =IF($G27="","",$G27*Settings!$B$12) | L27: =IF($G27="","",SUM($H27:$K27)) | M27: =IF($G27="","",IF(ROUND($L27,2)=ROUND($G27,2),"OK","MISMATCH")) | P27: =IF($D27="","",EDATE($D27,12))
... C203: =IFERROR(INDEX(Customers!$C$4:$C$1003,MATCH($B203,Customers!$A$4:$A$1003,0)),"") | E203: =IFERROR(INDEX(Customers!$F$4:$F$1003,MATCH($B203,Customers!$A$4:$A$1003,0)),"") | G203: =IFERROR(INDEX(Customers!$L$4:$L$1003,MATCH($B203,Customers!$A$4:$A$1003,0)),"") | H203: =IF($G203="","",$G203*Settings!$B$9) | I203: =IF($G203="","",$G203*Settings!$B$10) | J203: =IF($G203="","",$G203*Settings!$B$11) | K203: =IF($G203="","",$G203*Settings!$B$12) | L203: =IF($G203="","",SUM($H203:$K203)) | M203: =IF($G203="","",IF(ROUND($L203,2)=ROUND($G203,2),"OK","MISMATCH")) | P203: =IF($D203="","",EDATE($D203,12))

Sheet Process Tracking
A1: VUSLAT RECRUITMENT COMPANY | PROCESS TRACKING
A2: The 14-stage customer pipeline. Set each stage to Completed / In Progress / Pending / Blocked / N-A, and enter the completion date in the Date column. Current Stage, Progress and Case Outcome update automatically. Progress is measured against the 13 stages of the successful route (Visa Rejected is the alternative branch, so a rejected case stops at 10 of 13).
A3: CUSTOMER & CASE SUMMARY (calculated) | J3: 1. Contract Signed | N3: 2. Documents Being Prepared | R3: 3. Documents Completed | V3: 4. Documents Sent to Employer | Z3: 5. Work Permit Issued | AD3: 6. Employment Contract Issued | AH3: 7. Embassy Appointment Booked | AL3: 8. Visa Application Submitted | AP3: 9. Visa Decision Pending | AT3: 10. Visa Approved | AX3: 11. Visa Rejected | BB3: 12. Flight Ticket Prepared | BF3: 13. Customer Departed to Europe | BJ3: 14. Case Completed
A4: Customer ID | B4: Full Name | C4: Destination Country | D4: Assigned Manager | E4: Current Stage | F4: Stages Completed | G4: Progress | H4: Case Outcome | I4: Days in Process | J4: Status | K4: Date | L4: Responsible | M4: Comments | N4: Status | O4: Date | P4: Responsible | Q4: Comments | R4: Status | S4: Date | T4: Responsible | U4: Comments | V4: Status | W4: Date | X4: Responsible | Y4: Comments | Z4: Status | AA4: Date | AB4: Responsible | AC4: Comments | AD4: Status | AE4: Date | AF4: Responsible | AG4: Comments | AH4: Status | AI4: Date | AJ4: Responsible | AK4: Comments | AL4: Status | AM4: Date | AN4: Responsible | AO4: Comments | AP4: Status | AQ4: Date | AR4: Responsible | AS4: Comments | AT4: Status | AU4: Date | AV4: Responsible | AW4: Comments | AX4: Status | AY4: Date | AZ4: Responsible | BA4: Comments | BB4: Status | BC4: Date | BD4: Responsible | BE4: Comments | BF4: Status | BG4: Date | BH4: Responsible | BI4: Comments | BJ4: Status | BK4: Date | BL4: Responsible | BM4: Comments
A5: CUS-001 | B5: =IFERROR(INDEX(Customers!$C$4:$C$1003,MATCH($A5,Customers!$A$4:$A$1003,0)),"") -> Firdavs Rahmonov | C5: =IFERROR(INDEX(Customers!$F$4:$F$1003,MATCH($A5,Customers!$A$4:$A$1003,0)),"") -> Poland | D5: =IFERROR(INDEX(Customers!$K$4:$K$1003,MATCH($A5,Customers!$A$4:$A$1003,0)),"") -> Nilufar Karimova | E5: =IF($A5="","",IF($F5=0,"Not Started",IF($BJ5="Completed",Settings!$U$45,IF($BF5="Completed",Settings!$U$44,IF($BB5="Completed",Settings!$U$43,IF($AX5="Completed",Settings!$U$42,IF($AT5="Completed",Settings!$U$41,IF($AP5="Completed",Settings!$U$40,IF($AL5="Completed",Settings!$U$39,IF($AH5="Completed",Settings!$U$38,IF($AD5="Completed",Settings!$U$37,IF($Z5="Completed",Settings!$U$36,IF($V5="Completed",Settings!$U$35,IF($R5="Completed",Settings!$U$34,IF($N5="Completed",Settings!$U$33,IF($J5="Completed",Settings!$U$32,"")))))))))))))))) -> Case Completed | F5: =IF($A5="","",COUNTIF($J5:$BM5,"Completed")) -> 13 | G5: =IF($A5="","",MIN($F5/13,1)) -> 1 | H5: =IF($A5="","",IF($BJ5="Completed","Case Completed",IF($AX5="Completed","Visa Rejected",IF($BF5="Completed","Departed to Europe",IF($F5=0,"Not Started","In Progress"))))) -> Case Completed | I5: =IF($K5="","",IF($BK5<>"",$BK5-$K5,IF($AY5<>"",$AY5-$K5,TODAY()-$K5))) -> 115 | J5: Completed | K5: 46039 | L5: Nilufar Karimova | M5: Contract signed in the Dushanbe office. | N5: Completed | O5: 46044 | P5: Bakhtiyor Umarov | R5: Completed | S5: 46059 | T5: Bakhtiyor Umarov | V5: Completed | W5: 46064 | X5: Bakhtiyor Umarov | Z5: Completed | AA5: 46084 | AB5: Dilnoza Aliyeva | AC5: Work permit received from the employer. | AD5: Completed | AE5: 46091 | AF5: Dilnoza Aliyeva | AH5: Completed | AI5: 46099 | AJ5: Bakhtiyor Umarov | AL5: Completed | AM5: 46109 | AN5: Bakhtiyor Umarov | AO5: Application lodged at the embassy. | AP5: Completed | AQ5: 46114 | AR5: Bakhtiyor Umarov | AT5: Completed | AU5: 46134 | AV5: Bakhtiyor Umarov | AW5: Visa sticker issued. | AX5: N/A | BB5: Completed | BC5: 46139 | BD5: Dilnoza Aliyeva | BF5: Completed | BG5: 46146 | BH5: Dilnoza Aliyeva | BI5: Departure flight confirmed. | BJ5: Completed | BK5: 46154 | BL5: Farrukh Rahmonov | BM5: All obligations closed, file archived.
A6: CUS-002 | B6: =IFERROR(INDEX(Customers!$C$4:$C$1003,MATCH($A6,Customers!$A$4:$A$1003,0)),"") -> Nilufar Sharipova | C6: =IFERROR(INDEX(Customers!$F$4:$F$1003,MATCH($A6,Customers!$A$4:$A$1003,0)),"") -> Germany | D6: =IFERROR(INDEX(Customers!$K$4:$K$1003,MATCH($A6,Customers!$A$4:$A$1003,0)),"") -> Jamshed Sattorov | E6: =IF($A6="","",IF($F6=0,"Not Started",IF($BJ6="Completed",Settings!$U$45,IF($BF6="Completed",Settings!$U$44,IF($BB6="Completed",Settings!$U$43,IF($AX6="Completed",Settings!$U$42,IF($AT6="Completed",Settings!$U$41,IF($AP6="Completed",Settings!$U$40,IF($AL6="Completed",Settings!$U$39,IF($AH6="Completed",Settings!$U$38,IF($AD6="Completed",Settings!$U$37,IF($Z6="Completed",Settings!$U$36,IF($V6="Completed",Settings!$U$35,IF($R6="Completed",Settings!$U$34,IF($N6="Completed",Settings!$U$33,IF($J6="Completed",Settings!$U$32,"")))))))))))))))) -> Case Completed | F6: =IF($A6="","",COUNTIF($J6:$BM6,"Completed")) -> 13 | G6: =IF($A6="","",MIN($F6/13,1)) -> 1 | H6: =IF($A6="","",IF($BJ6="Completed","Case Completed",IF($AX6="Completed","Visa Rejected",IF($BF6="Completed","Departed to Europe",IF($F6=0,"Not Started","In Progress"))))) -> Case Completed | I6: =IF($K6="","",IF($BK6<>"",$BK6-$K6,IF($AY6<>"",$AY6-$K6,TODAY()-$K6))) -> 115 | J6: Completed | K6: 46046 | L6: Jamshed Sattorov | M6: Contract signed in the Dushanbe office. | N6: Completed | O6: 46051 | P6: Bakhtiyor Umarov | R6: Completed | S6: 46066 | T6: Bakhtiyor Umarov | V6: Completed | W6: 46071 | X6: Bakhtiyor Umarov | Z6: Completed | AA6: 46091 | AB6: Dilnoza Aliyeva | AC6: Work permit received from the employer. | AD6: Completed | AE6: 46098 | AF6: Dilnoza Aliyeva | AH6: Completed | AI6: 46106 | AJ6: Bakhtiyor Umarov | AL6: Completed | AM6: 46116 | AN6: Bakhtiyor Umarov | AO6: Application lodged at the embassy. | AP6: Completed | AQ6: 46121 | AR6: Bakhtiyor Umarov | AT6: Completed | AU6: 46141 | AV6: Bakhtiyor Umarov | AW6: Visa sticker issued. | AX6: N/A | BB6: Completed | BC6: 46146 | BD6: Dilnoza Aliyeva | BF6: Completed | BG6: 46153 | BH6: Dilnoza Aliyeva | BI6: Departure flight confirmed. | BJ6: Completed | BK6: 46161 | BL6: Farrukh Rahmonov | BM6: All obligations closed, file archived.
A7: CUS-003 | B7: =IFERROR(INDEX(Customers!$C$4:$C$1003,MATCH($A7,Customers!$A$4:$A$1003,0)),"") -> Jamshed Karimov | C7: =IFERROR(INDEX(Customers!$F$4:$F$1003,MATCH($A7,Customers!$A$4:$A$1003,0)),"") -> Czech Republic | D7: =IFERROR(INDEX(Customers!$K$4:$K$1003,MATCH($A7,Customers!$A$4:$A$1003,0)),"") -> Dilnoza Aliyeva | E7: =IF($A7="","",IF($F7=0,"Not Started",IF($BJ7="Completed",Settings!$U$45,IF($BF7="Completed",Settings!$U$44,IF($BB7="Completed",Settings!$U$43,IF($AX7="Completed",Settings!$U$42,IF($AT7="Completed",Settings!$U$41,IF($AP7="Completed",Settings!$U$40,IF($AL7="Completed",Settings!$U$39,IF($AH7="Completed",Settings!$U$38,IF($AD7="Completed",Settings!$U$37,IF($Z7="Completed",Settings!$U$36,IF($V7="Completed",Settings!$U$35,IF($R7="Completed",Settings!$U$34,IF($N7="Completed",Settings!$U$33,IF($J7="Completed",Settings!$U$32,"")))))))))))))))) -> Customer Departed to Europe | F7: =IF($A7="","",COUNTIF($J7:$BM7,"Completed")) -> 12 | G7: =IF($A7="","",MIN($F7/13,1)) -> 0.92307692 | H7: =IF($A7="","",IF($BJ7="Completed","Case Completed",IF($AX7="Completed","Visa Rejected",IF($BF7="Completed","Departed to Europe",IF($F7=0,"Not Started","In Progress"))))) -> Departed to Europe | I7: =IF($K7="","",IF($BK7<>"",$BK7-$K7,IF($AY7<>"",$AY7-$K7,TODAY()-$K7))) -> 166 | J7: Completed | K7: 46067 | L7: Dilnoza Aliyeva | M7: Contract signed in the Dushanbe office. | N7: Completed | O7: 46072 | P7: Bakhtiyor Umarov | R7: Completed | S7: 46087 | T7: Bakhtiyor Umarov | V7: Completed | W7: 46092 | X7: Bakhtiyor Umarov | Z7: Completed | AA7: 46112 | AB7: Dilnoza Aliyeva | AC7: Work permit received from the employer. | AD7: Completed | AE7: 46119 | AF7: Dilnoza Aliyeva | AH7: Completed | AI7: 46127 | AJ7: Bakhtiyor Umarov | AL7: Completed | AM7: 46137 | AN7: Bakhtiyor Umarov | AO7: Application lodged at the embassy. | AP7: Completed | AQ7: 46142 | AR7: Bakhtiyor Umarov | AT7: Completed | AU7: 46162 | AV7: Bakhtiyor Umarov | AW7: Visa sticker issued. | AX7: N/A | BB7: Completed | BC7: 46167 | BD7: Dilnoza Aliyeva | BF7: Completed | BG7: 46174 | BH7: Dilnoza Aliyeva | BI7: Departure flight confirmed. | BJ7: In Progress | BL7: Farrukh Rahmonov | BM7: Stage in progress.
A8: CUS-004 | B8: =IFERROR(INDEX(Customers!$C$4:$C$1003,MATCH($A8,Customers!$A$4:$A$1003,0)),"") -> Zarina Nazriyeva | C8: =IFERROR(INDEX(Customers!$F$4:$F$1003,MATCH($A8,Customers!$A$4:$A$1003,0)),"") -> Poland | D8: =IFERROR(INDEX(Customers!$K$4:$K$1003,MATCH($A8,Customers!$A$4:$A$1003,0)),"") -> Nilufar Karimova | E8: =IF($A8="","",IF($F8=0,"Not Started",IF($BJ8="Completed",Settings!$U$45,IF($BF8="Completed",Settings!$U$44,IF($BB8="Completed",Settings!$U$43,IF($AX8="Completed",Settings!$U$42,IF($AT8="Completed",Settings!$U$41,IF($AP8="Completed",Settings!$U$40,IF($AL8="Completed",Settings!$U$39,IF($AH8="Completed",Settings!$U$38,IF($AD8="Completed",Settings!$U$37,IF($Z8="Completed",Settings!$U$36,IF($V8="Completed",Settings!$U$35,IF($R8="Completed",Settings!$U$34,IF($N8="Completed",Settings!$U$33,IF($J8="Completed",Settings!$U$32,"")))))))))))))))) -> Flight Ticket Prepared | F8: =IF($A8="","",COUNTIF($J8:$BM8,"Completed")) -> 11 | G8: =IF($A8="","",MIN($F8/13,1)) -> 0.84615385 | H8: =IF($A8="","",IF($BJ8="Completed","Case Completed",IF($AX8="Completed","Visa Rejected",IF($BF8="Completed","Departed to Europe",IF($F8=0,"Not Started","In Progress"))))) -> In Progress | I8: =IF($K8="","",IF($BK8<>"",$BK8-$K8,IF($AY8<>"",$AY8-$K8,TODAY()-$K8))) -> 159 | J8: Completed | K8: 46074 | L8: Nilufar Karimova | M8: Contract signed in the Dushanbe office. | N8: Completed | O8: 46079 | P8: Bakhtiyor Umarov | R8: Completed | S8: 46094 | T8: Bakhtiyor Umarov | V8: Completed | W8: 46099 | X8: Bakhtiyor Umarov | Z8: Completed | AA8: 46119 | AB8: Dilnoza Aliyeva | AC8: Work permit received from the employer. | AD8: Completed | AE8: 46126 | AF8: Dilnoza Aliyeva | AH8: Completed | AI8: 46134 | AJ8: Bakhtiyor Umarov | AL8: Completed | AM8: 46144 | AN8: Bakhtiyor Umarov | AO8: Application lodged at the embassy. | AP8: Completed | AQ8: 46149 | AR8: Bakhtiyor Umarov | AT8: Completed | AU8: 46169 | AV8: Bakhtiyor Umarov | AW8: Visa sticker issued. | AX8: N/A | BB8: Completed | BC8: 46174 | BD8: Dilnoza Aliyeva | BF8: In Progress | BH8: Dilnoza Aliyeva | BI8: Stage in progress. | BJ8: Pending
A9: CUS-005 | B9: =IFERROR(INDEX(Customers!$C$4:$C$1003,MATCH($A9,Customers!$A$4:$A$1003,0)),"") -> Bakhtiyor Umarov | C9: =IFERROR(INDEX(Customers!$F$4:$F$1003,MATCH($A9,Customers!$A$4:$A$1003,0)),"") -> Slovakia | D9: =IFERROR(INDEX(Customers!$K$4:$K$1003,MATCH($A9,Customers!$A$4:$A$1003,0)),"") -> Jamshed Sattorov | E9: =IF($A9="","",IF($F9=0,"Not Started",IF($BJ9="Completed",Settings!$U$45,IF($BF9="Completed",Settings!$U$44,IF($BB9="Completed",Settings!$U$43,IF($AX9="Completed",Settings!$U$42,IF($AT9="Completed",Settings!$U$41,IF($AP9="Completed",Settings!$U$40,IF($AL9="Completed",Settings!$U$39,IF($AH9="Completed",Settings!$U$38,IF($AD9="Completed",Settings!$U$37,IF($Z9="Completed",Settings!$U$36,IF($V9="Completed",Settings!$U$35,IF($R9="Completed",Settings!$U$34,IF($N9="Completed",Settings!$U$33,IF($J9="Completed",Settings!$U$32,"")))))))))))))))) -> Visa Approved | F9: =IF($A9="","",COUNTIF($J9:$BM9,"Completed")) -> 10 | G9: =IF($A9="","",MIN($F9/13,1)) -> 0.76923077 | H9: =IF($A9="","",IF($BJ9="Completed","Case Completed",IF($AX9="Completed","Visa Rejected",IF($BF9="Completed","Departed to Europe",IF($F9=0,"Not Started","In Progress"))))) -> In Progress | I9: =IF($K9="","",IF($BK9<>"",$BK9-$K9,IF($AY9<>"",$AY9-$K9,TODAY()-$K9))) -> 180 | J9: Completed | K9: 46053 | L9: Jamshed Sattorov | M9: Contract signed in the Dushanbe office. | N9: Completed | O9: 46058 | P9: Bakhtiyor Umarov | R9: Completed | S9: 46073 | T9: Bakhtiyor Umarov | V9: Completed | W9: 46078 | X9: Bakhtiyor Umarov | Z9: Completed | AA9: 46098 | AB9: Dilnoza Aliyeva | AC9: Work permit received from the employer. | AD9: Completed | AE9: 46105 | AF9: Dilnoza Aliyeva | AH9: Completed | AI9: 46113 | AJ9: Bakhtiyor Umarov | AL9: Completed | AM9: 46123 | AN9: Bakhtiyor Umarov | AO9: Application lodged at the embassy. | AP9: Completed | AQ9: 46128 | AR9: Bakhtiyor Umarov | AT9: Completed | AU9: 46148 | AV9: Bakhtiyor Umarov | AW9: Visa sticker issued. | AX9: N/A | BB9: In Progress | BD9: Dilnoza Aliyeva | BE9: Stage in progress. | BF9: Pending | BJ9: Pending
A10: CUS-006 | B10: =IFERROR(INDEX(Customers!$C$4:$C$1003,MATCH($A10,Customers!$A$4:$A$1003,0)),"") -> Manizha Qodirova | C10: =IFERROR(INDEX(Customers!$F$4:$F$1003,MATCH($A10,Customers!$A$4:$A$1003,0)),"") -> Germany | D10: =IFERROR(INDEX(Customers!$K$4:$K$1003,MATCH($A10,Customers!$A$4:$A$1003,0)),"") -> Dilnoza Aliyeva | E10: =IF($A10="","",IF($F10=0,"Not Started",IF($BJ10="Completed",Settings!$U$45,IF($BF10="Completed",Settings!$U$44,IF($BB10="Completed",Settings!$U$43,IF($AX10="Completed",Settings!$U$42,IF($AT10="Completed",Settings!$U$41,IF($AP10="Completed",Settings!$U$40,IF($AL10="Completed",Settings!$U$39,IF($AH10="Completed",Settings!$U$38,IF($AD10="Completed",Settings!$U$37,IF($Z10="Completed",Settings!$U$36,IF($V10="Completed",Settings!$U$35,IF($R10="Completed",Settings!$U$34,IF($N10="Completed",Settings!$U$33,IF($J10="Completed",Settings!$U$32,"")))))))))))))))) -> Visa Rejected | F10: =IF($A10="","",COUNTIF($J10:$BM10,"Completed")) -> 10 | G10: =IF($A10="","",MIN($F10/13,1)) -> 0.76923077 | H10: =IF($A10="","",IF($BJ10="Completed","Case Completed",IF($AX10="Completed","Visa Rejected",IF($BF10="Completed","Departed to Europe",IF($F10=0,"Not Started","In Progress"))))) -> Visa Rejected | I10: =IF($K10="","",IF($BK10<>"",$BK10-$K10,IF($AY10<>"",$AY10-$K10,TODAY()-$K10))) -> 95 | J10: Completed | K10: 46080 | L10: Dilnoza Aliyeva | M10: Contract signed in the Dushanbe office. | N10: Completed | O10: 46085 | P10: Bakhtiyor Umarov | R10: Completed | S10: 46100 | T10: Bakhtiyor Umarov | V10: Completed | W10: 46105 | X10: Bakhtiyor Umarov | Z10: Completed | AA10: 46125 | AB10: Dilnoza Aliyeva | AC10: Work permit received from the employer. | AD10: Completed | AE10: 46132 | AF10: Dilnoza Aliyeva | AH10: Completed | AI10: 46140 | AJ10: Bakhtiyor Umarov | AL10: Completed | AM10: 46150 | AN10: Bakhtiyor Umarov | AO10: Application lodged at the embassy. | AP10: Completed | AQ10: 46155 | AR10: Bakhtiyor Umarov | AT10: N/A | AX10: Completed | AY10: 46175 | AZ10: Bakhtiyor Umarov | BA10: Refusal received - client informed. | BB10: N/A | BF10: N/A | BJ10: N/A
A11: CUS-007 | B11: =IFERROR(INDEX(Customers!$C$4:$C$1003,MATCH($A11,Customers!$A$4:$A$1003,0)),"") -> Rustam Sattorov | C11: =IFERROR(INDEX(Customers!$F$4:$F$1003,MATCH($A11,Customers!$A$4:$A$1003,0)),"") -> Poland | D11: =IFERROR(INDEX(Customers!$K$4:$K$1003,MATCH($A11,Customers!$A$4:$A$1003,0)),"") -> Nilufar Karimova | E11: =IF($A11="","",IF($F11=0,"Not Started",IF($BJ11="Completed",Settings!$U$45,IF($BF11="Completed",Settings!$U$44,IF($BB11="Completed",Settings!$U$43,IF($AX11="Completed",Settings!$U$42,IF($AT11="Completed",Settings!$U$41,IF($AP11="Completed",Settings!$U$40,IF($AL11="Completed",Settings!$U$39,IF($AH11="Completed",Settings!$U$38,IF($AD11="Completed",Settings!$U$37,IF($Z11="Completed",Settings!$U$36,IF($V11="Completed",Settings!$U$35,IF($R11="Completed",Settings!$U$34,IF($N11="Completed",Settings!$U$33,IF($J11="Completed",Settings!$U$32,"")))))))))))))))) -> Visa Decision Pending | F11: =IF($A11="","",COUNTIF($J11:$BM11,"Completed")) -> 9 | G11: =IF($A11="","",MIN($F11/13,1)) -> 0.69230769 | H11: =IF($A11="","",IF($BJ11="Completed","Case Completed",IF($AX11="Completed","Visa Rejected",IF($BF11="Completed","Departed to Europe",IF($F11=0,"Not Started","In Progress"))))) -> In Progress | I11: =IF($K11="","",IF($BK11<>"",$BK11-$K11,IF($AY11<>"",$AY11-$K11,TODAY()-$K11))) -> 139 | J11: Completed | K11: 46094 | L11: Nilufar Karimova | M11: Contract signed in the Dushanbe office. | N11: Completed | O11: 46099 | P11: Bakhtiyor Umarov | R11: Completed | S11: 46114 | T11: Bakhtiyor Umarov | V11: Completed | W11: 46119 | X11: Bakhtiyor Umarov | Z11: Completed | AA11: 46139 | AB11: Dilnoza Aliyeva | AC11: Work permit received from the employer. | AD11: Completed | AE11: 46146 | AF11: Dilnoza Aliyeva | AH11: Completed | AI11: 46154 | AJ11: Bakhtiyor Umarov | AL11: Completed | AM11: 46164 | AN11: Bakhtiyor Umarov | AO11: Application lodged at the embassy. | AP11: Completed | AQ11: 46169 | AR11: Bakhtiyor Umarov | AT11: In Progress | AV11: Bakhtiyor Umarov | AW11: Stage in progress. | AX11: Pending | BB11: Pending | BF11: Pending | BJ11: Pending
A12: CUS-008 | B12: =IFERROR(INDEX(Customers!$C$4:$C$1003,MATCH($A12,Customers!$A$4:$A$1003,0)),"") -> Dilnoza Aliyeva | C12: =IFERROR(INDEX(Customers!$F$4:$F$1003,MATCH($A12,Customers!$A$4:$A$1003,0)),"") -> Lithuania | D12: =IFERROR(INDEX(Customers!$K$4:$K$1003,MATCH($A12,Customers!$A$4:$A$1003,0)),"") -> Jamshed Sattorov | E12: =IF($A12="","",IF($F12=0,"Not Started",IF($BJ12="Completed",Settings!$U$45,IF($BF12="Completed",Settings!$U$44,IF($BB12="Completed",Settings!$U$43,IF($AX12="Completed",Settings!$U$42,IF($AT12="Completed",Settings!$U$41,IF($AP12="Completed",Settings!$U$40,IF($AL12="Completed",Settings!$U$39,IF($AH12="Completed",Settings!$U$38,IF($AD12="Completed",Settings!$U$37,IF($Z12="Completed",Settings!$U$36,IF($V12="Completed",Settings!$U$35,IF($R12="Completed",Settings!$U$34,IF($N12="Completed",Settings!$U$33,IF($J12="Completed",Settings!$U$32,"")))))))))))))))) -> Visa Application Submitted | F12: =IF($A12="","",COUNTIF($J12:$BM12,"Completed")) -> 8 | G12: =IF($A12="","",MIN($F12/13,1)) -> 0.61538462 | H12: =IF($A12="","",IF($BJ12="Completed","Case Completed",IF($AX12="Completed","Visa Rejected",IF($BF12="Completed","Departed to Europe",IF($F12=0,"Not Started","In Progress"))))) -> In Progress | I12: =IF($K12="","",IF($BK12<>"",$BK12-$K12,IF($AY12<>"",$AY12-$K12,TODAY()-$K12))) -> 132 | J12: Completed | K12: 46101 | L12: Jamshed Sattorov | M12: Contract signed in the Dushanbe office. | N12: Completed | O12: 46106 | P12: Bakhtiyor Umarov | R12: Completed | S12: 46121 | T12: Bakhtiyor Umarov | V12: Completed | W12: 46126 | X12: Bakhtiyor Umarov | Z12: Completed | AA12: 46146 | AB12: Dilnoza Aliyeva | AC12: Work permit received from the employer. | AD12: Completed | AE12: 46153 | AF12: Dilnoza Aliyeva | AH12: Completed | AI12: 46161 | AJ12: Bakhtiyor Umarov | AL12: Completed | AM12: 46171 | AN12: Bakhtiyor Umarov | AO12: Application lodged at the embassy. | AP12: In Progress | AR12: Bakhtiyor Umarov | AS12: Stage in progress. | AT12: Pending | AX12: Pending | BB12: Pending | BF12: Pending | BJ12: Pending
A13: CUS-009 | B13: =IFERROR(INDEX(Customers!$C$4:$C$1003,MATCH($A13,Customers!$A$4:$A$1003,0)),"") -> Sherali Yusupov | C13: =IFERROR(INDEX(Customers!$F$4:$F$1003,MATCH($A13,Customers!$A$4:$A$1003,0)),"") -> Czech Republic | D13: =IFERROR(INDEX(Customers!$K$4:$K$1003,MATCH($A13,Customers!$A$4:$A$1003,0)),"") -> Dilnoza Aliyeva | E13: =IF($A13="","",IF($F13=0,"Not Started",IF($BJ13="Completed",Settings!$U$45,IF($BF13="Completed",Settings!$U$44,IF($BB13="Completed",Settings!$U$43,IF($AX13="Completed",Settings!$U$42,IF($AT13="Completed",Settings!$U$41,IF($AP13="Completed",Settings!$U$40,IF($AL13="Completed",Settings!$U$39,IF($AH13="Completed",Settings!$U$38,IF($AD13="Completed",Settings!$U$37,IF($Z13="Completed",Settings!$U$36,IF($V13="Completed",Settings!$U$35,IF($R13="Completed",Settings!$U$34,IF($N13="Completed",Settings!$U$33,IF($J13="Completed",Settings!$U$32,"")))))))))))))))) -> Embassy Appointment Booked | F13: =IF($A13="","",COUNTIF($J13:$BM13,"Completed")) -> 7 | G13: =IF($A13="","",MIN($F13/13,1)) -> 0.53846154 | H13: =IF($A13="","",IF($BJ13="Completed","Case Completed",IF($AX13="Completed","Visa Rejected",IF($BF13="Completed","Departed to Europe",IF($F13=0,"Not Started","In Progress"))))) -> In Progress | I13: =IF($K13="","",IF($BK13<>"",$BK13-$K13,IF($AY13<>"",$AY13-$K13,TODAY()-$K13))) -> 125 | J13: Completed | K13: 46108 | L13: Dilnoza Aliyeva | M13: Contract signed in the Dushanbe office. | N13: Completed | O13: 46113 | P13: Bakhtiyor Umarov | R13: Completed | S13: 46128 | T13: Bakhtiyor Umarov | V13: Completed | W13: 46133 | X13: Bakhtiyor Umarov | Z13: Completed | AA13: 46153 | AB13: Dilnoza Aliyeva | AC13: Work permit received from the employer. | AD13: Completed | AE13: 46160 | AF13: Dilnoza Aliyeva | AH13: Completed | AI13: 46168 | AJ13: Bakhtiyor Umarov | AL13: In Progress | AN13: Bakhtiyor Umarov | AO13: Stage in progress. | AP13: Pending | AT13: Pending | AX13: Pending | BB13: Pending | BF13: Pending | BJ13: Pending
A14: CUS-010 | B14: =IFERROR(INDEX(Customers!$C$4:$C$1003,MATCH($A14,Customers!$A$4:$A$1003,0)),"") -> Malika Ismoilova | C14: =IFERROR(INDEX(Customers!$F$4:$F$1003,MATCH($A14,Customers!$A$4:$A$1003,0)),"") -> Poland | D14: =IFERROR(INDEX(Customers!$K$4:$K$1003,MATCH($A14,Customers!$A$4:$A$1003,0)),"") -> Nilufar Karimova | E14: =IF($A14="","",IF($F14=0,"Not Started",IF($BJ14="Completed",Settings!$U$45,IF($BF14="Completed",Settings!$U$44,IF($BB14="Completed",Settings!$U$43,IF($AX14="Completed",Settings!$U$42,IF($AT14="Completed",Settings!$U$41,IF($AP14="Completed",Settings!$U$40,IF($AL14="Completed",Settings!$U$39,IF($AH14="Completed",Settings!$U$38,IF($AD14="Completed",Settings!$U$37,IF($Z14="Completed",Settings!$U$36,IF($V14="Completed",Settings!$U$35,IF($R14="Completed",Settings!$U$34,IF($N14="Completed",Settings!$U$33,IF($J14="Completed",Settings!$U$32,"")))))))))))))))) -> Employment Contract Issued | F14: =IF($A14="","",COUNTIF($J14:$BM14,"Completed")) -> 6 | G14: =IF($A14="","",MIN($F14/13,1)) -> 0.46153846 | H14: =IF($A14="","",IF($BJ14="Completed","Case Completed",IF($AX14="Completed","Visa Rejected",IF($BF14="Completed","Departed to Europe",IF($F14=0,"Not Started","In Progress"))))) -> In Progress | I14: =IF($K14="","",IF($BK14<>"",$BK14-$K14,IF($AY14<>"",$AY14-$K14,TODAY()-$K14))) -> 110 | J14: Completed | K14: 46123 | L14: Nilufar Karimova | M14: Contract signed in the Dushanbe office. | N14: Completed | O14: 46128 | P14: Bakhtiyor Umarov | R14: Completed | S14: 46143 | T14: Bakhtiyor Umarov | V14: Completed | W14: 46148 | X14: Bakhtiyor Umarov | Z14: Completed | AA14: 46168 | AB14: Dilnoza Aliyeva | AC14: Work permit received from the employer. | AD14: Completed | AE14: 46175 | AF14: Dilnoza Aliyeva | AH14: In Progress | AJ14: Bakhtiyor Umarov | AK14: Stage in progress. | AL14: Pending | AP14: Pending | AT14: Pending | AX14: Pending | BB14: Pending | BF14: Pending | BJ14: Pending
A15: CUS-011 | B15: =IFERROR(INDEX(Customers!$C$4:$C$1003,MATCH($A15,Customers!$A$4:$A$1003,0)),"") -> Farrukh Davlatov | C15: =IFERROR(INDEX(Customers!$F$4:$F$1003,MATCH($A15,Customers!$A$4:$A$1003,0)),"") -> Hungary | D15: =IFERROR(INDEX(Customers!$K$4:$K$1003,MATCH($A15,Customers!$A$4:$A$1003,0)),"") -> Jamshed Sattorov | E15: =IF($A15="","",IF($F15=0,"Not Started",IF($BJ15="Completed",Settings!$U$45,IF($BF15="Completed",Settings!$U$44,IF($BB15="Completed",Settings!$U$43,IF($AX15="Completed",Settings!$U$42,IF($AT15="Completed",Settings!$U$41,IF($AP15="Completed",Settings!$U$40,IF($AL15="Completed",Settings!$U$39,IF($AH15="Completed",Settings!$U$38,IF($AD15="Completed",Settings!$U$37,IF($Z15="Completed",Settings!$U$36,IF($V15="Completed",Settings!$U$35,IF($R15="Completed",Settings!$U$34,IF($N15="Completed",Settings!$U$33,IF($J15="Completed",Settings!$U$32,"")))))))))))))))) -> Documents Sent to Employer | F15: =IF($A15="","",COUNTIF($J15:$BM15,"Completed")) -> 4 | G15: =IF($A15="","",MIN($F15/13,1)) -> 0.30769231 | H15: =IF($A15="","",IF($BJ15="Completed","Case Completed",IF($AX15="Completed","Visa Rejected",IF($BF15="Completed","Departed to Europe",IF($F15=0,"Not Started","In Progress"))))) -> In Progress | I15: =IF($K15="","",IF($BK15<>"",$BK15-$K15,IF($AY15<>"",$AY15-$K15,TODAY()-$K15))) -> 118 | J15: Completed | K15: 46115 | L15: Jamshed Sattorov | M15: Contract signed in the Dushanbe office. | N15: Completed | O15: 46120 | P15: Bakhtiyor Umarov | R15: Completed | S15: 46135 | T15: Bakhtiyor Umarov | V15: Completed | W15: 46140 | X15: Bakhtiyor Umarov | Z15: In Progress | AB15: Dilnoza Aliyeva | AC15: Stage in progress. | AD15: Pending | AH15: Pending | AL15: Pending | AP15: Pending | AT15: Pending | AX15: Pending | BB15: Pending | BF15: Pending | BJ15: Pending
A16: CUS-012 | B16: =IFERROR(INDEX(Customers!$C$4:$C$1003,MATCH($A16,Customers!$A$4:$A$1003,0)),"") -> Gulnora Safarova | C16: =IFERROR(INDEX(Customers!$F$4:$F$1003,MATCH($A16,Customers!$A$4:$A$1003,0)),"") -> Romania | D16: =IFERROR(INDEX(Customers!$K$4:$K$1003,MATCH($A16,Customers!$A$4:$A$1003,0)),"") -> Dilnoza Aliyeva | E16: =IF($A16="","",IF($F16=0,"Not Started",IF($BJ16="Completed",Settings!$U$45,IF($BF16="Completed",Settings!$U$44,IF($BB16="Completed",Settings!$U$43,IF($AX16="Completed",Settings!$U$42,IF($AT16="Completed",Settings!$U$41,IF($AP16="Completed",Settings!$U$40,IF($AL16="Completed",Settings!$U$39,IF($AH16="Completed",Settings!$U$38,IF($AD16="Completed",Settings!$U$37,IF($Z16="Completed",Settings!$U$36,IF($V16="Completed",Settings!$U$35,IF($R16="Completed",Settings!$U$34,IF($N16="Completed",Settings!$U$33,IF($J16="Completed",Settings!$U$32,"")))))))))))))))) -> Documents Being Prepared | F16: =IF($A16="","",COUNTIF($J16:$BM16,"Completed")) -> 2 | G16: =IF($A16="","",MIN($F16/13,1)) -> 0.15384615 | H16: =IF($A16="","",IF($BJ16="Completed","Case Completed",IF($AX16="Completed","Visa Rejected",IF($BF16="Completed","Departed to Europe",IF($F16=0,"Not Started","In Progress"))))) -> In Progress | I16: =IF($K16="","",IF($BK16<>"",$BK16-$K16,IF($AY16<>"",$AY16-$K16,TODAY()-$K16))) -> 103 | J16: Completed | K16: 46130 | L16: Dilnoza Aliyeva | M16: Contract signed in the Dushanbe office. | N16: Completed | O16: 46135 | P16: Bakhtiyor Umarov | R16: In Progress | T16: Bakhtiyor Umarov | U16: Stage in progress. | V16: Pending | Z16: Pending | AD16: Pending | AH16: Pending | AL16: Pending | AP16: Pending | AT16: Pending | AX16: Pending | BB16: Pending | BF16: Pending | BJ16: Pending
B17: =IFERROR(INDEX(Customers!$C$4:$C$1003,MATCH($A17,Customers!$A$4:$A$1003,0)),"") | C17: =IFERROR(INDEX(Customers!$F$4:$F$1003,MATCH($A17,Customers!$A$4:$A$1003,0)),"") | D17: =IFERROR(INDEX(Customers!$K$4:$K$1003,MATCH($A17,Customers!$A$4:$A$1003,0)),"") | E17: =IF($A17="","",IF($F17=0,"Not Started",IF($BJ17="Completed",Settings!$U$45,IF($BF17="Completed",Settings!$U$44,IF($BB17="Completed",Settings!$U$43,IF($AX17="Completed",Settings!$U$42,IF($AT17="Completed",Settings!$U$41,IF($AP17="Completed",Settings!$U$40,IF($AL17="Completed",Settings!$U$39,IF($AH17="Completed",Settings!$U$38,IF($AD17="Completed",Settings!$U$37,IF($Z17="Completed",Settings!$U$36,IF($V17="Completed",Settings!$U$35,IF($R17="Completed",Settings!$U$34,IF($N17="Completed",Settings!$U$33,IF($J17="Completed",Settings!$U$32,"")))))))))))))))) | F17: =IF($A17="","",COUNTIF($J17:$BM17,"Completed")) | G17: =IF($A17="","",MIN($F17/13,1)) | H17: =IF($A17="","",IF($BJ17="Completed","Case Completed",IF($AX17="Completed","Visa Rejected",IF($BF17="Completed","Departed to Europe",IF($F17=0,"Not Started","In Progress"))))) | I17: =IF($K17="","",IF($BK17<>"",$BK17-$K17,IF($AY17<>"",$AY17-$K17,TODAY()-$K17)))
B18: =IFERROR(INDEX(Customers!$C$4:$C$1003,MATCH($A18,Customers!$A$4:$A$1003,0)),"") | C18: =IFERROR(INDEX(Customers!$F$4:$F$1003,MATCH($A18,Customers!$A$4:$A$1003,0)),"") | D18: =IFERROR(INDEX(Customers!$K$4:$K$1003,MATCH($A18,Customers!$A$4:$A$1003,0)),"") | E18: =IF($A18="","",IF($F18=0,"Not Started",IF($BJ18="Completed",Settings!$U$45,IF($BF18="Completed",Settings!$U$44,IF($BB18="Completed",Settings!$U$43,IF($AX18="Completed",Settings!$U$42,IF($AT18="Completed",Settings!$U$41,IF($AP18="Completed",Settings!$U$40,IF($AL18="Completed",Settings!$U$39,IF($AH18="Completed",Settings!$U$38,IF($AD18="Completed",Settings!$U$37,IF($Z18="Completed",Settings!$U$36,IF($V18="Completed",Settings!$U$35,IF($R18="Completed",Settings!$U$34,IF($N18="Completed",Settings!$U$33,IF($J18="Completed",Settings!$U$32,"")))))))))))))))) | F18: =IF($A18="","",COUNTIF($J18:$BM18,"Completed")) | G18: =IF($A18="","",MIN($F18/13,1)) | H18: =IF($A18="","",IF($BJ18="Completed","Case Completed",IF($AX18="Completed","Visa Rejected",IF($BF18="Completed","Departed to Europe",IF($F18=0,"Not Started","In Progress"))))) | I18: =IF($K18="","",IF($BK18<>"",$BK18-$K18,IF($AY18<>"",$AY18-$K18,TODAY()-$K18)))
B19: =IFERROR(INDEX(Customers!$C$4:$C$1003,MATCH($A19,Customers!$A$4:$A$1003,0)),"") | C19: =IFERROR(INDEX(Customers!$F$4:$F$1003,MATCH($A19,Customers!$A$4:$A$1003,0)),"") | D19: =IFERROR(INDEX(Customers!$K$4:$K$1003,MATCH($A19,Customers!$A$4:$A$1003,0)),"") | E19: =IF($A19="","",IF($F19=0,"Not Started",IF($BJ19="Completed",Settings!$U$45,IF($BF19="Completed",Settings!$U$44,IF($BB19="Completed",Settings!$U$43,IF($AX19="Completed",Settings!$U$42,IF($AT19="Completed",Settings!$U$41,IF($AP19="Completed",Settings!$U$40,IF($AL19="Completed",Settings!$U$39,IF($AH19="Completed",Settings!$U$38,IF($AD19="Completed",Settings!$U$37,IF($Z19="Completed",Settings!$U$36,IF($V19="Completed",Settings!$U$35,IF($R19="Completed",Settings!$U$34,IF($N19="Completed",Settings!$U$33,IF($J19="Completed",Settings!$U$32,"")))))))))))))))) | F19: =IF($A19="","",COUNTIF($J19:$BM19,"Completed")) | G19: =IF($A19="","",MIN($F19/13,1)) | H19: =IF($A19="","",IF($BJ19="Completed","Case Completed",IF($AX19="Completed","Visa Rejected",IF($BF19="Completed","Departed to Europe",IF($F19=0,"Not Started","In Progress"))))) | I19: =IF($K19="","",IF($BK19<>"",$BK19-$K19,IF($AY19<>"",$AY19-$K19,TODAY()-$K19)))
B20: =IFERROR(INDEX(Customers!$C$4:$C$1003,MATCH($A20,Customers!$A$4:$A$1003,0)),"") | C20: =IFERROR(INDEX(Customers!$F$4:$F$1003,MATCH($A20,Customers!$A$4:$A$1003,0)),"") | D20: =IFERROR(INDEX(Customers!$K$4:$K$1003,MATCH($A20,Customers!$A$4:$A$1003,0)),"") | E20: =IF($A20="","",IF($F20=0,"Not Started",IF($BJ20="Completed",Settings!$U$45,IF($BF20="Completed",Settings!$U$44,IF($BB20="Completed",Settings!$U$43,IF($AX20="Completed",Settings!$U$42,IF($AT20="Completed",Settings!$U$41,IF($AP20="Completed",Settings!$U$40,IF($AL20="Completed",Settings!$U$39,IF($AH20="Completed",Settings!$U$38,IF($AD20="Completed",Settings!$U$37,IF($Z20="Completed",Settings!$U$36,IF($V20="Completed",Settings!$U$35,IF($R20="Completed",Settings!$U$34,IF($N20="Completed",Settings!$U$33,IF($J20="Completed",Settings!$U$32,"")))))))))))))))) | F20: =IF($A20="","",COUNTIF($J20:$BM20,"Completed")) | G20: =IF($A20="","",MIN($F20/13,1)) | H20: =IF($A20="","",IF($BJ20="Completed","Case Completed",IF($AX20="Completed","Visa Rejected",IF($BF20="Completed","Departed to Europe",IF($F20=0,"Not Started","In Progress"))))) | I20: =IF($K20="","",IF($BK20<>"",$BK20-$K20,IF($AY20<>"",$AY20-$K20,TODAY()-$K20)))
B21: =IFERROR(INDEX(Customers!$C$4:$C$1003,MATCH($A21,Customers!$A$4:$A$1003,0)),"") | C21: =IFERROR(INDEX(Customers!$F$4:$F$1003,MATCH($A21,Customers!$A$4:$A$1003,0)),"") | D21: =IFERROR(INDEX(Customers!$K$4:$K$1003,MATCH($A21,Customers!$A$4:$A$1003,0)),"") | E21: =IF($A21="","",IF($F21=0,"Not Started",IF($BJ21="Completed",Settings!$U$45,IF($BF21="Completed",Settings!$U$44,IF($BB21="Completed",Settings!$U$43,IF($AX21="Completed",Settings!$U$42,IF($AT21="Completed",Settings!$U$41,IF($AP21="Completed",Settings!$U$40,IF($AL21="Completed",Settings!$U$39,IF($AH21="Completed",Settings!$U$38,IF($AD21="Completed",Settings!$U$37,IF($Z21="Completed",Settings!$U$36,IF($V21="Completed",Settings!$U$35,IF($R21="Completed",Settings!$U$34,IF($N21="Completed",Settings!$U$33,IF($J21="Completed",Settings!$U$32,"")))))))))))))))) | F21: =IF($A21="","",COUNTIF($J21:$BM21,"Completed")) | G21: =IF($A21="","",MIN($F21/13,1)) | H21: =IF($A21="","",IF($BJ21="Completed","Case Completed",IF($AX21="Completed","Visa Rejected",IF($BF21="Completed","Departed to Europe",IF($F21=0,"Not Started","In Progress"))))) | I21: =IF($K21="","",IF($BK21<>"",$BK21-$K21,IF($AY21<>"",$AY21-$K21,TODAY()-$K21)))
B22: =IFERROR(INDEX(Customers!$C$4:$C$1003,MATCH($A22,Customers!$A$4:$A$1003,0)),"") | C22: =IFERROR(INDEX(Customers!$F$4:$F$1003,MATCH($A22,Customers!$A$4:$A$1003,0)),"") | D22: =IFERROR(INDEX(Customers!$K$4:$K$1003,MATCH($A22,Customers!$A$4:$A$1003,0)),"") | E22: =IF($A22="","",IF($F22=0,"Not Started",IF($BJ22="Completed",Settings!$U$45,IF($BF22="Completed",Settings!$U$44,IF($BB22="Completed",Settings!$U$43,IF($AX22="Completed",Settings!$U$42,IF($AT22="Completed",Settings!$U$41,IF($AP22="Completed",Settings!$U$40,IF($AL22="Completed",Settings!$U$39,IF($AH22="Completed",Settings!$U$38,IF($AD22="Completed",Settings!$U$37,IF($Z22="Completed",Settings!$U$36,IF($V22="Completed",Settings!$U$35,IF($R22="Completed",Settings!$U$34,IF($N22="Completed",Settings!$U$33,IF($J22="Completed",Settings!$U$32,"")))))))))))))))) | F22: =IF($A22="","",COUNTIF($J22:$BM22,"Completed")) | G22: =IF($A22="","",MIN($F22/13,1)) | H22: =IF($A22="","",IF($BJ22="Completed","Case Completed",IF($AX22="Completed","Visa Rejected",IF($BF22="Completed","Departed to Europe",IF($F22=0,"Not Started","In Progress"))))) | I22: =IF($K22="","",IF($BK22<>"",$BK22-$K22,IF($AY22<>"",$AY22-$K22,TODAY()-$K22)))
B23: =IFERROR(INDEX(Customers!$C$4:$C$1003,MATCH($A23,Customers!$A$4:$A$1003,0)),"") | C23: =IFERROR(INDEX(Customers!$F$4:$F$1003,MATCH($A23,Customers!$A$4:$A$1003,0)),"") | D23: =IFERROR(INDEX(Customers!$K$4:$K$1003,MATCH($A23,Customers!$A$4:$A$1003,0)),"") | E23: =IF($A23="","",IF($F23=0,"Not Started",IF($BJ23="Completed",Settings!$U$45,IF($BF23="Completed",Settings!$U$44,IF($BB23="Completed",Settings!$U$43,IF($AX23="Completed",Settings!$U$42,IF($AT23="Completed",Settings!$U$41,IF($AP23="Completed",Settings!$U$40,IF($AL23="Completed",Settings!$U$39,IF($AH23="Completed",Settings!$U$38,IF($AD23="Completed",Settings!$U$37,IF($Z23="Completed",Settings!$U$36,IF($V23="Completed",Settings!$U$35,IF($R23="Completed",Settings!$U$34,IF($N23="Completed",Settings!$U$33,IF($J23="Completed",Settings!$U$32,"")))))))))))))))) | F23: =IF($A23="","",COUNTIF($J23:$BM23,"Completed")) | G23: =IF($A23="","",MIN($F23/13,1)) | H23: =IF($A23="","",IF($BJ23="Completed","Case Completed",IF($AX23="Completed","Visa Rejected",IF($BF23="Completed","Departed to Europe",IF($F23=0,"Not Started","In Progress"))))) | I23: =IF($K23="","",IF($BK23<>"",$BK23-$K23,IF($AY23<>"",$AY23-$K23,TODAY()-$K23)))
B24: =IFERROR(INDEX(Customers!$C$4:$C$1003,MATCH($A24,Customers!$A$4:$A$1003,0)),"") | C24: =IFERROR(INDEX(Customers!$F$4:$F$1003,MATCH($A24,Customers!$A$4:$A$1003,0)),"") | D24: =IFERROR(INDEX(Customers!$K$4:$K$1003,MATCH($A24,Customers!$A$4:$A$1003,0)),"") | E24: =IF($A24="","",IF($F24=0,"Not Started",IF($BJ24="Completed",Settings!$U$45,IF($BF24="Completed",Settings!$U$44,IF($BB24="Completed",Settings!$U$43,IF($AX24="Completed",Settings!$U$42,IF($AT24="Completed",Settings!$U$41,IF($AP24="Completed",Settings!$U$40,IF($AL24="Completed",Settings!$U$39,IF($AH24="Completed",Settings!$U$38,IF($AD24="Completed",Settings!$U$37,IF($Z24="Completed",Settings!$U$36,IF($V24="Completed",Settings!$U$35,IF($R24="Completed",Settings!$U$34,IF($N24="Completed",Settings!$U$33,IF($J24="Completed",Settings!$U$32,"")))))))))))))))) | F24: =IF($A24="","",COUNTIF($J24:$BM24,"Completed")) | G24: =IF($A24="","",MIN($F24/13,1)) | H24: =IF($A24="","",IF($BJ24="Completed","Case Completed",IF($AX24="Completed","Visa Rejected",IF($BF24="Completed","Departed to Europe",IF($F24=0,"Not Started","In Progress"))))) | I24: =IF($K24="","",IF($BK24<>"",$BK24-$K24,IF($AY24<>"",$AY24-$K24,TODAY()-$K24)))
B25: =IFERROR(INDEX(Customers!$C$4:$C$1003,MATCH($A25,Customers!$A$4:$A$1003,0)),"") | C25: =IFERROR(INDEX(Customers!$F$4:$F$1003,MATCH($A25,Customers!$A$4:$A$1003,0)),"") | D25: =IFERROR(INDEX(Customers!$K$4:$K$1003,MATCH($A25,Customers!$A$4:$A$1003,0)),"") | E25: =IF($A25="","",IF($F25=0,"Not Started",IF($BJ25="Completed",Settings!$U$45,IF($BF25="Completed",Settings!$U$44,IF($BB25="Completed",Settings!$U$43,IF($AX25="Completed",Settings!$U$42,IF($AT25="Completed",Settings!$U$41,IF($AP25="Completed",Settings!$U$40,IF($AL25="Completed",Settings!$U$39,IF($AH25="Completed",Settings!$U$38,IF($AD25="Completed",Settings!$U$37,IF($Z25="Completed",Settings!$U$36,IF($V25="Completed",Settings!$U$35,IF($R25="Completed",Settings!$U$34,IF($N25="Completed",Settings!$U$33,IF($J25="Completed",Settings!$U$32,"")))))))))))))))) | F25: =IF($A25="","",COUNTIF($J25:$BM25,"Completed")) | G25: =IF($A25="","",MIN($F25/13,1)) | H25: =IF($A25="","",IF($BJ25="Completed","Case Completed",IF($AX25="Completed","Visa Rejected",IF($BF25="Completed","Departed to Europe",IF($F25=0,"Not Started","In Progress"))))) | I25: =IF($K25="","",IF($BK25<>"",$BK25-$K25,IF($AY25<>"",$AY25-$K25,TODAY()-$K25)))
B26: =IFERROR(INDEX(Customers!$C$4:$C$1003,MATCH($A26,Customers!$A$4:$A$1003,0)),"") | C26: =IFERROR(INDEX(Customers!$F$4:$F$1003,MATCH($A26,Customers!$A$4:$A$1003,0)),"") | D26: =IFERROR(INDEX(Customers!$K$4:$K$1003,MATCH($A26,Customers!$A$4:$A$1003,0)),"") | E26: =IF($A26="","",IF($F26=0,"Not Started",IF($BJ26="Completed",Settings!$U$45,IF($BF26="Completed",Settings!$U$44,IF($BB26="Completed",Settings!$U$43,IF($AX26="Completed",Settings!$U$42,IF($AT26="Completed",Settings!$U$41,IF($AP26="Completed",Settings!$U$40,IF($AL26="Completed",Settings!$U$39,IF($AH26="Completed",Settings!$U$38,IF($AD26="Completed",Settings!$U$37,IF($Z26="Completed",Settings!$U$36,IF($V26="Completed",Settings!$U$35,IF($R26="Completed",Settings!$U$34,IF($N26="Completed",Settings!$U$33,IF($J26="Completed",Settings!$U$32,"")))))))))))))))) | F26: =IF($A26="","",COUNTIF($J26:$BM26,"Completed")) | G26: =IF($A26="","",MIN($F26/13,1)) | H26: =IF($A26="","",IF($BJ26="Completed","Case Completed",IF($AX26="Completed","Visa Rejected",IF($BF26="Completed","Departed to Europe",IF($F26=0,"Not Started","In Progress"))))) | I26: =IF($K26="","",IF($BK26<>"",$BK26-$K26,IF($AY26<>"",$AY26-$K26,TODAY()-$K26)))
B27: =IFERROR(INDEX(Customers!$C$4:$C$1003,MATCH($A27,Customers!$A$4:$A$1003,0)),"") | C27: =IFERROR(INDEX(Customers!$F$4:$F$1003,MATCH($A27,Customers!$A$4:$A$1003,0)),"") | D27: =IFERROR(INDEX(Customers!$K$4:$K$1003,MATCH($A27,Customers!$A$4:$A$1003,0)),"") | E27: =IF($A27="","",IF($F27=0,"Not Started",IF($BJ27="Completed",Settings!$U$45,IF($BF27="Completed",Settings!$U$44,IF($BB27="Completed",Settings!$U$43,IF($AX27="Completed",Settings!$U$42,IF($AT27="Completed",Settings!$U$41,IF($AP27="Completed",Settings!$U$40,IF($AL27="Completed",Settings!$U$39,IF($AH27="Completed",Settings!$U$38,IF($AD27="Completed",Settings!$U$37,IF($Z27="Completed",Settings!$U$36,IF($V27="Completed",Settings!$U$35,IF($R27="Completed",Settings!$U$34,IF($N27="Completed",Settings!$U$33,IF($J27="Completed",Settings!$U$32,"")))))))))))))))) | F27: =IF($A27="","",COUNTIF($J27:$BM27,"Completed")) | G27: =IF($A27="","",MIN($F27/13,1)) | H27: =IF($A27="","",IF($BJ27="Completed","Case Completed",IF($AX27="Completed","Visa Rejected",IF($BF27="Completed","Departed to Europe",IF($F27=0,"Not Started","In Progress"))))) | I27: =IF($K27="","",IF($BK27<>"",$BK27-$K27,IF($AY27<>"",$AY27-$K27,TODAY()-$K27)))
B28: =IFERROR(INDEX(Customers!$C$4:$C$1003,MATCH($A28,Customers!$A$4:$A$1003,0)),"") | C28: =IFERROR(INDEX(Customers!$F$4:$F$1003,MATCH($A28,Customers!$A$4:$A$1003,0)),"") | D28: =IFERROR(INDEX(Customers!$K$4:$K$1003,MATCH($A28,Customers!$A$4:$A$1003,0)),"") | E28: =IF($A28="","",IF($F28=0,"Not Started",IF($BJ28="Completed",Settings!$U$45,IF($BF28="Completed",Settings!$U$44,IF($BB28="Completed",Settings!$U$43,IF($AX28="Completed",Settings!$U$42,IF($AT28="Completed",Settings!$U$41,IF($AP28="Completed",Settings!$U$40,IF($AL28="Completed",Settings!$U$39,IF($AH28="Completed",Settings!$U$38,IF($AD28="Completed",Settings!$U$37,IF($Z28="Completed",Settings!$U$36,IF($V28="Completed",Settings!$U$35,IF($R28="Completed",Settings!$U$34,IF($N28="Completed",Settings!$U$33,IF($J28="Completed",Settings!$U$32,"")))))))))))))))) | F28: =IF($A28="","",COUNTIF($J28:$BM28,"Completed")) | G28: =IF($A28="","",MIN($F28/13,1)) | H28: =IF($A28="","",IF($BJ28="Completed","Case Completed",IF($AX28="Completed","Visa Rejected",IF($BF28="Completed","Departed to Europe",IF($F28=0,"Not Started","In Progress"))))) | I28: =IF($K28="","",IF($BK28<>"",$BK28-$K28,IF($AY28<>"",$AY28-$K28,TODAY()-$K28)))
... B203: =IFERROR(INDEX(Customers!$C$4:$C$1003,MATCH($A203,Customers!$A$4:$A$1003,0)),"") | C203: =IFERROR(INDEX(Customers!$F$4:$F$1003,MATCH($A203,Customers!$A$4:$A$1003,0)),"") | D203: =IFERROR(INDEX(Customers!$K$4:$K$1003,MATCH($A203,Customers!$A$4:$A$1003,0)),"") | E203: =IF($A203="","",IF($F203=0,"Not Started",IF($BJ203="Completed",Settings!$U$45,IF($BF203="Completed",Settings!$U$44,IF($BB203="Completed",Settings!$U$43,IF($AX203="Completed",Settings!$U$42,IF($AT203="Completed",Settings!$U$41,IF($AP203="Completed",Settings!$U$40,IF($AL203="Completed",Settings!$U$39,IF($AH203="Completed",Settings!$U$38,IF($AD203="Completed",Settings!$U$37,IF($Z203="Completed",Settings!$U$36,IF($V203="Completed",Settings!$U$35,IF($R203="Completed",Settings!$U$34,IF($N203="Completed",Settings!$U$33,IF($J203="Completed",Settings!$U$32,"")))))))))))))))) | F203: =IF($A203="","",COUNTIF($J203:$BM203,"Completed")) | G203: =IF($A203="","",MIN($F203/13,1)) | H203: =IF($A203="","",IF($BJ203="Completed","Case Completed",IF($AX203="Completed","Visa Rejected",IF($BF203="Completed","Departed to Europe",IF($F203=0,"Not Started","In Progress"))))) | I203: =IF($K203="","",IF($BK203<>"",$BK203-$K203,IF($AY203<>"",$AY203-$K203,TODAY()-$K203)))

Sheet Finance
A1: VUSLAT RECRUITMENT COMPANY | FINANCE
A2: Left block = customer payments (4 instalments per contract). Middle block = company expenses. Right block = live totals. Only rows with Payment Status = Paid count as collected revenue.
A3: Invoice Number | B3: Customer ID | C3: Customer Name | D3: Payment Stage | E3: Amount (TJS) | F3: Payment Date | G3: Payment Method | H3: Receipt Number | I3: Due Date | J3: Payment Status | K3: Days Overdue | L3: Customer Total Paid (TJS) | M3: Remaining Balance (TJS) | N3: Received By | O3: Notes | Q3: Expense ID | R3: Date | S3: Category | T3: Description | U3: Amount (TJS) | V3: Payment Method | W3: Paid To | X3: Approved By | Z3: FINANCE SUMMARY (live)
A4: INV-2026-0001 | B4: CUS-001 | C4: =IFERROR(INDEX(Customers!$C$4:$C$1003,MATCH($B4,Customers!$A$4:$A$1003,0)),"") -> Firdavs Rahmonov | D4: Payment 1 - Contract | E4: 6600 | F4: 46039 | G4: Bank Transfer | H4: RCP-0001 | I4: 46039 | J4: Paid | K4: =IF(OR($A4="",$I4=""),"",IF($J4="Paid",0,IF(TODAY()>$I4,TODAY()-$I4,0))) -> 0 | L4: =IFERROR(INDEX(Customers!$M$4:$M$1003,MATCH($B4,Customers!$A$4:$A$1003,0)),"") -> 22000 | M4: =IFERROR(INDEX(Customers!$N$4:$N$1003,MATCH($B4,Customers!$A$4:$A$1003,0)),"") -> 0 | N4: Manizha Sharipova | Q4: EXP-001 | R4: 46027 | S4: Office Rent | T4: Office rent - Rudaki ave., Dushanbe | U4: 3500 | V4: Bank Transfer | W4: Ismoilov Property LLC | X4: Farrukh Rahmonov | Z4: Total Payments Collected | AA4: =SUMIFS($E$4:$E$1003,$J$4:$J$1003,"Paid") -> 225250
A5: INV-2026-0002 | B5: CUS-001 | C5: =IFERROR(INDEX(Customers!$C$4:$C$1003,MATCH($B5,Customers!$A$4:$A$1003,0)),"") -> Firdavs Rahmonov | D5: Payment 2 - Documents | E5: 4400 | F5: 46059 | G5: Mobile Money | H5: RCP-0002 | I5: 46059 | J5: Paid | K5: =IF(OR($A5="",$I5=""),"",IF($J5="Paid",0,IF(TODAY()>$I5,TODAY()-$I5,0))) -> 0 | L5: =IFERROR(INDEX(Customers!$M$4:$M$1003,MATCH($B5,Customers!$A$4:$A$1003,0)),"") -> 22000 | M5: =IFERROR(INDEX(Customers!$N$4:$N$1003,MATCH($B5,Customers!$A$4:$A$1003,0)),"") -> 0 | N5: Manizha Sharipova | Q5: EXP-002 | R5: 46050 | S5: Salaries | T5: Monthly staff salaries (8 employees) | U5: 19000 | V5: Bank Transfer | W5: Staff payroll | X5: Farrukh Rahmonov | Z5: Consultation Fees Collected | AA5: =SUMIFS(Consultation!$H$4:$H$1003,Consultation!$I$4:$I$1003,"Paid") -> 700
A6: INV-2026-0003 | B6: CUS-001 | C6: =IFERROR(INDEX(Customers!$C$4:$C$1003,MATCH($B6,Customers!$A$4:$A$1003,0)),"") -> Firdavs Rahmonov | D6: Payment 3 - Work Permit | E6: 5500 | F6: 46084 | G6: Bank Transfer | H6: RCP-0003 | I6: 46084 | J6: Paid | K6: =IF(OR($A6="",$I6=""),"",IF($J6="Paid",0,IF(TODAY()>$I6,TODAY()-$I6,0))) -> 0 | L6: =IFERROR(INDEX(Customers!$M$4:$M$1003,MATCH($B6,Customers!$A$4:$A$1003,0)),"") -> 22000 | M6: =IFERROR(INDEX(Customers!$N$4:$N$1003,MATCH($B6,Customers!$A$4:$A$1003,0)),"") -> 0 | N6: Manizha Sharipova | Q6: EXP-003 | R6: 46032 | S6: Marketing Costs | T6: Instagram / Facebook advertising budget | U6: 2200 | V6: Cash | W6: Meta Platforms | X6: Farrukh Rahmonov | Z6: Total Revenue | AA6: =$AA$4+$AA$5 -> 225950
A7: INV-2026-0004 | B7: CUS-001 | C7: =IFERROR(INDEX(Customers!$C$4:$C$1003,MATCH($B7,Customers!$A$4:$A$1003,0)),"") -> Firdavs Rahmonov | D7: Payment 4 - Visa Approved | E7: 5500 | F7: 46114 | G7: Mobile Money | H7: RCP-0004 | I7: 46114 | J7: Paid | K7: =IF(OR($A7="",$I7=""),"",IF($J7="Paid",0,IF(TODAY()>$I7,TODAY()-$I7,0))) -> 0 | L7: =IFERROR(INDEX(Customers!$M$4:$M$1003,MATCH($B7,Customers!$A$4:$A$1003,0)),"") -> 22000 | M7: =IFERROR(INDEX(Customers!$N$4:$N$1003,MATCH($B7,Customers!$A$4:$A$1003,0)),"") -> 0 | N7: Manizha Sharipova | Q7: EXP-004 | R7: 46040 | S7: Visa Expenses | T7: Embassy fees, translations, apostille | U7: 800 | V7: Cash | W7: Embassy / Notary | X7: Farrukh Rahmonov | Z7: Payments Still Pending | AA7: =SUMIFS($E$4:$E$1003,$J$4:$J$1003,"Pending") -> 6000
A8: INV-2026-0005 | B8: CUS-002 | C8: =IFERROR(INDEX(Customers!$C$4:$C$1003,MATCH($B8,Customers!$A$4:$A$1003,0)),"") -> Nilufar Sharipova | D8: Payment 1 - Contract | E8: 9600 | F8: 46046 | G8: Bank Transfer | H8: RCP-0005 | I8: 46046 | J8: Paid | K8: =IF(OR($A8="",$I8=""),"",IF($J8="Paid",0,IF(TODAY()>$I8,TODAY()-$I8,0))) -> 0 | L8: =IFERROR(INDEX(Customers!$M$4:$M$1003,MATCH($B8,Customers!$A$4:$A$1003,0)),"") -> 32000 | M8: =IFERROR(INDEX(Customers!$N$4:$N$1003,MATCH($B8,Customers!$A$4:$A$1003,0)),"") -> 0 | N8: Manizha Sharipova | Q8: EXP-005 | R8: 46044 | S8: Miscellaneous Expenses | T8: Utilities, stationery, transport | U8: 600 | V8: Cash | W8: Various | X8: Farrukh Rahmonov | Z8: Payments Overdue | AA8: =SUMIFS($E$4:$E$1003,$J$4:$J$1003,"Overdue") -> 6250
A9: INV-2026-0006 | B9: CUS-002 | C9: =IFERROR(INDEX(Customers!$C$4:$C$1003,MATCH($B9,Customers!$A$4:$A$1003,0)),"") -> Nilufar Sharipova | D9: Payment 2 - Documents | E9: 6400 | F9: 46066 | G9: Mobile Money | H9: RCP-0006 | I9: 46066 | J9: Paid | K9: =IF(OR($A9="",$I9=""),"",IF($J9="Paid",0,IF(TODAY()>$I9,TODAY()-$I9,0))) -> 0 | L9: =IFERROR(INDEX(Customers!$M$4:$M$1003,MATCH($B9,Customers!$A$4:$A$1003,0)),"") -> 32000 | M9: =IFERROR(INDEX(Customers!$N$4:$N$1003,MATCH($B9,Customers!$A$4:$A$1003,0)),"") -> 0 | N9: Manizha Sharipova | Q9: EXP-006 | R9: 46058 | S9: Office Rent | T9: Office rent - Rudaki ave., Dushanbe | U9: 3500 | V9: Bank Transfer | W9: Ismoilov Property LLC | X9: Farrukh Rahmonov | Z9: Outstanding Payments (pending + overdue) | AA9: =$AA$7+$AA$8 -> 12250
A10: INV-2026-0007 | B10: CUS-002 | C10: =IFERROR(INDEX(Customers!$C$4:$C$1003,MATCH($B10,Customers!$A$4:$A$1003,0)),"") -> Nilufar Sharipova | D10: Payment 3 - Work Permit | E10: 8000 | F10: 46091 | G10: Bank Transfer | H10: RCP-0007 | I10: 46091 | J10: Paid | K10: =IF(OR($A10="",$I10=""),"",IF($J10="Paid",0,IF(TODAY()>$I10,TODAY()-$I10,0))) -> 0 | L10: =IFERROR(INDEX(Customers!$M$4:$M$1003,MATCH($B10,Customers!$A$4:$A$1003,0)),"") -> 32000 | M10: =IFERROR(INDEX(Customers!$N$4:$N$1003,MATCH($B10,Customers!$A$4:$A$1003,0)),"") -> 0 | N10: Manizha Sharipova | Q10: EXP-007 | R10: 46081 | S10: Salaries | T10: Monthly staff salaries (8 employees) | U10: 19000 | V10: Bank Transfer | W10: Staff payroll | X10: Farrukh Rahmonov | Z10: Accounts Receivable (all balances) | AA10: =SUM(Customers!$N$4:$N$1003) -> 63750
A11: INV-2026-0008 | B11: CUS-002 | C11: =IFERROR(INDEX(Customers!$C$4:$C$1003,MATCH($B11,Customers!$A$4:$A$1003,0)),"") -> Nilufar Sharipova | D11: Payment 4 - Visa Approved | E11: 8000 | F11: 46121 | G11: Mobile Money | H11: RCP-0008 | I11: 46121 | J11: Paid | K11: =IF(OR($A11="",$I11=""),"",IF($J11="Paid",0,IF(TODAY()>$I11,TODAY()-$I11,0))) -> 0 | L11: =IFERROR(INDEX(Customers!$M$4:$M$1003,MATCH($B11,Customers!$A$4:$A$1003,0)),"") -> 32000 | M11: =IFERROR(INDEX(Customers!$N$4:$N$1003,MATCH($B11,Customers!$A$4:$A$1003,0)),"") -> 0 | N11: Manizha Sharipova | Q11: EXP-008 | R11: 46063 | S11: Marketing Costs | T11: Instagram / Facebook advertising budget | U11: 2600 | V11: Cash | W11: Meta Platforms | X11: Farrukh Rahmonov | Z11: Total Contract Value | AA11: =SUM(Customers!$L$4:$L$1003) -> 289000
A12: INV-2026-0009 | B12: CUS-003 | C12: =IFERROR(INDEX(Customers!$C$4:$C$1003,MATCH($B12,Customers!$A$4:$A$1003,0)),"") -> Jamshed Karimov | D12: Payment 1 - Contract | E12: 7500 | F12: 46067 | G12: Bank Transfer | H12: RCP-0009 | I12: 46067 | J12: Paid | K12: =IF(OR($A12="",$I12=""),"",IF($J12="Paid",0,IF(TODAY()>$I12,TODAY()-$I12,0))) -> 0 | L12: =IFERROR(INDEX(Customers!$M$4:$M$1003,MATCH($B12,Customers!$A$4:$A$1003,0)),"") -> 25000 | M12: =IFERROR(INDEX(Customers!$N$4:$N$1003,MATCH($B12,Customers!$A$4:$A$1003,0)),"") -> 0 | N12: Manizha Sharipova | Q12: EXP-009 | R12: 46071 | S12: Visa Expenses | T12: Embassy fees, translations, apostille | U12: 1200 | V12: Cash | W12: Embassy / Notary | X12: Farrukh Rahmonov
A13: INV-2026-0010 | B13: CUS-003 | C13: =IFERROR(INDEX(Customers!$C$4:$C$1003,MATCH($B13,Customers!$A$4:$A$1003,0)),"") -> Jamshed Karimov | D13: Payment 2 - Documents | E13: 5000 | F13: 46087 | G13: Mobile Money | H13: RCP-0010 | I13: 46087 | J13: Paid | K13: =IF(OR($A13="",$I13=""),"",IF($J13="Paid",0,IF(TODAY()>$I13,TODAY()-$I13,0))) -> 0 | L13: =IFERROR(INDEX(Customers!$M$4:$M$1003,MATCH($B13,Customers!$A$4:$A$1003,0)),"") -> 25000 | M13: =IFERROR(INDEX(Customers!$N$4:$N$1003,MATCH($B13,Customers!$A$4:$A$1003,0)),"") -> 0 | N13: Manizha Sharipova | Q13: EXP-010 | R13: 46075 | S13: Miscellaneous Expenses | T13: Utilities, stationery, transport | U13: 450 | V13: Cash | W13: Various | X13: Farrukh Rahmonov | Z13: Office Rent | AA13: =SUMIFS($U$4:$U$1003,$S$4:$S$1003,"Office Rent") -> 24500
A14: INV-2026-0011 | B14: CUS-003 | C14: =IFERROR(INDEX(Customers!$C$4:$C$1003,MATCH($B14,Customers!$A$4:$A$1003,0)),"") -> Jamshed Karimov | D14: Payment 3 - Work Permit | E14: 6250 | F14: 46112 | G14: Bank Transfer | H14: RCP-0011 | I14: 46112 | J14: Paid | K14: =IF(OR($A14="",$I14=""),"",IF($J14="Paid",0,IF(TODAY()>$I14,TODAY()-$I14,0))) -> 0 | L14: =IFERROR(INDEX(Customers!$M$4:$M$1003,MATCH($B14,Customers!$A$4:$A$1003,0)),"") -> 25000 | M14: =IFERROR(INDEX(Customers!$N$4:$N$1003,MATCH($B14,Customers!$A$4:$A$1003,0)),"") -> 0 | N14: Manizha Sharipova | Q14: EXP-011 | R14: 46086 | S14: Office Rent | T14: Office rent - Rudaki ave., Dushanbe | U14: 3500 | V14: Bank Transfer | W14: Ismoilov Property LLC | X14: Farrukh Rahmonov | Z14: Salaries | AA14: =SUMIFS($U$4:$U$1003,$S$4:$S$1003,"Salaries") -> 133000
A15: INV-2026-0012 | B15: CUS-003 | C15: =IFERROR(INDEX(Customers!$C$4:$C$1003,MATCH($B15,Customers!$A$4:$A$1003,0)),"") -> Jamshed Karimov | D15: Payment 4 - Visa Approved | E15: 6250 | F15: 46142 | G15: Mobile Money | H15: RCP-0012 | I15: 46142 | J15: Paid | K15: =IF(OR($A15="",$I15=""),"",IF($J15="Paid",0,IF(TODAY()>$I15,TODAY()-$I15,0))) -> 0 | L15: =IFERROR(INDEX(Customers!$M$4:$M$1003,MATCH($B15,Customers!$A$4:$A$1003,0)),"") -> 25000 | M15: =IFERROR(INDEX(Customers!$N$4:$N$1003,MATCH($B15,Customers!$A$4:$A$1003,0)),"") -> 0 | N15: Manizha Sharipova | Q15: EXP-012 | R15: 46109 | S15: Salaries | T15: Monthly staff salaries (8 employees) | U15: 19000 | V15: Bank Transfer | W15: Staff payroll | X15: Farrukh Rahmonov | Z15: Marketing Costs | AA15: =SUMIFS($U$4:$U$1003,$S$4:$S$1003,"Marketing Costs") -> 19300
A16: INV-2026-0013 | B16: CUS-004 | C16: =IFERROR(INDEX(Customers!$C$4:$C$1003,MATCH($B16,Customers!$A$4:$A$1003,0)),"") -> Zarina Nazriyeva | D16: Payment 1 - Contract | E16: 6600 | F16: 46074 | G16: Bank Transfer | H16: RCP-0013 | I16: 46074 | J16: Paid | K16: =IF(OR($A16="",$I16=""),"",IF($J16="Paid",0,IF(TODAY()>$I16,TODAY()-$I16,0))) -> 0 | L16: =IFERROR(INDEX(Customers!$M$4:$M$1003,MATCH($B16,Customers!$A$4:$A$1003,0)),"") -> 22000 | M16: =IFERROR(INDEX(Customers!$N$4:$N$1003,MATCH($B16,Customers!$A$4:$A$1003,0)),"") -> 0 | N16: Manizha Sharipova | Q16: EXP-013 | R16: 46091 | S16: Marketing Costs | T16: Instagram / Facebook advertising budget | U16: 3100 | V16: Cash | W16: Meta Platforms | X16: Farrukh Rahmonov | Z16: Visa Expenses | AA16: =SUMIFS($U$4:$U$1003,$S$4:$S$1003,"Visa Expenses") -> 11400
A17: INV-2026-0014 | B17: CUS-004 | C17: =IFERROR(INDEX(Customers!$C$4:$C$1003,MATCH($B17,Customers!$A$4:$A$1003,0)),"") -> Zarina Nazriyeva | D17: Payment 2 - Documents | E17: 4400 | F17: 46094 | G17: Mobile Money | H17: RCP-0014 | I17: 46094 | J17: Paid | K17: =IF(OR($A17="",$I17=""),"",IF($J17="Paid",0,IF(TODAY()>$I17,TODAY()-$I17,0))) -> 0 | L17: =IFERROR(INDEX(Customers!$M$4:$M$1003,MATCH($B17,Customers!$A$4:$A$1003,0)),"") -> 22000 | M17: =IFERROR(INDEX(Customers!$N$4:$N$1003,MATCH($B17,Customers!$A$4:$A$1003,0)),"") -> 0 | N17: Manizha Sharipova | Q17: EXP-014 | R17: 46099 | S17: Visa Expenses | T17: Embassy fees, translations, apostille | U17: 1500 | V17: Cash | W17: Embassy / Notary | X17: Farrukh Rahmonov | Z17: Miscellaneous Expenses | AA17: =SUMIFS($U$4:$U$1003,$S$4:$S$1003,"Miscellaneous Expenses") -> 4100
A18: INV-2026-0015 | B18: CUS-004 | C18: =IFERROR(INDEX(Customers!$C$4:$C$1003,MATCH($B18,Customers!$A$4:$A$1003,0)),"") -> Zarina Nazriyeva | D18: Payment 3 - Work Permit | E18: 5500 | F18: 46119 | G18: Bank Transfer | H18: RCP-0015 | I18: 46119 | J18: Paid | K18: =IF(OR($A18="",$I18=""),"",IF($J18="Paid",0,IF(TODAY()>$I18,TODAY()-$I18,0))) -> 0 | L18: =IFERROR(INDEX(Customers!$M$4:$M$1003,MATCH($B18,Customers!$A$4:$A$1003,0)),"") -> 22000 | M18: =IFERROR(INDEX(Customers!$N$4:$N$1003,MATCH($B18,Customers!$A$4:$A$1003,0)),"") -> 0 | N18: Manizha Sharipova | Q18: EXP-015 | R18: 46103 | S18: Miscellaneous Expenses | T18: Utilities, stationery, transport | U18: 700 | V18: Cash | W18: Various | X18: Farrukh Rahmonov | Z18: Total Expenses | AA18: =SUM($U$4:$U$1003) -> 192300
A19: INV-2026-0016 | B19: CUS-004 | C19: =IFERROR(INDEX(Customers!$C$4:$C$1003,MATCH($B19,Customers!$A$4:$A$1003,0)),"") -> Zarina Nazriyeva | D19: Payment 4 - Visa Approved | E19: 5500 | F19: 46149 | G19: Mobile Money | H19: RCP-0016 | I19: 46149 | J19: Paid | K19: =IF(OR($A19="",$I19=""),"",IF($J19="Paid",0,IF(TODAY()>$I19,TODAY()-$I19,0))) -> 0 | L19: =IFERROR(INDEX(Customers!$M$4:$M$1003,MATCH($B19,Customers!$A$4:$A$1003,0)),"") -> 22000 | M19: =IFERROR(INDEX(Customers!$N$4:$N$1003,MATCH($B19,Customers!$A$4:$A$1003,0)),"") -> 0 | N19: Manizha Sharipova | Q19: EXP-016 | R19: 46117 | S19: Office Rent | T19: Office rent - Rudaki ave., Dushanbe | U19: 3500 | V19: Bank Transfer | W19: Ismoilov Property LLC | X19: Farrukh Rahmonov
A20: INV-2026-0017 | B20: CUS-005 | C20: =IFERROR(INDEX(Customers!$C$4:$C$1003,MATCH($B20,Customers!$A$4:$A$1003,0)),"") -> Bakhtiyor Umarov | D20: Payment 1 - Contract | E20: 7200 | F20: 46053 | G20: Bank Transfer | H20: RCP-0017 | I20: 46053 | J20: Paid | K20: =IF(OR($A20="",$I20=""),"",IF($J20="Paid",0,IF(TODAY()>$I20,TODAY()-$I20,0))) -> 0 | L20: =IFERROR(INDEX(Customers!$M$4:$M$1003,MATCH($B20,Customers!$A$4:$A$1003,0)),"") -> 18000 | M20: =IFERROR(INDEX(Customers!$N$4:$N$1003,MATCH($B20,Customers!$A$4:$A$1003,0)),"") -> 6000 | N20: Manizha Sharipova | Q20: EXP-017 | R20: 46140 | S20: Salaries | T20: Monthly staff salaries (8 employees) | U20: 19000 | V20: Bank Transfer | W20: Staff payroll | X20: Farrukh Rahmonov | Z20: NET PROFIT | AA20: =$AA$6-$AA$18 -> 33650
A21: INV-2026-0018 | B21: CUS-005 | C21: =IFERROR(INDEX(Customers!$C$4:$C$1003,MATCH($B21,Customers!$A$4:$A$1003,0)),"") -> Bakhtiyor Umarov | D21: Payment 2 - Documents | E21: 4800 | F21: 46073 | G21: Mobile Money | H21: RCP-0018 | I21: 46073 | J21: Paid | K21: =IF(OR($A21="",$I21=""),"",IF($J21="Paid",0,IF(TODAY()>$I21,TODAY()-$I21,0))) -> 0 | L21: =IFERROR(INDEX(Customers!$M$4:$M$1003,MATCH($B21,Customers!$A$4:$A$1003,0)),"") -> 18000 | M21: =IFERROR(INDEX(Customers!$N$4:$N$1003,MATCH($B21,Customers!$A$4:$A$1003,0)),"") -> 6000 | N21: Manizha Sharipova | Q21: EXP-018 | R21: 46122 | S21: Marketing Costs | T21: Instagram / Facebook advertising budget | U21: 3300 | V21: Cash | W21: Meta Platforms | X21: Farrukh Rahmonov | Z21: Profit Margin | AA21: =IFERROR($AA$20/$AA$6,"") -> 0.14892675
A22: INV-2026-0019 | B22: CUS-005 | C22: =IFERROR(INDEX(Customers!$C$4:$C$1003,MATCH($B22,Customers!$A$4:$A$1003,0)),"") -> Bakhtiyor Umarov | D22: Payment 3 - Work Permit | E22: 6000 | F22: 46098 | G22: Bank Transfer | H22: RCP-0019 | I22: 46098 | J22: Paid | K22: =IF(OR($A22="",$I22=""),"",IF($J22="Paid",0,IF(TODAY()>$I22,TODAY()-$I22,0))) -> 0 | L22: =IFERROR(INDEX(Customers!$M$4:$M$1003,MATCH($B22,Customers!$A$4:$A$1003,0)),"") -> 18000 | M22: =IFERROR(INDEX(Customers!$N$4:$N$1003,MATCH($B22,Customers!$A$4:$A$1003,0)),"") -> 6000 | N22: Manizha Sharipova | Q22: EXP-019 | R22: 46130 | S22: Visa Expenses | T22: Embassy fees, translations, apostille | U22: 2100 | V22: Cash | W22: Embassy / Notary | X22: Farrukh Rahmonov | Z22: Collection Rate | AA22: =IFERROR($AA$4/$AA$11,"") -> 0.77941176
A23: INV-2026-0020 | B23: CUS-005 | C23: =IFERROR(INDEX(Customers!$C$4:$C$1003,MATCH($B23,Customers!$A$4:$A$1003,0)),"") -> Bakhtiyor Umarov | D23: Payment 4 - Visa Approved | E23: 6000 | G23: Mobile Money | I23: 46248 | J23: Pending | K23: =IF(OR($A23="",$I23=""),"",IF($J23="Paid",0,IF(TODAY()>$I23,TODAY()-$I23,0))) -> 0 | L23: =IFERROR(INDEX(Customers!$M$4:$M$1003,MATCH($B23,Customers!$A$4:$A$1003,0)),"") -> 18000 | M23: =IFERROR(INDEX(Customers!$N$4:$N$1003,MATCH($B23,Customers!$A$4:$A$1003,0)),"") -> 6000 | N23: Manizha Sharipova | Q23: EXP-020 | R23: 46134 | S23: Miscellaneous Expenses | T23: Utilities, stationery, transport | U23: 520 | V23: Cash | W23: Various | X23: Farrukh Rahmonov
A24: INV-2026-0021 | B24: CUS-006 | C24: =IFERROR(INDEX(Customers!$C$4:$C$1003,MATCH($B24,Customers!$A$4:$A$1003,0)),"") -> Manizha Qodirova | D24: Payment 1 - Contract | E24: 9600 | F24: 46080 | G24: Bank Transfer | H24: RCP-0021 | I24: 46080 | J24: Paid | K24: =IF(OR($A24="",$I24=""),"",IF($J24="Paid",0,IF(TODAY()>$I24,TODAY()-$I24,0))) -> 0 | L24: =IFERROR(INDEX(Customers!$M$4:$M$1003,MATCH($B24,Customers!$A$4:$A$1003,0)),"") -> 24000 | M24: =IFERROR(INDEX(Customers!$N$4:$N$1003,MATCH($B24,Customers!$A$4:$A$1003,0)),"") -> 8000 | N24: Manizha Sharipova | Q24: EXP-021 | R24: 46147 | S24: Office Rent | T24: Office rent - Rudaki ave., Dushanbe | U24: 3500 | V24: Bank Transfer | W24: Ismoilov Property LLC | X24: Farrukh Rahmonov
A25: INV-2026-0022 | B25: CUS-006 | C25: =IFERROR(INDEX(Customers!$C$4:$C$1003,MATCH($B25,Customers!$A$4:$A$1003,0)),"") -> Manizha Qodirova | D25: Payment 2 - Documents | E25: 6400 | F25: 46100 | G25: Mobile Money | H25: RCP-0022 | I25: 46100 | J25: Paid | K25: =IF(OR($A25="",$I25=""),"",IF($J25="Paid",0,IF(TODAY()>$I25,TODAY()-$I25,0))) -> 0 | L25: =IFERROR(INDEX(Customers!$M$4:$M$1003,MATCH($B25,Customers!$A$4:$A$1003,0)),"") -> 24000 | M25: =IFERROR(INDEX(Customers!$N$4:$N$1003,MATCH($B25,Customers!$A$4:$A$1003,0)),"") -> 8000 | N25: Manizha Sharipova | Q25: EXP-022 | R25: 46170 | S25: Salaries | T25: Monthly staff salaries (8 employees) | U25: 19000 | V25: Bank Transfer | W25: Staff payroll | X25: Farrukh Rahmonov
A26: INV-2026-0023 | B26: CUS-006 | C26: =IFERROR(INDEX(Customers!$C$4:$C$1003,MATCH($B26,Customers!$A$4:$A$1003,0)),"") -> Manizha Qodirova | D26: Payment 3 - Work Permit | E26: 8000 | F26: 46125 | G26: Bank Transfer | H26: RCP-0023 | I26: 46125 | J26: Paid | K26: =IF(OR($A26="",$I26=""),"",IF($J26="Paid",0,IF(TODAY()>$I26,TODAY()-$I26,0))) -> 0 | L26: =IFERROR(INDEX(Customers!$M$4:$M$1003,MATCH($B26,Customers!$A$4:$A$1003,0)),"") -> 24000 | M26: =IFERROR(INDEX(Customers!$N$4:$N$1003,MATCH($B26,Customers!$A$4:$A$1003,0)),"") -> 8000 | N26: Manizha Sharipova | Q26: EXP-023 | R26: 46152 | S26: Marketing Costs | T26: Instagram / Facebook advertising budget | U26: 2900 | V26: Cash | W26: Meta Platforms | X26: Farrukh Rahmonov
A27: INV-2026-0024 | B27: CUS-006 | C27: =IFERROR(INDEX(Customers!$C$4:$C$1003,MATCH($B27,Customers!$A$4:$A$1003,0)),"") -> Manizha Qodirova | D27: Payment 4 - Visa Approved | E27: 8000 | G27: Mobile Money | J27: Cancelled | K27: =IF(OR($A27="",$I27=""),"",IF($J27="Paid",0,IF(TODAY()>$I27,TODAY()-$I27,0))) | L27: =IFERROR(INDEX(Customers!$M$4:$M$1003,MATCH($B27,Customers!$A$4:$A$1003,0)),"") -> 24000 | M27: =IFERROR(INDEX(Customers!$N$4:$N$1003,MATCH($B27,Customers!$A$4:$A$1003,0)),"") -> 8000 | N27: Manizha Sharipova | O27: Cancelled - visa refused, final payment not due. | Q27: EXP-024 | R27: 46160 | S27: Visa Expenses | T27: Embassy fees, translations, apostille | U27: 2400 | V27: Cash | W27: Embassy / Notary | X27: Farrukh Rahmonov
A28: INV-2026-0025 | B28: CUS-007 | C28: =IFERROR(INDEX(Customers!$C$4:$C$1003,MATCH($B28,Customers!$A$4:$A$1003,0)),"") -> Rustam Sattorov | D28: Payment 1 - Contract | E28: 6600 | F28: 46094 | G28: Bank Transfer | H28: RCP-0025 | I28: 46094 | J28: Paid | K28: =IF(OR($A28="",$I28=""),"",IF($J28="Paid",0,IF(TODAY()>$I28,TODAY()-$I28,0))) -> 0 | L28: =IFERROR(INDEX(Customers!$M$4:$M$1003,MATCH($B28,Customers!$A$4:$A$1003,0)),"") -> 16500 | M28: =IFERROR(INDEX(Customers!$N$4:$N$1003,MATCH($B28,Customers!$A$4:$A$1003,0)),"") -> 5500 | N28: Manizha Sharipova | Q28: EXP-025 | R28: 46164 | S28: Miscellaneous Expenses | T28: Utilities, stationery, transport | U28: 640 | V28: Cash | W28: Various | X28: Farrukh Rahmonov
A29: INV-2026-0026 | B29: CUS-007 | C29: =IFERROR(INDEX(Customers!$C$4:$C$1003,MATCH($B29,Customers!$A$4:$A$1003,0)),"") -> Rustam Sattorov | D29: Payment 2 - Documents | E29: 4400 | F29: 46114 | G29: Mobile Money | H29: RCP-0026 | I29: 46114 | J29: Paid | K29: =IF(OR($A29="",$I29=""),"",IF($J29="Paid",0,IF(TODAY()>$I29,TODAY()-$I29,0))) -> 0 | L29: =IFERROR(INDEX(Customers!$M$4:$M$1003,MATCH($B29,Customers!$A$4:$A$1003,0)),"") -> 16500 | M29: =IFERROR(INDEX(Customers!$N$4:$N$1003,MATCH($B29,Customers!$A$4:$A$1003,0)),"") -> 5500 | N29: Manizha Sharipova | Q29: EXP-026 | R29: 46178 | S29: Office Rent | T29: Office rent - Rudaki ave., Dushanbe | U29: 3500 | V29: Bank Transfer | W29: Ismoilov Property LLC | X29: Farrukh Rahmonov
A30: INV-2026-0027 | B30: CUS-007 | C30: =IFERROR(INDEX(Customers!$C$4:$C$1003,MATCH($B30,Customers!$A$4:$A$1003,0)),"") -> Rustam Sattorov | D30: Payment 3 - Work Permit | E30: 5500 | F30: 46139 | G30: Bank Transfer | H30: RCP-0027 | I30: 46139 | J30: Paid | K30: =IF(OR($A30="",$I30=""),"",IF($J30="Paid",0,IF(TODAY()>$I30,TODAY()-$I30,0))) -> 0 | L30: =IFERROR(INDEX(Customers!$M$4:$M$1003,MATCH($B30,Customers!$A$4:$A$1003,0)),"") -> 16500 | M30: =IFERROR(INDEX(Customers!$N$4:$N$1003,MATCH($B30,Customers!$A$4:$A$1003,0)),"") -> 5500 | N30: Manizha Sharipova | Q30: EXP-027 | R30: 46201 | S30: Salaries | T30: Monthly staff salaries (8 employees) | U30: 19000 | V30: Bank Transfer | W30: Staff payroll | X30: Farrukh Rahmonov
A31: INV-2026-0028 | B31: CUS-008 | C31: =IFERROR(INDEX(Customers!$C$4:$C$1003,MATCH($B31,Customers!$A$4:$A$1003,0)),"") -> Dilnoza Aliyeva | D31: Payment 1 - Contract | E31: 6300 | F31: 46101 | G31: Cash | H31: RCP-0028 | I31: 46101 | J31: Paid | K31: =IF(OR($A31="",$I31=""),"",IF($J31="Paid",0,IF(TODAY()>$I31,TODAY()-$I31,0))) -> 0 | L31: =IFERROR(INDEX(Customers!$M$4:$M$1003,MATCH($B31,Customers!$A$4:$A$1003,0)),"") -> 15750 | M31: =IFERROR(INDEX(Customers!$N$4:$N$1003,MATCH($B31,Customers!$A$4:$A$1003,0)),"") -> 5250 | N31: Manizha Sharipova | Q31: EXP-028 | R31: 46183 | S31: Marketing Costs | T31: Instagram / Facebook advertising budget | U31: 2700 | V31: Cash | W31: Meta Platforms | X31: Farrukh Rahmonov
A32: INV-2026-0029 | B32: CUS-008 | C32: =IFERROR(INDEX(Customers!$C$4:$C$1003,MATCH($B32,Customers!$A$4:$A$1003,0)),"") -> Dilnoza Aliyeva | D32: Payment 2 - Documents | E32: 4200 | F32: 46121 | G32: Card | H32: RCP-0029 | I32: 46121 | J32: Paid | K32: =IF(OR($A32="",$I32=""),"",IF($J32="Paid",0,IF(TODAY()>$I32,TODAY()-$I32,0))) -> 0 | L32: =IFERROR(INDEX(Customers!$M$4:$M$1003,MATCH($B32,Customers!$A$4:$A$1003,0)),"") -> 15750 | M32: =IFERROR(INDEX(Customers!$N$4:$N$1003,MATCH($B32,Customers!$A$4:$A$1003,0)),"") -> 5250 | N32: Manizha Sharipova | Q32: EXP-029 | R32: 46191 | S32: Visa Expenses | T32: Embassy fees, translations, apostille | U32: 1800 | V32: Cash | W32: Embassy / Notary | X32: Farrukh Rahmonov
A33: INV-2026-0030 | B33: CUS-008 | C33: =IFERROR(INDEX(Customers!$C$4:$C$1003,MATCH($B33,Customers!$A$4:$A$1003,0)),"") -> Dilnoza Aliyeva | D33: Payment 3 - Work Permit | E33: 5250 | F33: 46146 | G33: Cash | H33: RCP-0030 | I33: 46146 | J33: Paid | K33: =IF(OR($A33="",$I33=""),"",IF($J33="Paid",0,IF(TODAY()>$I33,TODAY()-$I33,0))) -> 0 | L33: =IFERROR(INDEX(Customers!$M$4:$M$1003,MATCH($B33,Customers!$A$4:$A$1003,0)),"") -> 15750 | M33: =IFERROR(INDEX(Customers!$N$4:$N$1003,MATCH($B33,Customers!$A$4:$A$1003,0)),"") -> 5250 | N33: Manizha Sharipova | Q33: EXP-030 | R33: 46195 | S33: Miscellaneous Expenses | T33: Utilities, stationery, transport | U33: 580 | V33: Cash | W33: Various | X33: Farrukh Rahmonov
A34: INV-2026-0031 | B34: CUS-009 | C34: =IFERROR(INDEX(Customers!$C$4:$C$1003,MATCH($B34,Customers!$A$4:$A$1003,0)),"") -> Sherali Yusupov | D34: Payment 1 - Contract | E34: 7500 | F34: 46108 | G34: Mobile Money | H34: RCP-0031 | I34: 46108 | J34: Paid | K34: =IF(OR($A34="",$I34=""),"",IF($J34="Paid",0,IF(TODAY()>$I34,TODAY()-$I34,0))) -> 0 | L34: =IFERROR(INDEX(Customers!$M$4:$M$1003,MATCH($B34,Customers!$A$4:$A$1003,0)),"") -> 12500 | M34: =IFERROR(INDEX(Customers!$N$4:$N$1003,MATCH($B34,Customers!$A$4:$A$1003,0)),"") -> 12500 | N34: Manizha Sharipova | Q34: EXP-031 | R34: 46208 | S34: Office Rent | T34: Office rent - Rudaki ave., Dushanbe | U34: 3500 | V34: Bank Transfer | W34: Ismoilov Property LLC | X34: Farrukh Rahmonov
A35: INV-2026-0032 | B35: CUS-009 | C35: =IFERROR(INDEX(Customers!$C$4:$C$1003,MATCH($B35,Customers!$A$4:$A$1003,0)),"") -> Sherali Yusupov | D35: Payment 2 - Documents | E35: 5000 | F35: 46128 | G35: Bank Transfer | H35: RCP-0032 | I35: 46128 | J35: Paid | K35: =IF(OR($A35="",$I35=""),"",IF($J35="Paid",0,IF(TODAY()>$I35,TODAY()-$I35,0))) -> 0 | L35: =IFERROR(INDEX(Customers!$M$4:$M$1003,MATCH($B35,Customers!$A$4:$A$1003,0)),"") -> 12500 | M35: =IFERROR(INDEX(Customers!$N$4:$N$1003,MATCH($B35,Customers!$A$4:$A$1003,0)),"") -> 12500 | N35: Manizha Sharipova | Q35: EXP-032 | R35: 46231 | S35: Salaries | T35: Monthly staff salaries (8 employees) | U35: 19000 | V35: Bank Transfer | W35: Staff payroll | X35: Farrukh Rahmonov
A36: INV-2026-0033 | B36: CUS-009 | C36: =IFERROR(INDEX(Customers!$C$4:$C$1003,MATCH($B36,Customers!$A$4:$A$1003,0)),"") -> Sherali Yusupov | D36: Payment 3 - Work Permit | E36: 6250 | G36: Mobile Money | I36: 46153 | J36: Overdue | K36: =IF(OR($A36="",$I36=""),"",IF($J36="Paid",0,IF(TODAY()>$I36,TODAY()-$I36,0))) -> 80 | L36: =IFERROR(INDEX(Customers!$M$4:$M$1003,MATCH($B36,Customers!$A$4:$A$1003,0)),"") -> 12500 | M36: =IFERROR(INDEX(Customers!$N$4:$N$1003,MATCH($B36,Customers!$A$4:$A$1003,0)),"") -> 12500 | N36: Manizha Sharipova | Q36: EXP-033 | R36: 46213 | S36: Marketing Costs | T36: Instagram / Facebook advertising budget | U36: 2500 | V36: Cash | W36: Meta Platforms | X36: Farrukh Rahmonov
A37: INV-2026-0034 | B37: CUS-010 | C37: =IFERROR(INDEX(Customers!$C$4:$C$1003,MATCH($B37,Customers!$A$4:$A$1003,0)),"") -> Malika Ismoilova | D37: Payment 1 - Contract | E37: 6600 | F37: 46123 | G37: Card | H37: RCP-0034 | I37: 46123 | J37: Paid | K37: =IF(OR($A37="",$I37=""),"",IF($J37="Paid",0,IF(TODAY()>$I37,TODAY()-$I37,0))) -> 0 | L37: =IFERROR(INDEX(Customers!$M$4:$M$1003,MATCH($B37,Customers!$A$4:$A$1003,0)),"") -> 16500 | M37: =IFERROR(INDEX(Customers!$N$4:$N$1003,MATCH($B37,Customers!$A$4:$A$1003,0)),"") -> 5500 | N37: Manizha Sharipova | Q37: EXP-034 | R37: 46221 | S37: Visa Expenses | T37: Embassy fees, translations, apostille | U37: 1600 | V37: Cash | W37: Embassy / Notary | X37: Farrukh Rahmonov
A38: INV-2026-0035 | B38: CUS-010 | C38: =IFERROR(INDEX(Customers!$C$4:$C$1003,MATCH($B38,Customers!$A$4:$A$1003,0)),"") -> Malika Ismoilova | D38: Payment 2 - Documents | E38: 4400 | F38: 46143 | G38: Cash | H38: RCP-0035 | I38: 46143 | J38: Paid | K38: =IF(OR($A38="",$I38=""),"",IF($J38="Paid",0,IF(TODAY()>$I38,TODAY()-$I38,0))) -> 0 | L38: =IFERROR(INDEX(Customers!$M$4:$M$1003,MATCH($B38,Customers!$A$4:$A$1003,0)),"") -> 16500 | M38: =IFERROR(INDEX(Customers!$N$4:$N$1003,MATCH($B38,Customers!$A$4:$A$1003,0)),"") -> 5500 | N38: Manizha Sharipova | Q38: EXP-035 | R38: 46225 | S38: Miscellaneous Expenses | T38: Utilities, stationery, transport | U38: 610 | V38: Cash | W38: Various | X38: Farrukh Rahmonov
A39: INV-2026-0036 | B39: CUS-010 | C39: =IFERROR(INDEX(Customers!$C$4:$C$1003,MATCH($B39,Customers!$A$4:$A$1003,0)),"") -> Malika Ismoilova | D39: Payment 3 - Work Permit | E39: 5500 | F39: 46233 | G39: Card | H39: RCP-0036 | I39: 46168 | J39: Paid | K39: =IF(OR($A39="",$I39=""),"",IF($J39="Paid",0,IF(TODAY()>$I39,TODAY()-$I39,0))) -> 0 | L39: =IFERROR(INDEX(Customers!$M$4:$M$1003,MATCH($B39,Customers!$A$4:$A$1003,0)),"") -> 16500 | M39: =IFERROR(INDEX(Customers!$N$4:$N$1003,MATCH($B39,Customers!$A$4:$A$1003,0)),"") -> 5500 | N39: Manizha Sharipova | O39: Late payment received today.
A40: INV-2026-0037 | B40: CUS-011 | C40: =IFERROR(INDEX(Customers!$C$4:$C$1003,MATCH($B40,Customers!$A$4:$A$1003,0)),"") -> Farrukh Davlatov | D40: Payment 1 - Contract | E40: 6900 | F40: 46115 | G40: Bank Transfer | H40: RCP-0037 | I40: 46115 | J40: Paid | K40: =IF(OR($A40="",$I40=""),"",IF($J40="Paid",0,IF(TODAY()>$I40,TODAY()-$I40,0))) -> 0 | L40: =IFERROR(INDEX(Customers!$M$4:$M$1003,MATCH($B40,Customers!$A$4:$A$1003,0)),"") -> 11500 | M40: =IFERROR(INDEX(Customers!$N$4:$N$1003,MATCH($B40,Customers!$A$4:$A$1003,0)),"") -> 11500 | N40: Manizha Sharipova
A41: INV-2026-0038 | B41: CUS-011 | C41: =IFERROR(INDEX(Customers!$C$4:$C$1003,MATCH($B41,Customers!$A$4:$A$1003,0)),"") -> Farrukh Davlatov | D41: Payment 2 - Documents | E41: 4600 | F41: 46135 | G41: Mobile Money | H41: RCP-0038 | I41: 46135 | J41: Paid | K41: =IF(OR($A41="",$I41=""),"",IF($J41="Paid",0,IF(TODAY()>$I41,TODAY()-$I41,0))) -> 0 | L41: =IFERROR(INDEX(Customers!$M$4:$M$1003,MATCH($B41,Customers!$A$4:$A$1003,0)),"") -> 11500 | M41: =IFERROR(INDEX(Customers!$N$4:$N$1003,MATCH($B41,Customers!$A$4:$A$1003,0)),"") -> 11500 | N41: Manizha Sharipova
A42: INV-2026-0039 | B42: CUS-012 | C42: =IFERROR(INDEX(Customers!$C$4:$C$1003,MATCH($B42,Customers!$A$4:$A$1003,0)),"") -> Gulnora Safarova | D42: Payment 1 - Contract | E42: 5700 | F42: 46130 | G42: Mobile Money | H42: RCP-0039 | I42: 46130 | J42: Paid | K42: =IF(OR($A42="",$I42=""),"",IF($J42="Paid",0,IF(TODAY()>$I42,TODAY()-$I42,0))) -> 0 | L42: =IFERROR(INDEX(Customers!$M$4:$M$1003,MATCH($B42,Customers!$A$4:$A$1003,0)),"") -> 9500 | M42: =IFERROR(INDEX(Customers!$N$4:$N$1003,MATCH($B42,Customers!$A$4:$A$1003,0)),"") -> 9500 | N42: Manizha Sharipova
A43: INV-2026-0040 | B43: CUS-012 | C43: =IFERROR(INDEX(Customers!$C$4:$C$1003,MATCH($B43,Customers!$A$4:$A$1003,0)),"") -> Gulnora Safarova | D43: Payment 2 - Documents | E43: 3800 | F43: 46233 | G43: Bank Transfer | H43: RCP-0040 | I43: 46150 | J43: Paid | K43: =IF(OR($A43="",$I43=""),"",IF($J43="Paid",0,IF(TODAY()>$I43,TODAY()-$I43,0))) -> 0 | L43: =IFERROR(INDEX(Customers!$M$4:$M$1003,MATCH($B43,Customers!$A$4:$A$1003,0)),"") -> 9500 | M43: =IFERROR(INDEX(Customers!$N$4:$N$1003,MATCH($B43,Customers!$A$4:$A$1003,0)),"") -> 9500 | N43: Manizha Sharipova | O43: Late payment received today.
C44: =IFERROR(INDEX(Customers!$C$4:$C$1003,MATCH($B44,Customers!$A$4:$A$1003,0)),"") | K44: =IF(OR($A44="",$I44=""),"",IF($J44="Paid",0,IF(TODAY()>$I44,TODAY()-$I44,0))) | L44: =IFERROR(INDEX(Customers!$M$4:$M$1003,MATCH($B44,Customers!$A$4:$A$1003,0)),"") | M44: =IFERROR(INDEX(Customers!$N$4:$N$1003,MATCH($B44,Customers!$A$4:$A$1003,0)),"")
C45: =IFERROR(INDEX(Customers!$C$4:$C$1003,MATCH($B45,Customers!$A$4:$A$1003,0)),"") | K45: =IF(OR($A45="",$I45=""),"",IF($J45="Paid",0,IF(TODAY()>$I45,TODAY()-$I45,0))) | L45: =IFERROR(INDEX(Customers!$M$4:$M$1003,MATCH($B45,Customers!$A$4:$A$1003,0)),"") | M45: =IFERROR(INDEX(Customers!$N$4:$N$1003,MATCH($B45,Customers!$A$4:$A$1003,0)),"")
C46: =IFERROR(INDEX(Customers!$C$4:$C$1003,MATCH($B46,Customers!$A$4:$A$1003,0)),"") | K46: =IF(OR($A46="",$I46=""),"",IF($J46="Paid",0,IF(TODAY()>$I46,TODAY()-$I46,0))) | L46: =IFERROR(INDEX(Customers!$M$4:$M$1003,MATCH($B46,Customers!$A$4:$A$1003,0)),"") | M46: =IFERROR(INDEX(Customers!$N$4:$N$1003,MATCH($B46,Customers!$A$4:$A$1003,0)),"")
C47: =IFERROR(INDEX(Customers!$C$4:$C$1003,MATCH($B47,Customers!$A$4:$A$1003,0)),"") | K47: =IF(OR($A47="",$I47=""),"",IF($J47="Paid",0,IF(TODAY()>$I47,TODAY()-$I47,0))) | L47: =IFERROR(INDEX(Customers!$M$4:$M$1003,MATCH($B47,Customers!$A$4:$A$1003,0)),"") | M47: =IFERROR(INDEX(Customers!$N$4:$N$1003,MATCH($B47,Customers!$A$4:$A$1003,0)),"")
C48: =IFERROR(INDEX(Customers!$C$4:$C$1003,MATCH($B48,Customers!$A$4:$A$1003,0)),"") | K48: =IF(OR($A48="",$I48=""),"",IF($J48="Paid",0,IF(TODAY()>$I48,TODAY()-$I48,0))) | L48: =IFERROR(INDEX(Customers!$M$4:$M$1003,MATCH($B48,Customers!$A$4:$A$1003,0)),"") | M48: =IFERROR(INDEX(Customers!$N$4:$N$1003,MATCH($B48,Customers!$A$4:$A$1003,0)),"")
C49: =IFERROR(INDEX(Customers!$C$4:$C$1003,MATCH($B49,Customers!$A$4:$A$1003,0)),"") | K49: =IF(OR($A49="",$I49=""),"",IF($J49="Paid",0,IF(TODAY()>$I49,TODAY()-$I49,0))) | L49: =IFERROR(INDEX(Customers!$M$4:$M$1003,MATCH($B49,Customers!$A$4:$A$1003,0)),"") | M49: =IFERROR(INDEX(Customers!$N$4:$N$1003,MATCH($B49,Customers!$A$4:$A$1003,0)),"")
C50: =IFERROR(INDEX(Customers!$C$4:$C$1003,MATCH($B50,Customers!$A$4:$A$1003,0)),"") | K50: =IF(OR($A50="",$I50=""),"",IF($J50="Paid",0,IF(TODAY()>$I50,TODAY()-$I50,0))) | L50: =IFERROR(INDEX(Customers!$M$4:$M$1003,MATCH($B50,Customers!$A$4:$A$1003,0)),"") | M50: =IFERROR(INDEX(Customers!$N$4:$N$1003,MATCH($B50,Customers!$A$4:$A$1003,0)),"")
C51: =IFERROR(INDEX(Customers!$C$4:$C$1003,MATCH($B51,Customers!$A$4:$A$1003,0)),"") | K51: =IF(OR($A51="",$I51=""),"",IF($J51="Paid",0,IF(TODAY()>$I51,TODAY()-$I51,0))) | L51: =IFERROR(INDEX(Customers!$M$4:$M$1003,MATCH($B51,Customers!$A$4:$A$1003,0)),"") | M51: =IFERROR(INDEX(Customers!$N$4:$N$1003,MATCH($B51,Customers!$A$4:$A$1003,0)),"")
C52: =IFERROR(INDEX(Customers!$C$4:$C$1003,MATCH($B52,Customers!$A$4:$A$1003,0)),"") | K52: =IF(OR($A52="",$I52=""),"",IF($J52="Paid",0,IF(TODAY()>$I52,TODAY()-$I52,0))) | L52: =IFERROR(INDEX(Customers!$M$4:$M$1003,MATCH($B52,Customers!$A$4:$A$1003,0)),"") | M52: =IFERROR(INDEX(Customers!$N$4:$N$1003,MATCH($B52,Customers!$A$4:$A$1003,0)),"")
C53: =IFERROR(INDEX(Customers!$C$4:$C$1003,MATCH($B53,Customers!$A$4:$A$1003,0)),"") | K53: =IF(OR($A53="",$I53=""),"",IF($J53="Paid",0,IF(TODAY()>$I53,TODAY()-$I53,0))) | L53: =IFERROR(INDEX(Customers!$M$4:$M$1003,MATCH($B53,Customers!$A$4:$A$1003,0)),"") | M53: =IFERROR(INDEX(Customers!$N$4:$N$1003,MATCH($B53,Customers!$A$4:$A$1003,0)),"")
C54: =IFERROR(INDEX(Customers!$C$4:$C$1003,MATCH($B54,Customers!$A$4:$A$1003,0)),"") | K54: =IF(OR($A54="",$I54=""),"",IF($J54="Paid",0,IF(TODAY()>$I54,TODAY()-$I54,0))) | L54: =IFERROR(INDEX(Customers!$M$4:$M$1003,MATCH($B54,Customers!$A$4:$A$1003,0)),"") | M54: =IFERROR(INDEX(Customers!$N$4:$N$1003,MATCH($B54,Customers!$A$4:$A$1003,0)),"")
C55: =IFERROR(INDEX(Customers!$C$4:$C$1003,MATCH($B55,Customers!$A$4:$A$1003,0)),"") | K55: =IF(OR($A55="",$I55=""),"",IF($J55="Paid",0,IF(TODAY()>$I55,TODAY()-$I55,0))) | L55: =IFERROR(INDEX(Customers!$M$4:$M$1003,MATCH($B55,Customers!$A$4:$A$1003,0)),"") | M55: =IFERROR(INDEX(Customers!$N$4:$N$1003,MATCH($B55,Customers!$A$4:$A$1003,0)),"")
... C203: =IFERROR(INDEX(Customers!$C$4:$C$1003,MATCH($B203,Customers!$A$4:$A$1003,0)),"") | K203: =IF(OR($A203="",$I203=""),"",IF($J203="Paid",0,IF(TODAY()>$I203,TODAY()-$I203,0))) | L203: =IFERROR(INDEX(Customers!$M$4:$M$1003,MATCH($B203,Customers!$A$4:$A$1003,0)),"") | M203: =IFERROR(INDEX(Customers!$N$4:$N$1003,MATCH($B203,Customers!$A$4:$A$1003,0)),"")

Sheet Documents
A1: VUSLAT RECRUITMENT COMPANY | DOCUMENT MANAGEMENT
A2: Yes / No per document. Received, Completion % and Document Status are calculated. Green = present, red = still missing.
A3: Customer ID | B3: Full Name | C3: Destination Country | D3: Passport | E3: Diploma | F3: Europass CV | G3: Photo | H3: Criminal Record Certificate | I3: Medical Certificate | J3: Work Permit | K3: Employment Contract | L3: Visa | M3: Insurance | N3: Apostille Documents | O3: Documents Received | P3: Documents Required | Q3: Completion % | R3: Document Status | S3: Responsible Officer | T3: Last Updated | U3: Notes
A4: CUS-001 | B4: =IFERROR(INDEX(Customers!$C$4:$C$1003,MATCH($A4,Customers!$A$4:$A$1003,0)),"") -> Firdavs Rahmonov | C4: =IFERROR(INDEX(Customers!$F$4:$F$1003,MATCH($A4,Customers!$A$4:$A$1003,0)),"") -> Poland | D4: Yes | E4: Yes | F4: Yes | G4: Yes | H4: Yes | I4: Yes | J4: Yes | K4: Yes | L4: Yes | M4: Yes | N4: Yes | O4: =IF($A4="","",COUNTIF($D4:$N4,"Yes")) -> 11 | P4: =IF($A4="","",COUNTA($D$3:$N$3)) -> 11 | Q4: =IF($A4="","",IFERROR($O4/$P4,"")) -> 1 | R4: =IF($A4="","",IF($Q4=1,"Complete",IF($Q4>=0.7,"Almost Complete",IF($Q4>0,"In Progress","Not Started")))) -> Complete | S4: Bakhtiyor Umarov | T4: 46233
A5: CUS-002 | B5: =IFERROR(INDEX(Customers!$C$4:$C$1003,MATCH($A5,Customers!$A$4:$A$1003,0)),"") -> Nilufar Sharipova | C5: =IFERROR(INDEX(Customers!$F$4:$F$1003,MATCH($A5,Customers!$A$4:$A$1003,0)),"") -> Germany | D5: Yes | E5: Yes | F5: Yes | G5: Yes | H5: Yes | I5: Yes | J5: Yes | K5: Yes | L5: Yes | M5: Yes | N5: Yes | O5: =IF($A5="","",COUNTIF($D5:$N5,"Yes")) -> 11 | P5: =IF($A5="","",COUNTA($D$3:$N$3)) -> 11 | Q5: =IF($A5="","",IFERROR($O5/$P5,"")) -> 1 | R5: =IF($A5="","",IF($Q5=1,"Complete",IF($Q5>=0.7,"Almost Complete",IF($Q5>0,"In Progress","Not Started")))) -> Complete | S5: Bakhtiyor Umarov | T5: 46233
A6: CUS-003 | B6: =IFERROR(INDEX(Customers!$C$4:$C$1003,MATCH($A6,Customers!$A$4:$A$1003,0)),"") -> Jamshed Karimov | C6: =IFERROR(INDEX(Customers!$F$4:$F$1003,MATCH($A6,Customers!$A$4:$A$1003,0)),"") -> Czech Republic | D6: Yes | E6: Yes | F6: Yes | G6: Yes | H6: Yes | I6: Yes | J6: Yes | K6: Yes | L6: Yes | M6: Yes | N6: Yes | O6: =IF($A6="","",COUNTIF($D6:$N6,"Yes")) -> 11 | P6: =IF($A6="","",COUNTA($D$3:$N$3)) -> 11 | Q6: =IF($A6="","",IFERROR($O6/$P6,"")) -> 1 | R6: =IF($A6="","",IF($Q6=1,"Complete",IF($Q6>=0.7,"Almost Complete",IF($Q6>0,"In Progress","Not Started")))) -> Complete | S6: Bakhtiyor Umarov | T6: 46233
A7: CUS-004 | B7: =IFERROR(INDEX(Customers!$C$4:$C$1003,MATCH($A7,Customers!$A$4:$A$1003,0)),"") -> Zarina Nazriyeva | C7: =IFERROR(INDEX(Customers!$F$4:$F$1003,MATCH($A7,Customers!$A$4:$A$1003,0)),"") -> Poland | D7: Yes | E7: Yes | F7: Yes | G7: Yes | H7: Yes | I7: Yes | J7: Yes | K7: Yes | L7: Yes | M7: Yes | N7: Yes | O7: =IF($A7="","",COUNTIF($D7:$N7,"Yes")) -> 11 | P7: =IF($A7="","",COUNTA($D$3:$N$3)) -> 11 | Q7: =IF($A7="","",IFERROR($O7/$P7,"")) -> 1 | R7: =IF($A7="","",IF($Q7=1,"Complete",IF($Q7>=0.7,"Almost Complete",IF($Q7>0,"In Progress","Not Started")))) -> Complete | S7: Bakhtiyor Umarov | T7: 46233
A8: CUS-005 | B8: =IFERROR(INDEX(Customers!$C$4:$C$1003,MATCH($A8,Customers!$A$4:$A$1003,0)),"") -> Bakhtiyor Umarov | C8: =IFERROR(INDEX(Customers!$F$4:$F$1003,MATCH($A8,Customers!$A$4:$A$1003,0)),"") -> Slovakia | D8: Yes | E8: Yes | F8: Yes | G8: Yes | H8: Yes | I8: Yes | J8: Yes | K8: Yes | L8: Yes | M8: No | N8: Yes | O8: =IF($A8="","",COUNTIF($D8:$N8,"Yes")) -> 10 | P8: =IF($A8="","",COUNTA($D$3:$N$3)) -> 11 | Q8: =IF($A8="","",IFERROR($O8/$P8,"")) -> 0.90909091 | R8: =IF($A8="","",IF($Q8=1,"Complete",IF($Q8>=0.7,"Almost Complete",IF($Q8>0,"In Progress","Not Started")))) -> Almost Complete | S8: Bakhtiyor Umarov | T8: 46233
A9: CUS-006 | B9: =IFERROR(INDEX(Customers!$C$4:$C$1003,MATCH($A9,Customers!$A$4:$A$1003,0)),"") -> Manizha Qodirova | C9: =IFERROR(INDEX(Customers!$F$4:$F$1003,MATCH($A9,Customers!$A$4:$A$1003,0)),"") -> Germany | D9: Yes | E9: Yes | F9: Yes | G9: Yes | H9: Yes | I9: Yes | J9: Yes | K9: Yes | L9: No | M9: No | N9: Yes | O9: =IF($A9="","",COUNTIF($D9:$N9,"Yes")) -> 9 | P9: =IF($A9="","",COUNTA($D$3:$N$3)) -> 11 | Q9: =IF($A9="","",IFERROR($O9/$P9,"")) -> 0.81818182 | R9: =IF($A9="","",IF($Q9=1,"Complete",IF($Q9>=0.7,"Almost Complete",IF($Q9>0,"In Progress","Not Started")))) -> Almost Complete | S9: Bakhtiyor Umarov | T9: 46233 | U9: Visa refused - file closed.
A10: CUS-007 | B10: =IFERROR(INDEX(Customers!$C$4:$C$1003,MATCH($A10,Customers!$A$4:$A$1003,0)),"") -> Rustam Sattorov | C10: =IFERROR(INDEX(Customers!$F$4:$F$1003,MATCH($A10,Customers!$A$4:$A$1003,0)),"") -> Poland | D10: Yes | E10: Yes | F10: Yes | G10: Yes | H10: Yes | I10: Yes | J10: Yes | K10: Yes | L10: No | M10: No | N10: Yes | O10: =IF($A10="","",COUNTIF($D10:$N10,"Yes")) -> 9 | P10: =IF($A10="","",COUNTA($D$3:$N$3)) -> 11 | Q10: =IF($A10="","",IFERROR($O10/$P10,"")) -> 0.81818182 | R10: =IF($A10="","",IF($Q10=1,"Complete",IF($Q10>=0.7,"Almost Complete",IF($Q10>0,"In Progress","Not Started")))) -> Almost Complete | S10: Bakhtiyor Umarov | T10: 46233
A11: CUS-008 | B11: =IFERROR(INDEX(Customers!$C$4:$C$1003,MATCH($A11,Customers!$A$4:$A$1003,0)),"") -> Dilnoza Aliyeva | C11: =IFERROR(INDEX(Customers!$F$4:$F$1003,MATCH($A11,Customers!$A$4:$A$1003,0)),"") -> Lithuania | D11: Yes | E11: Yes | F11: Yes | G11: Yes | H11: Yes | I11: Yes | J11: Yes | K11: Yes | L11: No | M11: No | N11: Yes | O11: =IF($A11="","",COUNTIF($D11:$N11,"Yes")) -> 9 | P11: =IF($A11="","",COUNTA($D$3:$N$3)) -> 11 | Q11: =IF($A11="","",IFERROR($O11/$P11,"")) -> 0.81818182 | R11: =IF($A11="","",IF($Q11=1,"Complete",IF($Q11>=0.7,"Almost Complete",IF($Q11>0,"In Progress","Not Started")))) -> Almost Complete | S11: Bakhtiyor Umarov | T11: 46233
A12: CUS-009 | B12: =IFERROR(INDEX(Customers!$C$4:$C$1003,MATCH($A12,Customers!$A$4:$A$1003,0)),"") -> Sherali Yusupov | C12: =IFERROR(INDEX(Customers!$F$4:$F$1003,MATCH($A12,Customers!$A$4:$A$1003,0)),"") -> Czech Republic | D12: Yes | E12: Yes | F12: Yes | G12: Yes | H12: Yes | I12: Yes | J12: Yes | K12: Yes | L12: No | M12: No | N12: Yes | O12: =IF($A12="","",COUNTIF($D12:$N12,"Yes")) -> 9 | P12: =IF($A12="","",COUNTA($D$3:$N$3)) -> 11 | Q12: =IF($A12="","",IFERROR($O12/$P12,"")) -> 0.81818182 | R12: =IF($A12="","",IF($Q12=1,"Complete",IF($Q12>=0.7,"Almost Complete",IF($Q12>0,"In Progress","Not Started")))) -> Almost Complete | S12: Bakhtiyor Umarov | T12: 46233
A13: CUS-010 | B13: =IFERROR(INDEX(Customers!$C$4:$C$1003,MATCH($A13,Customers!$A$4:$A$1003,0)),"") -> Malika Ismoilova | C13: =IFERROR(INDEX(Customers!$F$4:$F$1003,MATCH($A13,Customers!$A$4:$A$1003,0)),"") -> Poland | D13: Yes | E13: Yes | F13: Yes | G13: Yes | H13: Yes | I13: Yes | J13: Yes | K13: Yes | L13: No | M13: No | N13: Yes | O13: =IF($A13="","",COUNTIF($D13:$N13,"Yes")) -> 9 | P13: =IF($A13="","",COUNTA($D$3:$N$3)) -> 11 | Q13: =IF($A13="","",IFERROR($O13/$P13,"")) -> 0.81818182 | R13: =IF($A13="","",IF($Q13=1,"Complete",IF($Q13>=0.7,"Almost Complete",IF($Q13>0,"In Progress","Not Started")))) -> Almost Complete | S13: Bakhtiyor Umarov | T13: 46233
A14: CUS-011 | B14: =IFERROR(INDEX(Customers!$C$4:$C$1003,MATCH($A14,Customers!$A$4:$A$1003,0)),"") -> Farrukh Davlatov | C14: =IFERROR(INDEX(Customers!$F$4:$F$1003,MATCH($A14,Customers!$A$4:$A$1003,0)),"") -> Hungary | D14: Yes | E14: Yes | F14: Yes | G14: Yes | H14: Yes | I14: Yes | J14: No | K14: No | L14: No | M14: No | N14: Yes | O14: =IF($A14="","",COUNTIF($D14:$N14,"Yes")) -> 7 | P14: =IF($A14="","",COUNTA($D$3:$N$3)) -> 11 | Q14: =IF($A14="","",IFERROR($O14/$P14,"")) -> 0.63636364 | R14: =IF($A14="","",IF($Q14=1,"Complete",IF($Q14>=0.7,"Almost Complete",IF($Q14>0,"In Progress","Not Started")))) -> In Progress | S14: Bakhtiyor Umarov | T14: 46233
A15: CUS-012 | B15: =IFERROR(INDEX(Customers!$C$4:$C$1003,MATCH($A15,Customers!$A$4:$A$1003,0)),"") -> Gulnora Safarova | C15: =IFERROR(INDEX(Customers!$F$4:$F$1003,MATCH($A15,Customers!$A$4:$A$1003,0)),"") -> Romania | D15: Yes | E15: Yes | F15: Yes | G15: Yes | H15: No | I15: No | J15: No | K15: No | L15: No | M15: No | N15: No | O15: =IF($A15="","",COUNTIF($D15:$N15,"Yes")) -> 4 | P15: =IF($A15="","",COUNTA($D$3:$N$3)) -> 11 | Q15: =IF($A15="","",IFERROR($O15/$P15,"")) -> 0.36363636 | R15: =IF($A15="","",IF($Q15=1,"Complete",IF($Q15>=0.7,"Almost Complete",IF($Q15>0,"In Progress","Not Started")))) -> In Progress | S15: Bakhtiyor Umarov | T15: 46233
B16: =IFERROR(INDEX(Customers!$C$4:$C$1003,MATCH($A16,Customers!$A$4:$A$1003,0)),"") | C16: =IFERROR(INDEX(Customers!$F$4:$F$1003,MATCH($A16,Customers!$A$4:$A$1003,0)),"") | O16: =IF($A16="","",COUNTIF($D16:$N16,"Yes")) | P16: =IF($A16="","",COUNTA($D$3:$N$3)) | Q16: =IF($A16="","",IFERROR($O16/$P16,"")) | R16: =IF($A16="","",IF($Q16=1,"Complete",IF($Q16>=0.7,"Almost Complete",IF($Q16>0,"In Progress","Not Started"))))
B17: =IFERROR(INDEX(Customers!$C$4:$C$1003,MATCH($A17,Customers!$A$4:$A$1003,0)),"") | C17: =IFERROR(INDEX(Customers!$F$4:$F$1003,MATCH($A17,Customers!$A$4:$A$1003,0)),"") | O17: =IF($A17="","",COUNTIF($D17:$N17,"Yes")) | P17: =IF($A17="","",COUNTA($D$3:$N$3)) | Q17: =IF($A17="","",IFERROR($O17/$P17,"")) | R17: =IF($A17="","",IF($Q17=1,"Complete",IF($Q17>=0.7,"Almost Complete",IF($Q17>0,"In Progress","Not Started"))))
B18: =IFERROR(INDEX(Customers!$C$4:$C$1003,MATCH($A18,Customers!$A$4:$A$1003,0)),"") | C18: =IFERROR(INDEX(Customers!$F$4:$F$1003,MATCH($A18,Customers!$A$4:$A$1003,0)),"") | O18: =IF($A18="","",COUNTIF($D18:$N18,"Yes")) | P18: =IF($A18="","",COUNTA($D$3:$N$3)) | Q18: =IF($A18="","",IFERROR($O18/$P18,"")) | R18: =IF($A18="","",IF($Q18=1,"Complete",IF($Q18>=0.7,"Almost Complete",IF($Q18>0,"In Progress","Not Started"))))
B19: =IFERROR(INDEX(Customers!$C$4:$C$1003,MATCH($A19,Customers!$A$4:$A$1003,0)),"") | C19: =IFERROR(INDEX(Customers!$F$4:$F$1003,MATCH($A19,Customers!$A$4:$A$1003,0)),"") | O19: =IF($A19="","",COUNTIF($D19:$N19,"Yes")) | P19: =IF($A19="","",COUNTA($D$3:$N$3)) | Q19: =IF($A19="","",IFERROR($O19/$P19,"")) | R19: =IF($A19="","",IF($Q19=1,"Complete",IF($Q19>=0.7,"Almost Complete",IF($Q19>0,"In Progress","Not Started"))))
B20: =IFERROR(INDEX(Customers!$C$4:$C$1003,MATCH($A20,Customers!$A$4:$A$1003,0)),"") | C20: =IFERROR(INDEX(Customers!$F$4:$F$1003,MATCH($A20,Customers!$A$4:$A$1003,0)),"") | O20: =IF($A20="","",COUNTIF($D20:$N20,"Yes")) | P20: =IF($A20="","",COUNTA($D$3:$N$3)) | Q20: =IF($A20="","",IFERROR($O20/$P20,"")) | R20: =IF($A20="","",IF($Q20=1,"Complete",IF($Q20>=0.7,"Almost Complete",IF($Q20>0,"In Progress","Not Started"))))
B21: =IFERROR(INDEX(Customers!$C$4:$C$1003,MATCH($A21,Customers!$A$4:$A$1003,0)),"") | C21: =IFERROR(INDEX(Customers!$F$4:$F$1003,MATCH($A21,Customers!$A$4:$A$1003,0)),"") | O21: =IF($A21="","",COUNTIF($D21:$N21,"Yes")) | P21: =IF($A21="","",COUNTA($D$3:$N$3)) | Q21: =IF($A21="","",IFERROR($O21/$P21,"")) | R21: =IF($A21="","",IF($Q21=1,"Complete",IF($Q21>=0.7,"Almost Complete",IF($Q21>0,"In Progress","Not Started"))))
B22: =IFERROR(INDEX(Customers!$C$4:$C$1003,MATCH($A22,Customers!$A$4:$A$1003,0)),"") | C22: =IFERROR(INDEX(Customers!$F$4:$F$1003,MATCH($A22,Customers!$A$4:$A$1003,0)),"") | O22: =IF($A22="","",COUNTIF($D22:$N22,"Yes")) | P22: =IF($A22="","",COUNTA($D$3:$N$3)) | Q22: =IF($A22="","",IFERROR($O22/$P22,"")) | R22: =IF($A22="","",IF($Q22=1,"Complete",IF($Q22>=0.7,"Almost Complete",IF($Q22>0,"In Progress","Not Started"))))
B23: =IFERROR(INDEX(Customers!$C$4:$C$1003,MATCH($A23,Customers!$A$4:$A$1003,0)),"") | C23: =IFERROR(INDEX(Customers!$F$4:$F$1003,MATCH($A23,Customers!$A$4:$A$1003,0)),"") | O23: =IF($A23="","",COUNTIF($D23:$N23,"Yes")) | P23: =IF($A23="","",COUNTA($D$3:$N$3)) | Q23: =IF($A23="","",IFERROR($O23/$P23,"")) | R23: =IF($A23="","",IF($Q23=1,"Complete",IF($Q23>=0.7,"Almost Complete",IF($Q23>0,"In Progress","Not Started"))))
B24: =IFERROR(INDEX(Customers!$C$4:$C$1003,MATCH($A24,Customers!$A$4:$A$1003,0)),"") | C24: =IFERROR(INDEX(Customers!$F$4:$F$1003,MATCH($A24,Customers!$A$4:$A$1003,0)),"") | O24: =IF($A24="","",COUNTIF($D24:$N24,"Yes")) | P24: =IF($A24="","",COUNTA($D$3:$N$3)) | Q24: =IF($A24="","",IFERROR($O24/$P24,"")) | R24: =IF($A24="","",IF($Q24=1,"Complete",IF($Q24>=0.7,"Almost Complete",IF($Q24>0,"In Progress","Not Started"))))
B25: =IFERROR(INDEX(Customers!$C$4:$C$1003,MATCH($A25,Customers!$A$4:$A$1003,0)),"") | C25: =IFERROR(INDEX(Customers!$F$4:$F$1003,MATCH($A25,Customers!$A$4:$A$1003,0)),"") | O25: =IF($A25="","",COUNTIF($D25:$N25,"Yes")) | P25: =IF($A25="","",COUNTA($D$3:$N$3)) | Q25: =IF($A25="","",IFERROR($O25/$P25,"")) | R25: =IF($A25="","",IF($Q25=1,"Complete",IF($Q25>=0.7,"Almost Complete",IF($Q25>0,"In Progress","Not Started"))))
B26: =IFERROR(INDEX(Customers!$C$4:$C$1003,MATCH($A26,Customers!$A$4:$A$1003,0)),"") | C26: =IFERROR(INDEX(Customers!$F$4:$F$1003,MATCH($A26,Customers!$A$4:$A$1003,0)),"") | O26: =IF($A26="","",COUNTIF($D26:$N26,"Yes")) | P26: =IF($A26="","",COUNTA($D$3:$N$3)) | Q26: =IF($A26="","",IFERROR($O26/$P26,"")) | R26: =IF($A26="","",IF($Q26=1,"Complete",IF($Q26>=0.7,"Almost Complete",IF($Q26>0,"In Progress","Not Started"))))
B27: =IFERROR(INDEX(Customers!$C$4:$C$1003,MATCH($A27,Customers!$A$4:$A$1003,0)),"") | C27: =IFERROR(INDEX(Customers!$F$4:$F$1003,MATCH($A27,Customers!$A$4:$A$1003,0)),"") | O27: =IF($A27="","",COUNTIF($D27:$N27,"Yes")) | P27: =IF($A27="","",COUNTA($D$3:$N$3)) | Q27: =IF($A27="","",IFERROR($O27/$P27,"")) | R27: =IF($A27="","",IF($Q27=1,"Complete",IF($Q27>=0.7,"Almost Complete",IF($Q27>0,"In Progress","Not Started"))))
... B203: =IFERROR(INDEX(Customers!$C$4:$C$1003,MATCH($A203,Customers!$A$4:$A$1003,0)),"") | C203: =IFERROR(INDEX(Customers!$F$4:$F$1003,MATCH($A203,Customers!$A$4:$A$1003,0)),"") | O203: =IF($A203="","",COUNTIF($D203:$N203,"Yes")) | P203: =IF($A203="","",COUNTA($D$3:$N$3)) | Q203: =IF($A203="","",IFERROR($O203/$P203,"")) | R203: =IF($A203="","",IF($Q203=1,"Complete",IF($Q203>=0.7,"Almost Complete",IF($Q203>0,"In Progress","Not Started"))))

Sheet Employee Management
A1: VUSLAT RECRUITMENT COMPANY | EMPLOYEE MANAGEMENT
A2: Staff register. Leads, consultations, customers, revenue and commission are calculated from the operational sheets. The names in column B feed every employee drop-down in the workbook.
A3: Employee ID | B3: Full Name | C3: Role | D3: Department | E3: Phone | F3: Email | G3: Hire Date | H3: Employment Status | I3: Monthly Salary (TJS) | J3: Leads Assigned | K3: Consultations Handled | L3: Customers Managed | M3: Revenue Collected (TJS) | N3: Commission % | O3: Commission Earned (TJS) | P3: Conversion Rate | Q3: Notes
A4: EMP-001 | B4: Farrukh Rahmonov | C4: Director | D4: Management | E4: +992 90 111 2201 | F4: f.rahmonov@vuslat.tj | G4: 44958 | H4: Active | I4: 4000 | J4: =IF($B4="","",COUNTIF('Lead Management'!$Q$4:$Q$1003,$B4)) -> 0 | K4: =IF($B4="","",COUNTIF(Consultation!$G$4:$G$1003,$B4)) -> 0 | L4: =IF($B4="","",COUNTIF(Customers!$K$4:$K$1003,$B4)) -> 0 | M4: =IF($B4="","",SUMIF(Customers!$K$4:$K$1003,$B4,Customers!$M$4:$M$1003)) -> 0 | N4: 0 | O4: =IF($B4="","",$M4*$N4) -> 0 | P4: =IF(OR($B4="",$J4=0),"",$L4/$J4) | Q4: Owner of the company, signs every contract.
A5: EMP-002 | B5: Nilufar Karimova | C5: Sales Manager | D5: Sales | E5: +992 90 111 2202 | F5: n.karimova@vuslat.tj | G5: 45061 | H5: Active | I5: 2200 | J5: =IF($B5="","",COUNTIF('Lead Management'!$Q$4:$Q$1003,$B5)) -> 10 | K5: =IF($B5="","",COUNTIF(Consultation!$G$4:$G$1003,$B5)) -> 0 | L5: =IF($B5="","",COUNTIF(Customers!$K$4:$K$1003,$B5)) -> 4 | M5: =IF($B5="","",SUMIF(Customers!$K$4:$K$1003,$B5,Customers!$M$4:$M$1003)) -> 77000 | N5: 0.03 | O5: =IF($B5="","",$M5*$N5) -> 2310 | P5: =IF(OR($B5="",$J5=0),"",$L5/$J5) -> 0.4
A6: EMP-003 | B6: Jamshed Sattorov | C6: Sales Manager | D6: Sales | E6: +992 90 111 2203 | F6: j.sattorov@vuslat.tj | G6: 45301 | H6: Active | I6: 2200 | J6: =IF($B6="","",COUNTIF('Lead Management'!$Q$4:$Q$1003,$B6)) -> 10 | K6: =IF($B6="","",COUNTIF(Consultation!$G$4:$G$1003,$B6)) -> 0 | L6: =IF($B6="","",COUNTIF(Customers!$K$4:$K$1003,$B6)) -> 4 | M6: =IF($B6="","",SUMIF(Customers!$K$4:$K$1003,$B6,Customers!$M$4:$M$1003)) -> 77250 | N6: 0.03 | O6: =IF($B6="","",$M6*$N6) -> 2317.5 | P6: =IF(OR($B6="",$J6=0),"",$L6/$J6) -> 0.4
A7: EMP-004 | B7: Zarina Nazarova | C7: Consultant | D7: Consulting | E7: +992 90 111 2204 | F7: z.nazarova@vuslat.tj | G7: 45355 | H7: Active | I7: 2000 | J7: =IF($B7="","",COUNTIF('Lead Management'!$Q$4:$Q$1003,$B7)) -> 0 | K7: =IF($B7="","",COUNTIF(Consultation!$G$4:$G$1003,$B7)) -> 9 | L7: =IF($B7="","",COUNTIF(Customers!$K$4:$K$1003,$B7)) -> 0 | M7: =IF($B7="","",SUMIF(Customers!$K$4:$K$1003,$B7,Customers!$M$4:$M$1003)) -> 0 | N7: 0.02 | O7: =IF($B7="","",$M7*$N7) -> 0 | P7: =IF(OR($B7="",$J7=0),"",$L7/$J7)
A8: EMP-005 | B8: Bakhtiyor Umarov | C8: Document Specialist | D8: Operations | E8: +992 90 111 2205 | F8: b.umarov@vuslat.tj | G8: 45463 | H8: Active | I8: 1800 | J8: =IF($B8="","",COUNTIF('Lead Management'!$Q$4:$Q$1003,$B8)) -> 0 | K8: =IF($B8="","",COUNTIF(Consultation!$G$4:$G$1003,$B8)) -> 0 | L8: =IF($B8="","",COUNTIF(Customers!$K$4:$K$1003,$B8)) -> 0 | M8: =IF($B8="","",SUMIF(Customers!$K$4:$K$1003,$B8,Customers!$M$4:$M$1003)) -> 0 | N8: 0 | O8: =IF($B8="","",$M8*$N8) -> 0 | P8: =IF(OR($B8="",$J8=0),"",$L8/$J8)
A9: EMP-006 | B9: Manizha Sharipova | C9: Accountant | D9: Finance | E9: +992 90 111 2206 | F9: m.sharipova@vuslat.tj | G9: 45537 | H9: Active | I9: 2000 | J9: =IF($B9="","",COUNTIF('Lead Management'!$Q$4:$Q$1003,$B9)) -> 0 | K9: =IF($B9="","",COUNTIF(Consultation!$G$4:$G$1003,$B9)) -> 0 | L9: =IF($B9="","",COUNTIF(Customers!$K$4:$K$1003,$B9)) -> 0 | M9: =IF($B9="","",SUMIF(Customers!$K$4:$K$1003,$B9,Customers!$M$4:$M$1003)) -> 0 | N9: 0 | O9: =IF($B9="","",$M9*$N9) -> 0 | P9: =IF(OR($B9="",$J9=0),"",$L9/$J9)
A10: EMP-007 | B10: Rustam Qodirov | C10: Marketing Specialist | D10: Marketing | E10: +992 90 111 2207 | F10: r.qodirov@vuslat.tj | G10: 45705 | H10: Active | I10: 1800 | J10: =IF($B10="","",COUNTIF('Lead Management'!$Q$4:$Q$1003,$B10)) -> 0 | K10: =IF($B10="","",COUNTIF(Consultation!$G$4:$G$1003,$B10)) -> 0 | L10: =IF($B10="","",COUNTIF(Customers!$K$4:$K$1003,$B10)) -> 0 | M10: =IF($B10="","",SUMIF(Customers!$K$4:$K$1003,$B10,Customers!$M$4:$M$1003)) -> 0 | N10: 0 | O10: =IF($B10="","",$M10*$N10) -> 0 | P10: =IF(OR($B10="",$J10=0),"",$L10/$J10)
A11: EMP-008 | B11: Dilnoza Aliyeva | C11: Manager | D11: Operations | E11: +992 90 111 2208 | F11: d.aliyeva@vuslat.tj | G11: 45748 | H11: Active | I11: 3000 | J11: =IF($B11="","",COUNTIF('Lead Management'!$Q$4:$Q$1003,$B11)) -> 10 | K11: =IF($B11="","",COUNTIF(Consultation!$G$4:$G$1003,$B11)) -> 9 | L11: =IF($B11="","",COUNTIF(Customers!$K$4:$K$1003,$B11)) -> 4 | M11: =IF($B11="","",SUMIF(Customers!$K$4:$K$1003,$B11,Customers!$M$4:$M$1003)) -> 71000 | N11: 0.02 | O11: =IF($B11="","",$M11*$N11) -> 1420 | P11: =IF(OR($B11="",$J11=0),"",$L11/$J11) -> 0.4
J12: =IF($B12="","",COUNTIF('Lead Management'!$Q$4:$Q$1003,$B12)) | K12: =IF($B12="","",COUNTIF(Consultation!$G$4:$G$1003,$B12)) | L12: =IF($B12="","",COUNTIF(Customers!$K$4:$K$1003,$B12)) | M12: =IF($B12="","",SUMIF(Customers!$K$4:$K$1003,$B12,Customers!$M$4:$M$1003)) | O12: =IF($B12="","",$M12*$N12) | P12: =IF(OR($B12="",$J12=0),"",$L12/$J12)
J13: =IF($B13="","",COUNTIF('Lead Management'!$Q$4:$Q$1003,$B13)) | K13: =IF($B13="","",COUNTIF(Consultation!$G$4:$G$1003,$B13)) | L13: =IF($B13="","",COUNTIF(Customers!$K$4:$K$1003,$B13)) | M13: =IF($B13="","",SUMIF(Customers!$K$4:$K$1003,$B13,Customers!$M$4:$M$1003)) | O13: =IF($B13="","",$M13*$N13) | P13: =IF(OR($B13="",$J13=0),"",$L13/$J13)
J14: =IF($B14="","",COUNTIF('Lead Management'!$Q$4:$Q$1003,$B14)) | K14: =IF($B14="","",COUNTIF(Consultation!$G$4:$G$1003,$B14)) | L14: =IF($B14="","",COUNTIF(Customers!$K$4:$K$1003,$B14)) | M14: =IF($B14="","",SUMIF(Customers!$K$4:$K$1003,$B14,Customers!$M$4:$M$1003)) | O14: =IF($B14="","",$M14*$N14) | P14: =IF(OR($B14="",$J14=0),"",$L14/$J14)
J15: =IF($B15="","",COUNTIF('Lead Management'!$Q$4:$Q$1003,$B15)) | K15: =IF($B15="","",COUNTIF(Consultation!$G$4:$G$1003,$B15)) | L15: =IF($B15="","",COUNTIF(Customers!$K$4:$K$1003,$B15)) | M15: =IF($B15="","",SUMIF(Customers!$K$4:$K$1003,$B15,Customers!$M$4:$M$1003)) | O15: =IF($B15="","",$M15*$N15) | P15: =IF(OR($B15="",$J15=0),"",$L15/$J15)
J16: =IF($B16="","",COUNTIF('Lead Management'!$Q$4:$Q$1003,$B16)) | K16: =IF($B16="","",COUNTIF(Consultation!$G$4:$G$1003,$B16)) | L16: =IF($B16="","",COUNTIF(Customers!$K$4:$K$1003,$B16)) | M16: =IF($B16="","",SUMIF(Customers!$K$4:$K$1003,$B16,Customers!$M$4:$M$1003)) | O16: =IF($B16="","",$M16*$N16) | P16: =IF(OR($B16="",$J16=0),"",$L16/$J16)
J17: =IF($B17="","",COUNTIF('Lead Management'!$Q$4:$Q$1003,$B17)) | K17: =IF($B17="","",COUNTIF(Consultation!$G$4:$G$1003,$B17)) | L17: =IF($B17="","",COUNTIF(Customers!$K$4:$K$1003,$B17)) | M17: =IF($B17="","",SUMIF(Customers!$K$4:$K$1003,$B17,Customers!$M$4:$M$1003)) | O17: =IF($B17="","",$M17*$N17) | P17: =IF(OR($B17="",$J17=0),"",$L17/$J17)
J18: =IF($B18="","",COUNTIF('Lead Management'!$Q$4:$Q$1003,$B18)) | K18: =IF($B18="","",COUNTIF(Consultation!$G$4:$G$1003,$B18)) | L18: =IF($B18="","",COUNTIF(Customers!$K$4:$K$1003,$B18)) | M18: =IF($B18="","",SUMIF(Customers!$K$4:$K$1003,$B18,Customers!$M$4:$M$1003)) | O18: =IF($B18="","",$M18*$N18) | P18: =IF(OR($B18="",$J18=0),"",$L18/$J18)
J19: =IF($B19="","",COUNTIF('Lead Management'!$Q$4:$Q$1003,$B19)) | K19: =IF($B19="","",COUNTIF(Consultation!$G$4:$G$1003,$B19)) | L19: =IF($B19="","",COUNTIF(Customers!$K$4:$K$1003,$B19)) | M19: =IF($B19="","",SUMIF(Customers!$K$4:$K$1003,$B19,Customers!$M$4:$M$1003)) | O19: =IF($B19="","",$M19*$N19) | P19: =IF(OR($B19="",$J19=0),"",$L19/$J19)
J20: =IF($B20="","",COUNTIF('Lead Management'!$Q$4:$Q$1003,$B20)) | K20: =IF($B20="","",COUNTIF(Consultation!$G$4:$G$1003,$B20)) | L20: =IF($B20="","",COUNTIF(Customers!$K$4:$K$1003,$B20)) | M20: =IF($B20="","",SUMIF(Customers!$K$4:$K$1003,$B20,Customers!$M$4:$M$1003)) | O20: =IF($B20="","",$M20*$N20) | P20: =IF(OR($B20="",$J20=0),"",$L20/$J20)
J21: =IF($B21="","",COUNTIF('Lead Management'!$Q$4:$Q$1003,$B21)) | K21: =IF($B21="","",COUNTIF(Consultation!$G$4:$G$1003,$B21)) | L21: =IF($B21="","",COUNTIF(Customers!$K$4:$K$1003,$B21)) | M21: =IF($B21="","",SUMIF(Customers!$K$4:$K$1003,$B21,Customers!$M$4:$M$1003)) | O21: =IF($B21="","",$M21*$N21) | P21: =IF(OR($B21="",$J21=0),"",$L21/$J21)
J22: =IF($B22="","",COUNTIF('Lead Management'!$Q$4:$Q$1003,$B22)) | K22: =IF($B22="","",COUNTIF(Consultation!$G$4:$G$1003,$B22)) | L22: =IF($B22="","",COUNTIF(Customers!$K$4:$K$1003,$B22)) | M22: =IF($B22="","",SUMIF(Customers!$K$4:$K$1003,$B22,Customers!$M$4:$M$1003)) | O22: =IF($B22="","",$M22*$N22) | P22: =IF(OR($B22="",$J22=0),"",$L22/$J22)
J23: =IF($B23="","",COUNTIF('Lead Management'!$Q$4:$Q$1003,$B23)) | K23: =IF($B23="","",COUNTIF(Consultation!$G$4:$G$1003,$B23)) | L23: =IF($B23="","",COUNTIF(Customers!$K$4:$K$1003,$B23)) | M23: =IF($B23="","",SUMIF(Customers!$K$4:$K$1003,$B23,Customers!$M$4:$M$1003)) | O23: =IF($B23="","",$M23*$N23) | P23: =IF(OR($B23="",$J23=0),"",$L23/$J23)
... J203: =IF($B203="","",COUNTIF('Lead Management'!$Q$4:$Q$1003,$B203)) | K203: =IF($B203="","",COUNTIF(Consultation!$G$4:$G$1003,$B203)) | L203: =IF($B203="","",COUNTIF(Customers!$K$4:$K$1003,$B203)) | M203: =IF($B203="","",SUMIF(Customers!$K$4:$K$1003,$B203,Customers!$M$4:$M$1003)) | O203: =IF($B203="","",$M203*$N203) | P203: =IF(OR($B203="",$J203=0),"",$L203/$J203)

Sheet Marketing & Advertising
A1: VUSLAT RECRUITMENT COMPANY | MARKETING & ADVERTISING
A2: Leads, consultations, customers and revenue are attributed automatically to the campaign whose channel and date range match the lead registration date.
A3: Campaign ID | B3: Campaign Name | C3: Channel | D3: Start Date | E3: End Date | F3: Budget (TJS) | G3: Actual Spend (TJS) | H3: Impressions | I3: Clicks | J3: CTR | K3: Leads Generated | L3: Cost per Lead (TJS) | M3: Consultations | N3: Customers Converted | O3: Revenue Attributed (TJS) | P3: ROI | Q3: Lead to Customer Rate | R3: Campaign Status | S3: Notes
A4: CMP-001 | B4: Instagram - Winter Europe Jobs | C4: Instagram | D4: 46027 | E4: 46081 | F4: 4500 | G4: 4300 | H4: 182000 | I4: 5460 | J4: =IF(OR($A4="",$H4=0),"",$I4/$H4) -> 0.03 | K4: =IF($A4="","",COUNTIFS('Lead Management'!$O$4:$O$1003,$C4,'Lead Management'!$P$4:$P$1003,">="&$D4,'Lead Management'!$P$4:$P$1003,"<="&$E4)) -> 3 | L4: =IF(OR($A4="",$K4=0),"",$G4/$K4) -> 1433.3333 | M4: =IF($A4="","",COUNTIFS('Lead Management'!$O$4:$O$1003,$C4,'Lead Management'!$P$4:$P$1003,">="&$D4,'Lead Management'!$P$4:$P$1003,"<="&$E4,'Lead Management'!$V$4:$V$1003,"Yes")) -> 3 | N4: =IF($A4="","",COUNTIFS(Customers!$S$4:$S$1003,$C4,Customers!$T$4:$T$1003,">="&$D4,Customers!$T$4:$T$1003,"<="&$E4)) -> 3 | O4: =IF($A4="","",SUMIFS(Customers!$M$4:$M$1003,Customers!$S$4:$S$1003,$C4,Customers!$T$4:$T$1003,">="&$D4,Customers!$T$4:$T$1003,"<="&$E4)) -> 76000 | P4: =IF(OR($A4="",$G4=0),"",($O4-$G4)/$G4) -> 16.674419 | Q4: =IF(OR($A4="",$K4=0),"",$N4/$K4) -> 1 | R4: Completed | S4: Best performing winter campaign, 3 qualified leads.
A5: CMP-002 | B5: Instagram - Spring Poland Push | C5: Instagram | D5: 46082 | E5: 46142 | F5: 6000 | G5: 5850 | H5: 246000 | I5: 8610 | J5: =IF(OR($A5="",$H5=0),"",$I5/$H5) -> 0.035 | K5: =IF($A5="","",COUNTIFS('Lead Management'!$O$4:$O$1003,$C5,'Lead Management'!$P$4:$P$1003,">="&$D5,'Lead Management'!$P$4:$P$1003,"<="&$E5)) -> 4 | L5: =IF(OR($A5="",$K5=0),"",$G5/$K5) -> 1462.5 | M5: =IF($A5="","",COUNTIFS('Lead Management'!$O$4:$O$1003,$C5,'Lead Management'!$P$4:$P$1003,">="&$D5,'Lead Management'!$P$4:$P$1003,"<="&$E5,'Lead Management'!$V$4:$V$1003,"Yes")) -> 4 | N5: =IF($A5="","",COUNTIFS(Customers!$S$4:$S$1003,$C5,Customers!$T$4:$T$1003,">="&$D5,Customers!$T$4:$T$1003,"<="&$E5)) -> 3 | O5: =IF($A5="","",SUMIFS(Customers!$M$4:$M$1003,Customers!$S$4:$S$1003,$C5,Customers!$T$4:$T$1003,">="&$D5,Customers!$T$4:$T$1003,"<="&$E5)) -> 48750 | P5: =IF(OR($A5="",$G5=0),"",($O5-$G5)/$G5) -> 7.3333333 | Q5: =IF(OR($A5="",$K5=0),"",$N5/$K5) -> 0.75 | R5: Completed | S5: Targeted welders and construction workers in Sughd region.
A6: CMP-003 | B6: Facebook - Germany Welders | C6: Facebook | D6: 46054 | E6: 46127 | F6: 3200 | G6: 3050 | H6: 121000 | I6: 3388 | J6: =IF(OR($A6="",$H6=0),"",$I6/$H6) -> 0.028 | K6: =IF($A6="","",COUNTIFS('Lead Management'!$O$4:$O$1003,$C6,'Lead Management'!$P$4:$P$1003,">="&$D6,'Lead Management'!$P$4:$P$1003,"<="&$E6)) -> 3 | L6: =IF(OR($A6="",$K6=0),"",$G6/$K6) -> 1016.6667 | M6: =IF($A6="","",COUNTIFS('Lead Management'!$O$4:$O$1003,$C6,'Lead Management'!$P$4:$P$1003,">="&$D6,'Lead Management'!$P$4:$P$1003,"<="&$E6,'Lead Management'!$V$4:$V$1003,"Yes")) -> 3 | N6: =IF($A6="","",COUNTIFS(Customers!$S$4:$S$1003,$C6,Customers!$T$4:$T$1003,">="&$D6,Customers!$T$4:$T$1003,"<="&$E6)) -> 2 | O6: =IF($A6="","",SUMIFS(Customers!$M$4:$M$1003,Customers!$S$4:$S$1003,$C6,Customers!$T$4:$T$1003,">="&$D6,Customers!$T$4:$T$1003,"<="&$E6)) -> 37500 | P6: =IF(OR($A6="",$G6=0),"",($O6-$G6)/$G6) -> 11.295082 | Q6: =IF(OR($A6="",$K6=0),"",$N6/$K6) -> 0.66666667 | R6: Completed | S6: Higher cost per lead than Instagram.
A7: CMP-004 | B7: Website SEO & Landing Page | C7: Website | D7: 46023 | E7: 46234 | F7: 2800 | G7: 2400 | H7: 64000 | I7: 2560 | J7: =IF(OR($A7="",$H7=0),"",$I7/$H7) -> 0.04 | K7: =IF($A7="","",COUNTIFS('Lead Management'!$O$4:$O$1003,$C7,'Lead Management'!$P$4:$P$1003,">="&$D7,'Lead Management'!$P$4:$P$1003,"<="&$E7)) -> 5 | L7: =IF(OR($A7="",$K7=0),"",$G7/$K7) -> 480 | M7: =IF($A7="","",COUNTIFS('Lead Management'!$O$4:$O$1003,$C7,'Lead Management'!$P$4:$P$1003,">="&$D7,'Lead Management'!$P$4:$P$1003,"<="&$E7,'Lead Management'!$V$4:$V$1003,"Yes")) -> 3 | N7: =IF($A7="","",COUNTIFS(Customers!$S$4:$S$1003,$C7,Customers!$T$4:$T$1003,">="&$D7,Customers!$T$4:$T$1003,"<="&$E7)) -> 2 | O7: =IF($A7="","",SUMIFS(Customers!$M$4:$M$1003,Customers!$S$4:$S$1003,$C7,Customers!$T$4:$T$1003,">="&$D7,Customers!$T$4:$T$1003,"<="&$E7)) -> 29500 | P7: =IF(OR($A7="",$G7=0),"",($O7-$G7)/$G7) -> 11.291667 | Q7: =IF(OR($A7="",$K7=0),"",$N7/$K7) -> 0.4 | R7: Active | S7: Organic search traffic, cheapest channel.
A8: CMP-005 | B8: Referral Bonus Program | C8: Referral | D8: 46054 | E8: 46234 | F8: 1500 | G8: 1400 | H8: 0 | I8: 0 | J8: =IF(OR($A8="",$H8=0),"",$I8/$H8) | K8: =IF($A8="","",COUNTIFS('Lead Management'!$O$4:$O$1003,$C8,'Lead Management'!$P$4:$P$1003,">="&$D8,'Lead Management'!$P$4:$P$1003,"<="&$E8)) -> 4 | L8: =IF(OR($A8="",$K8=0),"",$G8/$K8) -> 350 | M8: =IF($A8="","",COUNTIFS('Lead Management'!$O$4:$O$1003,$C8,'Lead Management'!$P$4:$P$1003,">="&$D8,'Lead Management'!$P$4:$P$1003,"<="&$E8,'Lead Management'!$V$4:$V$1003,"Yes")) -> 2 | N8: =IF($A8="","",COUNTIFS(Customers!$S$4:$S$1003,$C8,Customers!$T$4:$T$1003,">="&$D8,Customers!$T$4:$T$1003,"<="&$E8)) -> 2 | O8: =IF($A8="","",SUMIFS(Customers!$M$4:$M$1003,Customers!$S$4:$S$1003,$C8,Customers!$T$4:$T$1003,">="&$D8,Customers!$T$4:$T$1003,"<="&$E8)) -> 33500 | P8: =IF(OR($A8="",$G8=0),"",($O8-$G8)/$G8) -> 22.928571 | Q8: =IF(OR($A8="",$K8=0),"",$N8/$K8) -> 0.5 | R8: Active | S8: 150 TJS bonus paid for every referral that signs a contract.
A9: CMP-006 | B9: Instagram - Summer Reels | C9: Instagram | D9: 46143 | E9: 46234 | F9: 5200 | G9: 2300 | H9: 158000 | I9: 6320 | J9: =IF(OR($A9="",$H9=0),"",$I9/$H9) -> 0.04 | K9: =IF($A9="","",COUNTIFS('Lead Management'!$O$4:$O$1003,$C9,'Lead Management'!$P$4:$P$1003,">="&$D9,'Lead Management'!$P$4:$P$1003,"<="&$E9)) -> 8 | L9: =IF(OR($A9="",$K9=0),"",$G9/$K9) -> 287.5 | M9: =IF($A9="","",COUNTIFS('Lead Management'!$O$4:$O$1003,$C9,'Lead Management'!$P$4:$P$1003,">="&$D9,'Lead Management'!$P$4:$P$1003,"<="&$E9,'Lead Management'!$V$4:$V$1003,"Yes")) -> 2 | N9: =IF($A9="","",COUNTIFS(Customers!$S$4:$S$1003,$C9,Customers!$T$4:$T$1003,">="&$D9,Customers!$T$4:$T$1003,"<="&$E9)) -> 0 | O9: =IF($A9="","",SUMIFS(Customers!$M$4:$M$1003,Customers!$S$4:$S$1003,$C9,Customers!$T$4:$T$1003,">="&$D9,Customers!$T$4:$T$1003,"<="&$E9)) -> 0 | P9: =IF(OR($A9="",$G9=0),"",($O9-$G9)/$G9) -> -1 | Q9: =IF(OR($A9="",$K9=0),"",$N9/$K9) -> 0 | R9: Active | S9: Short video format, campaign still running.
J10: =IF(OR($A10="",$H10=0),"",$I10/$H10) | K10: =IF($A10="","",COUNTIFS('Lead Management'!$O$4:$O$1003,$C10,'Lead Management'!$P$4:$P$1003,">="&$D10,'Lead Management'!$P$4:$P$1003,"<="&$E10)) | L10: =IF(OR($A10="",$K10=0),"",$G10/$K10) | M10: =IF($A10="","",COUNTIFS('Lead Management'!$O$4:$O$1003,$C10,'Lead Management'!$P$4:$P$1003,">="&$D10,'Lead Management'!$P$4:$P$1003,"<="&$E10,'Lead Management'!$V$4:$V$1003,"Yes")) | N10: =IF($A10="","",COUNTIFS(Customers!$S$4:$S$1003,$C10,Customers!$T$4:$T$1003,">="&$D10,Customers!$T$4:$T$1003,"<="&$E10)) | O10: =IF($A10="","",SUMIFS(Customers!$M$4:$M$1003,Customers!$S$4:$S$1003,$C10,Customers!$T$4:$T$1003,">="&$D10,Customers!$T$4:$T$1003,"<="&$E10)) | P10: =IF(OR($A10="",$G10=0),"",($O10-$G10)/$G10) | Q10: =IF(OR($A10="",$K10=0),"",$N10/$K10)
J11: =IF(OR($A11="",$H11=0),"",$I11/$H11) | K11: =IF($A11="","",COUNTIFS('Lead Management'!$O$4:$O$1003,$C11,'Lead Management'!$P$4:$P$1003,">="&$D11,'Lead Management'!$P$4:$P$1003,"<="&$E11)) | L11: =IF(OR($A11="",$K11=0),"",$G11/$K11) | M11: =IF($A11="","",COUNTIFS('Lead Management'!$O$4:$O$1003,$C11,'Lead Management'!$P$4:$P$1003,">="&$D11,'Lead Management'!$P$4:$P$1003,"<="&$E11,'Lead Management'!$V$4:$V$1003,"Yes")) | N11: =IF($A11="","",COUNTIFS(Customers!$S$4:$S$1003,$C11,Customers!$T$4:$T$1003,">="&$D11,Customers!$T$4:$T$1003,"<="&$E11)) | O11: =IF($A11="","",SUMIFS(Customers!$M$4:$M$1003,Customers!$S$4:$S$1003,$C11,Customers!$T$4:$T$1003,">="&$D11,Customers!$T$4:$T$1003,"<="&$E11)) | P11: =IF(OR($A11="",$G11=0),"",($O11-$G11)/$G11) | Q11: =IF(OR($A11="",$K11=0),"",$N11/$K11)
J12: =IF(OR($A12="",$H12=0),"",$I12/$H12) | K12: =IF($A12="","",COUNTIFS('Lead Management'!$O$4:$O$1003,$C12,'Lead Management'!$P$4:$P$1003,">="&$D12,'Lead Management'!$P$4:$P$1003,"<="&$E12)) | L12: =IF(OR($A12="",$K12=0),"",$G12/$K12) | M12: =IF($A12="","",COUNTIFS('Lead Management'!$O$4:$O$1003,$C12,'Lead Management'!$P$4:$P$1003,">="&$D12,'Lead Management'!$P$4:$P$1003,"<="&$E12,'Lead Management'!$V$4:$V$1003,"Yes")) | N12: =IF($A12="","",COUNTIFS(Customers!$S$4:$S$1003,$C12,Customers!$T$4:$T$1003,">="&$D12,Customers!$T$4:$T$1003,"<="&$E12)) | O12: =IF($A12="","",SUMIFS(Customers!$M$4:$M$1003,Customers!$S$4:$S$1003,$C12,Customers!$T$4:$T$1003,">="&$D12,Customers!$T$4:$T$1003,"<="&$E12)) | P12: =IF(OR($A12="",$G12=0),"",($O12-$G12)/$G12) | Q12: =IF(OR($A12="",$K12=0),"",$N12/$K12)
J13: =IF(OR($A13="",$H13=0),"",$I13/$H13) | K13: =IF($A13="","",COUNTIFS('Lead Management'!$O$4:$O$1003,$C13,'Lead Management'!$P$4:$P$1003,">="&$D13,'Lead Management'!$P$4:$P$1003,"<="&$E13)) | L13: =IF(OR($A13="",$K13=0),"",$G13/$K13) | M13: =IF($A13="","",COUNTIFS('Lead Management'!$O$4:$O$1003,$C13,'Lead Management'!$P$4:$P$1003,">="&$D13,'Lead Management'!$P$4:$P$1003,"<="&$E13,'Lead Management'!$V$4:$V$1003,"Yes")) | N13: =IF($A13="","",COUNTIFS(Customers!$S$4:$S$1003,$C13,Customers!$T$4:$T$1003,">="&$D13,Customers!$T$4:$T$1003,"<="&$E13)) | O13: =IF($A13="","",SUMIFS(Customers!$M$4:$M$1003,Customers!$S$4:$S$1003,$C13,Customers!$T$4:$T$1003,">="&$D13,Customers!$T$4:$T$1003,"<="&$E13)) | P13: =IF(OR($A13="",$G13=0),"",($O13-$G13)/$G13) | Q13: =IF(OR($A13="",$K13=0),"",$N13/$K13)
J14: =IF(OR($A14="",$H14=0),"",$I14/$H14) | K14: =IF($A14="","",COUNTIFS('Lead Management'!$O$4:$O$1003,$C14,'Lead Management'!$P$4:$P$1003,">="&$D14,'Lead Management'!$P$4:$P$1003,"<="&$E14)) | L14: =IF(OR($A14="",$K14=0),"",$G14/$K14) | M14: =IF($A14="","",COUNTIFS('Lead Management'!$O$4:$O$1003,$C14,'Lead Management'!$P$4:$P$1003,">="&$D14,'Lead Management'!$P$4:$P$1003,"<="&$E14,'Lead Management'!$V$4:$V$1003,"Yes")) | N14: =IF($A14="","",COUNTIFS(Customers!$S$4:$S$1003,$C14,Customers!$T$4:$T$1003,">="&$D14,Customers!$T$4:$T$1003,"<="&$E14)) | O14: =IF($A14="","",SUMIFS(Customers!$M$4:$M$1003,Customers!$S$4:$S$1003,$C14,Customers!$T$4:$T$1003,">="&$D14,Customers!$T$4:$T$1003,"<="&$E14)) | P14: =IF(OR($A14="",$G14=0),"",($O14-$G14)/$G14) | Q14: =IF(OR($A14="",$K14=0),"",$N14/$K14)
J15: =IF(OR($A15="",$H15=0),"",$I15/$H15) | K15: =IF($A15="","",COUNTIFS('Lead Management'!$O$4:$O$1003,$C15,'Lead Management'!$P$4:$P$1003,">="&$D15,'Lead Management'!$P$4:$P$1003,"<="&$E15)) | L15: =IF(OR($A15="",$K15=0),"",$G15/$K15) | M15: =IF($A15="","",COUNTIFS('Lead Management'!$O$4:$O$1003,$C15,'Lead Management'!$P$4:$P$1003,">="&$D15,'Lead Management'!$P$4:$P$1003,"<="&$E15,'Lead Management'!$V$4:$V$1003,"Yes")) | N15: =IF($A15="","",COUNTIFS(Customers!$S$4:$S$1003,$C15,Customers!$T$4:$T$1003,">="&$D15,Customers!$T$4:$T$1003,"<="&$E15)) | O15: =IF($A15="","",SUMIFS(Customers!$M$4:$M$1003,Customers!$S$4:$S$1003,$C15,Customers!$T$4:$T$1003,">="&$D15,Customers!$T$4:$T$1003,"<="&$E15)) | P15: =IF(OR($A15="",$G15=0),"",($O15-$G15)/$G15) | Q15: =IF(OR($A15="",$K15=0),"",$N15/$K15)
